Workbook

Sheet 📊 Dashboard
A1: Anubis v6.1 — Threat Intelligence Dashboard
A2: Generated: 2026-02-26 00:15 | By Ramiz Alsafi | J2: Risk Level | K2: Count
A3: Threat Type | B3: Total | C3: P1 (Urgent) | D3: P2 (High) | E3: KEV Active | F3: Critical | G3: High | J3: CRITICAL | K3: =COUNTIF('Threat Intelligence'!$H:$H,"CRITICAL")
A4: ABUSE_IP | B4: =COUNTIF('Threat Intelligence'!$A:$A,A4) | C4: =COUNTIFS('Threat Intelligence'!$A:$A,A4,'Threat Intelligence'!$Q:$Q,"P1") | D4: =COUNTIFS('Threat Intelligence'!$A:$A,A4,'Threat Intelligence'!$Q:$Q,"P2") | E4: =COUNTIFS('Threat Intelligence'!$A:$A,A4,'Threat Intelligence'!$J:$J,"YES") | F4: =COUNTIFS('Threat Intelligence'!$A:$A,A4,'Threat Intelligence'!$E:$E,"CRITICAL") | G4: =COUNTIFS('Threat Intelligence'!$A:$A,A4,'Threat Intelligence'!$E:$E,"HIGH") | J4: HIGH | K4: =COUNTIF('Threat Intelligence'!$H:$H,"HIGH")
A5: BLOCKLIST_DE | B5: =COUNTIF('Threat Intelligence'!$A:$A,A5) | C5: =COUNTIFS('Threat Intelligence'!$A:$A,A5,'Threat Intelligence'!$Q:$Q,"P1") | D5: =COUNTIFS('Threat Intelligence'!$A:$A,A5,'Threat Intelligence'!$Q:$Q,"P2") | E5: =COUNTIFS('Threat Intelligence'!$A:$A,A5,'Threat Intelligence'!$J:$J,"YES") | F5: =COUNTIFS('Threat Intelligence'!$A:$A,A5,'Threat Intelligence'!$E:$E,"CRITICAL") | G5: =COUNTIFS('Threat Intelligence'!$A:$A,A5,'Threat Intelligence'!$E:$E,"HIGH") | J5: MEDIUM | K5: =COUNTIF('Threat Intelligence'!$H:$H,"MEDIUM")
A6: CENSYS_EXPOSED | B6: =COUNTIF('Threat Intelligence'!$A:$A,A6) | C6: =COUNTIFS('Threat Intelligence'!$A:$A,A6,'Threat Intelligence'!$Q:$Q,"P1") | D6: =COUNTIFS('Threat Intelligence'!$A:$A,A6,'Threat Intelligence'!$Q:$Q,"P2") | E6: =COUNTIFS('Threat Intelligence'!$A:$A,A6,'Threat Intelligence'!$J:$J,"YES") | F6: =COUNTIFS('Threat Intelligence'!$A:$A,A6,'Threat Intelligence'!$E:$E,"CRITICAL") | G6: =COUNTIFS('Threat Intelligence'!$A:$A,A6,'Threat Intelligence'!$E:$E,"HIGH") | J6: LOW | K6: =COUNTIF('Threat Intelligence'!$H:$H,"LOW")
A7: CVE | B7: =COUNTIF('Threat Intelligence'!$A:$A,A7) | C7: =COUNTIFS('Threat Intelligence'!$A:$A,A7,'Threat Intelligence'!$Q:$Q,"P1") | D7: =COUNTIFS('Threat Intelligence'!$A:$A,A7,'Threat Intelligence'!$Q:$Q,"P2") | E7: =COUNTIFS('Threat Intelligence'!$A:$A,A7,'Threat Intelligence'!$J:$J,"YES") | F7: =COUNTIFS('Threat Intelligence'!$A:$A,A7,'Threat Intelligence'!$E:$E,"CRITICAL") | G7: =COUNTIFS('Threat Intelligence'!$A:$A,A7,'Threat Intelligence'!$E:$E,"HIGH") | J7: Priority | K7: Count
A8: EMERGING_THREAT_IP | B8: =COUNTIF('Threat Intelligence'!$A:$A,A8) | C8: =COUNTIFS('Threat Intelligence'!$A:$A,A8,'Threat Intelligence'!$Q:$Q,"P1") | D8: =COUNTIFS('Threat Intelligence'!$A:$A,A8,'Threat Intelligence'!$Q:$Q,"P2") | E8: =COUNTIFS('Threat Intelligence'!$A:$A,A8,'Threat Intelligence'!$J:$J,"YES") | F8: =COUNTIFS('Threat Intelligence'!$A:$A,A8,'Threat Intelligence'!$E:$E,"CRITICAL") | G8: =COUNTIFS('Threat Intelligence'!$A:$A,A8,'Threat Intelligence'!$E:$E,"HIGH") | J8: P1 | K8: =COUNTIF('Threat Intelligence'!$Q:$Q,"P1")
A9: EXPLOIT | B9: =COUNTIF('Threat Intelligence'!$A:$A,A9) | C9: =COUNTIFS('Threat Intelligence'!$A:$A,A9,'Threat Intelligence'!$Q:$Q,"P1") | D9: =COUNTIFS('Threat Intelligence'!$A:$A,A9,'Threat Intelligence'!$Q:$Q,"P2") | E9: =COUNTIFS('Threat Intelligence'!$A:$A,A9,'Threat Intelligence'!$J:$J,"YES") | F9: =COUNTIFS('Threat Intelligence'!$A:$A,A9,'Threat Intelligence'!$E:$E,"CRITICAL") | G9: =COUNTIFS('Threat Intelligence'!$A:$A,A9,'Threat Intelligence'!$E:$E,"HIGH") | J9: P2 | K9: =COUNTIF('Threat Intelligence'!$Q:$Q,"P2")
A10: FEODO_C2 | B10: =COUNTIF('Threat Intelligence'!$A:$A,A10) | C10: =COUNTIFS('Threat Intelligence'!$A:$A,A10,'Threat Intelligence'!$Q:$Q,"P1") | D10: =COUNTIFS('Threat Intelligence'!$A:$A,A10,'Threat Intelligence'!$Q:$Q,"P2") | E10: =COUNTIFS('Threat Intelligence'!$A:$A,A10,'Threat Intelligence'!$J:$J,"YES") | F10: =COUNTIFS('Threat Intelligence'!$A:$A,A10,'Threat Intelligence'!$E:$E,"CRITICAL") | G10: =COUNTIFS('Threat Intelligence'!$A:$A,A10,'Threat Intelligence'!$E:$E,"HIGH") | J10: P3 | K10: =COUNTIF('Threat Intelligence'!$Q:$Q,"P3")
A11: FIREHOL_THREAT | B11: =COUNTIF('Threat Intelligence'!$A:$A,A11) | C11: =COUNTIFS('Threat Intelligence'!$A:$A,A11,'Threat Intelligence'!$Q:$Q,"P1") | D11: =COUNTIFS('Threat Intelligence'!$A:$A,A11,'Threat Intelligence'!$Q:$Q,"P2") | E11: =COUNTIFS('Threat Intelligence'!$A:$A,A11,'Threat Intelligence'!$J:$J,"YES") | F11: =COUNTIFS('Threat Intelligence'!$A:$A,A11,'Threat Intelligence'!$E:$E,"CRITICAL") | G11: =COUNTIFS('Threat Intelligence'!$A:$A,A11,'Threat Intelligence'!$E:$E,"HIGH") | J11: P4 | K11: =COUNTIF('Threat Intelligence'!$Q:$Q,"P4")
A12: FIREWALL_ADVISORY | B12: =COUNTIF('Threat Intelligence'!$A:$A,A12) | C12: =COUNTIFS('Threat Intelligence'!$A:$A,A12,'Threat Intelligence'!$Q:$Q,"P1") | D12: =COUNTIFS('Threat Intelligence'!$A:$A,A12,'Threat Intelligence'!$Q:$Q,"P2") | E12: =COUNTIFS('Threat Intelligence'!$A:$A,A12,'Threat Intelligence'!$J:$J,"YES") | F12: =COUNTIFS('Threat Intelligence'!$A:$A,A12,'Threat Intelligence'!$E:$E,"CRITICAL") | G12: =COUNTIFS('Threat Intelligence'!$A:$A,A12,'Threat Intelligence'!$E:$E,"HIGH") | J12: Threat Type | K12: Count
A13: GH_ADVISORY | B13: =COUNTIF('Threat Intelligence'!$A:$A,A13) | C13: =COUNTIFS('Threat Intelligence'!$A:$A,A13,'Threat Intelligence'!$Q:$Q,"P1") | D13: =COUNTIFS('Threat Intelligence'!$A:$A,A13,'Threat Intelligence'!$Q:$Q,"P2") | E13: =COUNTIFS('Threat Intelligence'!$A:$A,A13,'Threat Intelligence'!$J:$J,"YES") | F13: =COUNTIFS('Threat Intelligence'!$A:$A,A13,'Threat Intelligence'!$E:$E,"CRITICAL") | G13: =COUNTIFS('Threat Intelligence'!$A:$A,A13,'Threat Intelligence'!$E:$E,"HIGH") | J13: =A4 | K13: =B4
A14: MAL_URL | B14: =COUNTIF('Threat Intelligence'!$A:$A,A14) | C14: =COUNTIFS('Threat Intelligence'!$A:$A,A14,'Threat Intelligence'!$Q:$Q,"P1") | D14: =COUNTIFS('Threat Intelligence'!$A:$A,A14,'Threat Intelligence'!$Q:$Q,"P2") | E14: =COUNTIFS('Threat Intelligence'!$A:$A,A14,'Threat Intelligence'!$J:$J,"YES") | F14: =COUNTIFS('Threat Intelligence'!$A:$A,A14,'Threat Intelligence'!$E:$E,"CRITICAL") | G14: =COUNTIFS('Threat Intelligence'!$A:$A,A14,'Threat Intelligence'!$E:$E,"HIGH") | J14: =A5 | K14: =B5
A15: MSF_MODULE | B15: =COUNTIF('Threat Intelligence'!$A:$A,A15) | C15: =COUNTIFS('Threat Intelligence'!$A:$A,A15,'Threat Intelligence'!$Q:$Q,"P1") | D15: =COUNTIFS('Threat Intelligence'!$A:$A,A15,'Threat Intelligence'!$Q:$Q,"P2") | E15: =COUNTIFS('Threat Intelligence'!$A:$A,A15,'Threat Intelligence'!$J:$J,"YES") | F15: =COUNTIFS('Threat Intelligence'!$A:$A,A15,'Threat Intelligence'!$E:$E,"CRITICAL") | G15: =COUNTIFS('Threat Intelligence'!$A:$A,A15,'Threat Intelligence'!$E:$E,"HIGH") | J15: =A6 | K15: =B6
A16: MSRC_UPDATE | B16: =COUNTIF('Threat Intelligence'!$A:$A,A16) | C16: =COUNTIFS('Threat Intelligence'!$A:$A,A16,'Threat Intelligence'!$Q:$Q,"P1") | D16: =COUNTIFS('Threat Intelligence'!$A:$A,A16,'Threat Intelligence'!$Q:$Q,"P2") | E16: =COUNTIFS('Threat Intelligence'!$A:$A,A16,'Threat Intelligence'!$J:$J,"YES") | F16: =COUNTIFS('Threat Intelligence'!$A:$A,A16,'Threat Intelligence'!$E:$E,"CRITICAL") | G16: =COUNTIFS('Threat Intelligence'!$A:$A,A16,'Threat Intelligence'!$E:$E,"HIGH") | J16: =A7 | K16: =B7
A17: NEWS_ALERT | B17: =COUNTIF('Threat Intelligence'!$A:$A,A17) | C17: =COUNTIFS('Threat Intelligence'!$A:$A,A17,'Threat Intelligence'!$Q:$Q,"P1") | D17: =COUNTIFS('Threat Intelligence'!$A:$A,A17,'Threat Intelligence'!$Q:$Q,"P2") | E17: =COUNTIFS('Threat Intelligence'!$A:$A,A17,'Threat Intelligence'!$J:$J,"YES") | F17: =COUNTIFS('Threat Intelligence'!$A:$A,A17,'Threat Intelligence'!$E:$E,"CRITICAL") | G17: =COUNTIFS('Threat Intelligence'!$A:$A,A17,'Threat Intelligence'!$E:$E,"HIGH") | J17: =A8 | K17: =B8
A18: OTX_PULSE | B18: =COUNTIF('Threat Intelligence'!$A:$A,A18) | C18: =COUNTIFS('Threat Intelligence'!$A:$A,A18,'Threat Intelligence'!$Q:$Q,"P1") | D18: =COUNTIFS('Threat Intelligence'!$A:$A,A18,'Threat Intelligence'!$Q:$Q,"P2") | E18: =COUNTIFS('Threat Intelligence'!$A:$A,A18,'Threat Intelligence'!$J:$J,"YES") | F18: =COUNTIFS('Threat Intelligence'!$A:$A,A18,'Threat Intelligence'!$E:$E,"CRITICAL") | G18: =COUNTIFS('Threat Intelligence'!$A:$A,A18,'Threat Intelligence'!$E:$E,"HIGH") | J18: =A9 | K18: =B9
A19: PATCH_TUESDAY | B19: =COUNTIF('Threat Intelligence'!$A:$A,A19) | C19: =COUNTIFS('Threat Intelligence'!$A:$A,A19,'Threat Intelligence'!$Q:$Q,"P1") | D19: =COUNTIFS('Threat Intelligence'!$A:$A,A19,'Threat Intelligence'!$Q:$Q,"P2") | E19: =COUNTIFS('Threat Intelligence'!$A:$A,A19,'Threat Intelligence'!$J:$J,"YES") | F19: =COUNTIFS('Threat Intelligence'!$A:$A,A19,'Threat Intelligence'!$E:$E,"CRITICAL") | G19: =COUNTIFS('Threat Intelligence'!$A:$A,A19,'Threat Intelligence'!$E:$E,"HIGH") | J19: =A10 | K19: =B10
A20: PHISH | B20: =COUNTIF('Threat Intelligence'!$A:$A,A20) | C20: =COUNTIFS('Threat Intelligence'!$A:$A,A20,'Threat Intelligence'!$Q:$Q,"P1") | D20: =COUNTIFS('Threat Intelligence'!$A:$A,A20,'Threat Intelligence'!$Q:$Q,"P2") | E20: =COUNTIFS('Threat Intelligence'!$A:$A,A20,'Threat Intelligence'!$J:$J,"YES") | F20: =COUNTIFS('Threat Intelligence'!$A:$A,A20,'Threat Intelligence'!$E:$E,"CRITICAL") | G20: =COUNTIFS('Threat Intelligence'!$A:$A,A20,'Threat Intelligence'!$E:$E,"HIGH") | J20: =A11 | K20: =B11
A21: REDHAT_CVE | B21: =COUNTIF('Threat Intelligence'!$A:$A,A21) | C21: =COUNTIFS('Threat Intelligence'!$A:$A,A21,'Threat Intelligence'!$Q:$Q,"P1") | D21: =COUNTIFS('Threat Intelligence'!$A:$A,A21,'Threat Intelligence'!$Q:$Q,"P2") | E21: =COUNTIFS('Threat Intelligence'!$A:$A,A21,'Threat Intelligence'!$J:$J,"YES") | F21: =COUNTIFS('Threat Intelligence'!$A:$A,A21,'Threat Intelligence'!$E:$E,"CRITICAL") | G21: =COUNTIFS('Threat Intelligence'!$A:$A,A21,'Threat Intelligence'!$E:$E,"HIGH")
A22: SANS_ISC | B22: =COUNTIF('Threat Intelligence'!$A:$A,A22) | C22: =COUNTIFS('Threat Intelligence'!$A:$A,A22,'Threat Intelligence'!$Q:$Q,"P1") | D22: =COUNTIFS('Threat Intelligence'!$A:$A,A22,'Threat Intelligence'!$Q:$Q,"P2") | E22: =COUNTIFS('Threat Intelligence'!$A:$A,A22,'Threat Intelligence'!$J:$J,"YES") | F22: =COUNTIFS('Threat Intelligence'!$A:$A,A22,'Threat Intelligence'!$E:$E,"CRITICAL") | G22: =COUNTIFS('Threat Intelligence'!$A:$A,A22,'Threat Intelligence'!$E:$E,"HIGH")
A23: SHODAN_VULN | B23: =COUNTIF('Threat Intelligence'!$A:$A,A23) | C23: =COUNTIFS('Threat Intelligence'!$A:$A,A23,'Threat Intelligence'!$Q:$Q,"P1") | D23: =COUNTIFS('Threat Intelligence'!$A:$A,A23,'Threat Intelligence'!$Q:$Q,"P2") | E23: =COUNTIFS('Threat Intelligence'!$A:$A,A23,'Threat Intelligence'!$J:$J,"YES") | F23: =COUNTIFS('Threat Intelligence'!$A:$A,A23,'Threat Intelligence'!$E:$E,"CRITICAL") | G23: =COUNTIFS('Threat Intelligence'!$A:$A,A23,'Threat Intelligence'!$E:$E,"HIGH")
A24: TALOS_IP | B24: =COUNTIF('Threat Intelligence'!$A:$A,A24) | C24: =COUNTIFS('Threat Intelligence'!$A:$A,A24,'Threat Intelligence'!$Q:$Q,"P1") | D24: =COUNTIFS('Threat Intelligence'!$A:$A,A24,'Threat Intelligence'!$Q:$Q,"P2") | E24: =COUNTIFS('Threat Intelligence'!$A:$A,A24,'Threat Intelligence'!$J:$J,"YES") | F24: =COUNTIFS('Threat Intelligence'!$A:$A,A24,'Threat Intelligence'!$E:$E,"CRITICAL") | G24: =COUNTIFS('Threat Intelligence'!$A:$A,A24,'Threat Intelligence'!$E:$E,"HIGH")
A25: THREATFOX_IOC | B25: =COUNTIF('Threat Intelligence'!$A:$A,A25) | C25: =COUNTIFS('Threat Intelligence'!$A:$A,A25,'Threat Intelligence'!$Q:$Q,"P1") | D25: =COUNTIFS('Threat Intelligence'!$A:$A,A25,'Threat Intelligence'!$Q:$Q,"P2") | E25: =COUNTIFS('Threat Intelligence'!$A:$A,A25,'Threat Intelligence'!$J:$J,"YES") | F25: =COUNTIFS('Threat Intelligence'!$A:$A,A25,'Threat Intelligence'!$E:$E,"CRITICAL") | G25: =COUNTIFS('Threat Intelligence'!$A:$A,A25,'Threat Intelligence'!$E:$E,"HIGH")
A26: THREATMINER | B26: =COUNTIF('Threat Intelligence'!$A:$A,A26) | C26: =COUNTIFS('Threat Intelligence'!$A:$A,A26,'Threat Intelligence'!$Q:$Q,"P1") | D26: =COUNTIFS('Threat Intelligence'!$A:$A,A26,'Threat Intelligence'!$Q:$Q,"P2") | E26: =COUNTIFS('Threat Intelligence'!$A:$A,A26,'Threat Intelligence'!$J:$J,"YES") | F26: =COUNTIFS('Threat Intelligence'!$A:$A,A26,'Threat Intelligence'!$E:$E,"CRITICAL") | G26: =COUNTIFS('Threat Intelligence'!$A:$A,A26,'Threat Intelligence'!$E:$E,"HIGH")
A27: TOR_EXIT | B27: =COUNTIF('Threat Intelligence'!$A:$A,A27) | C27: =COUNTIFS('Threat Intelligence'!$A:$A,A27,'Threat Intelligence'!$Q:$Q,"P1") | D27: =COUNTIFS('Threat Intelligence'!$A:$A,A27,'Threat Intelligence'!$Q:$Q,"P2") | E27: =COUNTIFS('Threat Intelligence'!$A:$A,A27,'Threat Intelligence'!$J:$J,"YES") | F27: =COUNTIFS('Threat Intelligence'!$A:$A,A27,'Threat Intelligence'!$E:$E,"CRITICAL") | G27: =COUNTIFS('Threat Intelligence'!$A:$A,A27,'Threat Intelligence'!$E:$E,"HIGH")
A28: UBUNTU_SEC | B28: =COUNTIF('Threat Intelligence'!$A:$A,A28) | C28: =COUNTIFS('Threat Intelligence'!$A:$A,A28,'Threat Intelligence'!$Q:$Q,"P1") | D28: =COUNTIFS('Threat Intelligence'!$A:$A,A28,'Threat Intelligence'!$Q:$Q,"P2") | E28: =COUNTIFS('Threat Intelligence'!$A:$A,A28,'Threat Intelligence'!$J:$J,"YES") | F28: =COUNTIFS('Threat Intelligence'!$A:$A,A28,'Threat Intelligence'!$E:$E,"CRITICAL") | G28: =COUNTIFS('Threat Intelligence'!$A:$A,A28,'Threat Intelligence'!$E:$E,"HIGH")
A29: VULNCHECK_KEV | B29: =COUNTIF('Threat Intelligence'!$A:$A,A29) | C29: =COUNTIFS('Threat Intelligence'!$A:$A,A29,'Threat Intelligence'!$Q:$Q,"P1") | D29: =COUNTIFS('Threat Intelligence'!$A:$A,A29,'Threat Intelligence'!$Q:$Q,"P2") | E29: =COUNTIFS('Threat Intelligence'!$A:$A,A29,'Threat Intelligence'!$J:$J,"YES") | F29: =COUNTIFS('Threat Intelligence'!$A:$A,A29,'Threat Intelligence'!$E:$E,"CRITICAL") | G29: =COUNTIFS('Threat Intelligence'!$A:$A,A29,'Threat Intelligence'!$E:$E,"HIGH")
A30: ZDI_ADVISORY | B30: =COUNTIF('Threat Intelligence'!$A:$A,A30) | C30: =COUNTIFS('Threat Intelligence'!$A:$A,A30,'Threat Intelligence'!$Q:$Q,"P1") | D30: =COUNTIFS('Threat Intelligence'!$A:$A,A30,'Threat Intelligence'!$Q:$Q,"P2") | E30: =COUNTIFS('Threat Intelligence'!$A:$A,A30,'Threat Intelligence'!$J:$J,"YES") | F30: =COUNTIFS('Threat Intelligence'!$A:$A,A30,'Threat Intelligence'!$E:$E,"CRITICAL") | G30: =COUNTIFS('Threat Intelligence'!$A:$A,A30,'Threat Intelligence'!$E:$E,"HIGH")
A31: TOTAL | B31: =SUM(B4:B30) | C31: =SUM(C4:C30) | D31: =SUM(D4:D30) | E31: =SUM(E4:E30) | F31: =SUM(F4:F30) | G31: =SUM(G4:G30)
A33: 🔥 RISK HEATMAP ─ Likelihood × Impact | F33: 📐 RISK MATRIX ─ Score = Likelihood × Impact
A34: Likelihood / Impact | B34: Low Impact (1) | C34: Med Impact (2) | D34: High Impact (3) | G34: Impact 1 | H34: Impact 2 | I34: Impact 3 | J34: Zone
A35: Low Likelihood (1) | B35: =COUNTIFS('Threat Intelligence'!$F:$F,1,'Threat Intelligence'!$G:$G,1) | C35: =COUNTIFS('Threat Intelligence'!$F:$F,1,'Threat Intelligence'!$G:$G,2) | D35: =COUNTIFS('Threat Intelligence'!$F:$F,1,'Threat Intelligence'!$G:$G,3) | F35: L=1 (Low) | G35: L1×I1=1 (LOW) | H35: L1×I2=2 (LOW) | I35: L1×I3=3 (MEDIUM) | J35: MEDIUM
A36: Med Likelihood (2) | B36: =COUNTIFS('Threat Intelligence'!$F:$F,2,'Threat Intelligence'!$G:$G,1) | C36: =COUNTIFS('Threat Intelligence'!$F:$F,2,'Threat Intelligence'!$G:$G,2) | D36: =COUNTIFS('Threat Intelligence'!$F:$F,2,'Threat Intelligence'!$G:$G,3) | F36: L=2 (Med) | G36: L2×I1=2 (LOW) | H36: L2×I2=4 (MEDIUM) | I36: L2×I3=6 (HIGH) | J36: HIGH
A37: High Likelihood (3) | B37: =COUNTIFS('Threat Intelligence'!$F:$F,3,'Threat Intelligence'!$G:$G,1) | C37: =COUNTIFS('Threat Intelligence'!$F:$F,3,'Threat Intelligence'!$G:$G,2) | D37: =COUNTIFS('Threat Intelligence'!$F:$F,3,'Threat Intelligence'!$G:$G,3) | F37: L=3 (High) | G37: L3×I1=3 (MEDIUM) | H37: L3×I2=6 (HIGH) | I37: L3×I3=9 (CRITICAL) | J37: CRITICAL
A39: 🟢 LOW | B39: 🟡 MEDIUM | C39: 🟠 HIGH | D39: 🔴 CRITICAL | F39: Risk Score = Likelihood (1-3) × Impact (1-3) → Max 9 = CRITICAL

Sheet Threat Intelligence
A1: Type | B1: ID | C1: Description | D1: CVSS | E1: Severity | F1: Likelihood | G1: Impact | H1: Risk_Level | I1: Final_Score | J1: CISA_KEV | K1: Link | L1: Timestamp | M1: Patch_Available | N1: Patch_Links | O1: Workarounds | P1: Affected_Products | Q1: Remediation_Priority | R1: Remediation_Steps | S1: GreyNoise_Context | T1: EPSS_Score | U1: EPSS_Percentile | V1: MITRE_Techniques | W1: Source_Count | X1: Confidence_Score | Y1: Exploit_Status | Z1: Fix_Available | AA1: Intel_URL | AB1: ZDI_Advisory | AC1: AttackerKB_Score | AD1: News_Coverage
A2: CVE | B2: CVE-2019-25326 | C2: ipPulse 1.92 contains a denial of service vulnerability that allows local attackers to crash the application by providing an oversized input in the Enter Key field. Attackers can generate a 256-byte buffer of repeated 'A' characters to trigger an application crash when pasting the malicious content. | D2: 6.2 | E2: MEDIUM | F2: 2 | G2: 2 | H2: MEDIUM | I2: 10.2 | J2: NO | K2: https://nvd.nist.gov/vuln/detail/CVE-2019-25326 | L2: 2026-02-26 00:15 | M2: CHECK_VENDOR | N2: See NVD references | O2: Apply vendor patches | P2: nwpsw ippulse * | Q2: P4 | R2: 📅 Schedule patch deployment within 30 days | 🔍 Monitor for exploitation attempts | S2: CVE - IP enrichment n/a | T2: 0.0001 | U2: 0.0199 | V2: T1203:Exploitation for Client Execution | T1499:Endpoint Denial of Service | W2: 1 | X2: LOW (40%) | Y2: UNLIKELY | Z2: CHECK_VENDOR | AA2: https://nvd.nist.gov/vuln/detail/CVE-2019-25326 | AB2: NONE | AC2: 0
A3: CVE | B3: CVE-2019-25349 | C3: ScadaApp for iOS 1.1.4.0 contains a denial of service vulnerability that allows attackers to crash the application by inputting an oversized buffer in the Servername field. Attackers can paste a 257-character buffer during login to trigger an application crash on iOS devices. | D3: 7.5 | E3: HIGH | F3: 2 | G3: 3 | H3: HIGH | I3: 13.5 | J3: NO | K3: https://nvd.nist.gov/vuln/detail/CVE-2019-25349 | L3: 2026-02-26 00:15 | M3: CHECK_VENDOR | N3: See NVD references | O3: Apply vendor patches | P3: See CVE details | Q3: P2 | R3: 🚨 URGENT: Apply vendor patches immediately | 🔒 Isolate affected systems if patch unavailable | 🛡️ Enable additional monitoring/IDS rules | S3: CVE - IP enrichment n/a | T3: 0 | U3: 0 | V3: T1203:Exploitation for Client Execution | T1499:Endpoint Denial of Service | W3: 2 | X3: HIGH (72%) | Y3: POSSIBLE | Z3: CHECK_VENDOR | AA3: https://nvd.nist.gov/vuln/detail/CVE-2019-25349 | AB3: NONE | AC3: 3.75
A4: CVE | B4: CVE-2019-25350 | C4: XMedia Recode 3.4.8.6 contains a denial of service vulnerability that allows attackers to crash the application by loading a specially crafted .m3u playlist file. Attackers can create a malicious .m3u file with an oversized buffer to trigger an application crash when the file is opened. | D4: 7.5 | E4: HIGH | F4: 2 | G4: 3 | H4: HIGH | I4: 13.5 | J4: NO | K4: https://nvd.nist.gov/vuln/detail/CVE-2019-25350 | L4: 2026-02-26 00:15 | M4: CHECK_VENDOR | N4: See NVD references | O4: Apply vendor patches | P4: See CVE details | Q4: P3 | R4: 🚨 URGENT: Apply vendor patches immediately | 🔒 Isolate affected systems if patch unavailable | 🛡️ Enable additional monitoring/IDS rules | S4: CVE - IP enrichment n/a | T4: 0 | U4: 0 | V4: T1499:Endpoint Denial of Service | W4: 1 | X4: LOW (40%) | Y4: UNLIKELY | Z4: CHECK_VENDOR | AA4: https://nvd.nist.gov/vuln/detail/CVE-2019-25350 | AB4: NONE | AC4: 0
A5: CVE | B5: CVE-2019-25351 | C5: Centova Cast 3.2.11 contains a file download vulnerability that allows authenticated attackers to retrieve arbitrary system files through the server.copyfile API endpoint. Attackers can exploit the vulnerability by supplying crafted parameters to download sensitive files like /etc/passwd using curl and wget requests. | D5: 8.8 | E5: HIGH | F5: 2 | G5: 3 | H5: HIGH | I5: 14.8 | J5: NO | K5: https://nvd.nist.gov/vuln/detail/CVE-2019-25351 | L5: 2026-02-26 00:15 | M5: CHECK_VENDOR | N5: See NVD references | O5: Apply vendor patches | P5: See CVE details | Q5: P3 | R5: 🚨 URGENT: Apply vendor patches immediately | 🔒 Isolate affected systems if patch unavailable | 🛡️ Enable additional monitoring/IDS rules | S5: CVE - IP enrichment n/a | T5: 0.0005 | U5: 0.1573 | V5: T1190:Exploit Public-Facing Application | W5: 1 | X5: LOW (40%) | Y5: UNLIKELY | Z5: CHECK_VENDOR | AA5: https://nvd.nist.gov/vuln/detail/CVE-2019-25351 | AB5: NONE | AC5: 0
A6: CVE | B6: CVE-2019-25352 | C6: Crystal Live HTTP Server 6.01 contains a directory traversal vulnerability that allows remote attackers to access system files by manipulating URL path segments. Attackers can use multiple '../' sequences to navigate outside the web root and retrieve sensitive configuration files like Windows system files. | D6: 7.5 | E6: HIGH | F6: 2 | G6: 3 | H6: HIGH | I6: 13.5 | J6: NO | K6: https://nvd.nist.gov/vuln/detail/CVE-2019-25352 | L6: 2026-02-26 00:15 | M6: CHECK_VENDOR | N6: See NVD references | O6: Apply vendor patches | P6: See CVE details | Q6: P2 | R6: 🚨 URGENT: Apply vendor patches immediately | 🔒 Isolate affected systems if patch unavailable | 🛡️ Enable additional monitoring/IDS rules | S6: CVE - IP enrichment n/a | T6: 0 | U6: 0 | V6: T1083:File and Directory Discovery | W6: 2 | X6: HIGH (72%) | Y6: POSSIBLE | Z6: CHECK_VENDOR | AA6: https://nvd.nist.gov/vuln/detail/CVE-2019-25352 | AB6: NONE | AC6: 3.75
A7: CVE | B7: CVE-2019-25353 | C7: Foscam Video Management System 1.1.4.9 contains a denial of service vulnerability in the username input field that allows attackers to crash the application. Attackers can overwrite the username with a 520-byte buffer of repeated 'A' characters to trigger an application crash during device login. | D7: 7.5 | E7: HIGH | F7: 2 | G7: 3 | H7: HIGH | I7: 13.5 | J7: NO | K7: https://nvd.nist.gov/vuln/detail/CVE-2019-25353 | L7: 2026-02-26 00:15 | M7: CHECK_VENDOR | N7: See NVD references | O7: Apply vendor patches | P7: See CVE details | Q7: P3 | R7: 🚨 URGENT: Apply vendor patches immediately | 🔒 Isolate affected systems if patch unavailable | 🛡️ Enable additional monitoring/IDS rules | S7: CVE - IP enrichment n/a | T7: 0 | U7: 0 | V7: T1203:Exploitation for Client Execution | T1499:Endpoint Denial of Service | W7: 1 | X7: LOW (40%) | Y7: UNLIKELY | Z7: CHECK_VENDOR | AA7: https://nvd.nist.gov/vuln/detail/CVE-2019-25353 | AB7: NONE | AC7: 0
A8: CVE | B8: CVE-2019-25354 | C8: iSmartViewPro 1.3.34 contains a denial of service vulnerability that allows attackers to crash the application by overflowing the camera ID input field. Attackers can paste a 257-character buffer into the camera DID and password fields to trigger an application crash on iOS devices. | D8: 7.5 | E8: HIGH | F8: 2 | G8: 3 | H8: HIGH | I8: 13.5 | J8: NO | K8: https://nvd.nist.gov/vuln/detail/CVE-2019-25354 | L8: 2026-02-26 00:15 | M8: CHECK_VENDOR | N8: See NVD references | O8: Apply vendor patches | P8: See CVE details | Q8: P2 | R8: 🚨 URGENT: Apply vendor patches immediately | 🔒 Isolate affected systems if patch unavailable | 🛡️ Enable additional monitoring/IDS rules | S8: CVE - IP enrichment n/a | T8: 0 | U8: 0 | V8: T1203:Exploitation for Client Execution | T1499:Endpoint Denial of Service | W8: 2 | X8: HIGH (72%) | Y8: POSSIBLE | Z8: CHECK_VENDOR | AA8: https://nvd.nist.gov/vuln/detail/CVE-2019-25354 | AB8: NONE | AC8: 3.75
A9: CVE | B9: CVE-2019-25355 | C9: gSOAP 2.8 contains a directory traversal vulnerability that allows unauthenticated attackers to access system files by manipulating HTTP path traversal techniques. Attackers can retrieve sensitive files like /etc/passwd by sending crafted GET requests with multiple '../' directory traversal sequences. | D9: 7.5 | E9: HIGH | F9: 2 | G9: 3 | H9: HIGH | I9: 13.5 | J9: NO | K9: https://nvd.nist.gov/vuln/detail/CVE-2019-25355 | L9: 2026-02-26 00:15 | M9: CHECK_VENDOR | N9: See NVD references | O9: Apply vendor patches | P9: See CVE details | Q9: P2 | R9: 🚨 URGENT: Apply vendor patches immediately | 🔒 Isolate affected systems if patch unavailable | 🛡️ Enable additional monitoring/IDS rules | S9: CVE - IP enrichment n/a | T9: 0 | U9: 0 | V9: T1083:File and Directory Discovery | W9: 2 | X9: HIGH (72%) | Y9: POSSIBLE | Z9: CHECK_VENDOR | AA9: https://nvd.nist.gov/vuln/detail/CVE-2019-25355 | AB9: NONE | AC9: 3.75
A10: CVE | B10: CVE-2019-25356 | C10: Bematech (formerly Logic Controls, now Elgin) MP-4200 TH printer contains a cross-site scripting vulnerability in the admin configuration page. Attackers can inject malicious scripts via crafted POST requests with malformed 'admin' and 'person' parameters, allowing execution of arbitrary JavaScript in the context of an authenticated user's browser session. | D10: 6.1 | E10: MEDIUM | F10: 2 | G10: 2 | H10: MEDIUM | I10: 10.1 | J10: NO | K10: https://nvd.nist.gov/vuln/detail/CVE-2019-25356 | L10: 2026-02-26 00:15 | M10: CHECK_VENDOR | N10: See NVD references | O10: Apply vendor patches | P10: See CVE details | Q10: P4 | R10: 📅 Schedule patch deployment within 30 days | 🔍 Monitor for exploitation attempts | S10: CVE - IP enrichment n/a | T10: 0.0004 | U10: 0.1135 | V10: T1189:Drive-by Compromise | W10: 1 | X10: LOW (40%) | Y10: UNLIKELY | Z10: CHECK_VENDOR | AA10: https://nvd.nist.gov/vuln/detail/CVE-2019-25356 | AB10: NONE | AC10: 0
A11: CVE | B11: CVE-2019-25357 | C11: Control Center PRO 6.2.9 contains a stack-based buffer overflow vulnerability in the user creation module's username field that allows attackers to overwrite Structured Exception Handler (SEH). Attackers can craft a malicious payload exceeding 664 bytes to inject shellcode and potentially execute arbitrary code on vulnerable Windows systems. | D11: 8.4 | E11: HIGH | F11: 2 | G11: 3 | H11: HIGH | I11: 14.4 | J11: NO | K11: https://nvd.nist.gov/vuln/detail/CVE-2019-25357 | L11: 2026-02-26 00:15 | M11: CHECK_VENDOR | N11: See NVD references | O11: Apply vendor patches | P11: See CVE details | Q11: P3 | R11: 🚨 URGENT: Apply vendor patches immediately | 🔒 Isolate affected systems if patch unavailable | 🛡️ Enable additional monitoring/IDS rules | S11: CVE - IP enrichment n/a | T11: 0 | U11: 0 | V11: T1190:Exploit Public-Facing Application | T1203:Exploitation for Client Execution | W11: 1 | X11: LOW (40%) | Y11: UNLIKELY | Z11: CHECK_VENDOR | AA11: https://nvd.nist.gov/vuln/detail/CVE-2019-25357 | AB11: NONE | AC11: 0
A12: CVE | B12: CVE-2019-25358 | C12: FileOptimizer 14.00.2524 contains a denial of service vulnerability that allows attackers to crash the application by manipulating the FileOptimizer32.ini configuration file. Attackers can overwrite the TempDirectory parameter with a 5000-character buffer to cause the application to crash when opening options. | D12: 7.5 | E12: HIGH | F12: 2 | G12: 3 | H12: HIGH | I12: 13.5 | J12: NO | K12: https://nvd.nist.gov/vuln/detail/CVE-2019-25358 | L12: 2026-02-26 00:15 | M12: CHECK_VENDOR | N12: See NVD references | O12: Apply vendor patches | P12: See CVE details | Q12: P3 | R12: 🚨 URGENT: Apply vendor patches immediately | 🔒 Isolate affected systems if patch unavailable | 🛡️ Enable additional monitoring/IDS rules | S12: CVE - IP enrichment n/a | T12: 0 | U12: 0 | V12: T1499:Endpoint Denial of Service | W12: 1 | X12: LOW (40%) | Y12: UNLIKELY | Z12: CHECK_VENDOR | AA12: https://nvd.nist.gov/vuln/detail/CVE-2019-25358 | AB12: NONE | AC12: 0
A13: CVE | B13: CVE-2019-25359 | C13: SD.NET RIM versions before 4.7.3c contain a SQL injection vulnerability that allows attackers to inject malicious SQL statements through POST parameters 'idtyp' and 'idgremium'. Attackers can exploit this vulnerability by crafting specially formed POST requests to the /vorlagen/ endpoint, enabling unauthorized database manipulation and potential information disclosure. | D13: 8.2 | E13: HIGH | F13: 2 | G13: 3 | H13: HIGH | I13: 14.2 | J13: NO | K13: https://nvd.nist.gov/vuln/detail/CVE-2019-25359 | L13: 2026-02-26 00:15 | M13: CHECK_VENDOR | N13: See NVD references | O13: Apply vendor patches | P13: See CVE details | Q13: P3 | R13: 🚨 URGENT: Apply vendor patches immediately | 🔒 Isolate affected systems if patch unavailable | 🛡️ Enable additional monitoring/IDS rules | S13: CVE - IP enrichment n/a | T13: 0 | U13: 0 | V13: T1185:Browser Session Hijacking | T1190:Exploit Public-Facing Application | T1213:Data from Information Repositories | W13: 1 | X13: LOW (40%) | Y13: UNLIKELY | Z13: CHECK_VENDOR | AA13: https://nvd.nist.gov/vuln/detail/CVE-2019-25359 | AB13: NONE | AC13: 0
... A1123: CVE | B1123: CVE-2025-11848 | C1123: A null pointer dereference vulnerability in the Wake-on-LAN CGI program of the Zyxel VMG3625-T50B firmware version through 5.50(ABPM.9.6)C0 and the Zyxel WX3100-T0 firmware versions through 5.50(ABVL.4.8)C0 could allow an authenticated attacker with administrator privileges to trigger a denial-of-service (DoS) condition by sending a crafted HTTP request. | D1123: 4.9 | E1123: MEDIUM | F1123: 2 | G1123: 2 | H1123: MEDIUM | I1123: 8.9 | J1123: NO | K1123: https://nvd.nist.gov/vuln/detail/CVE-2025-11848 | L1123: 2026-02-26 00:15 | M1123: YES | N1123: https://www.zyxel.com/global/en/support/security-advisories/zyxel-security-advisory-for-null-pointer-dereference-and-command-injection-vulnerabilities-in-certain-4g-lte-5g-nr-cpe-dsl-ethernet-cpe-fiber-onts-security-routers-and-wireless-extenders-02-24-2026 | O1123: Apply vendor patches | P1123: zyxel vmg4005-b60a_firmware * | zyxel pm7500-00 - | zyxel ex7501-b0 - | Q1123: P4 | R1123: 📅 Schedule patch deployment within 30 days | 🔍 Monitor for exploitation attempts | S1123: CVE - IP enrichment n/a | T1123: 0.0018 | U1123: 0.3897 | V1123: T1499:Endpoint Denial of Service | W1123: 1 | X1123: LOW (40%) | Y1123: UNLIKELY | Z1123: PATCH_AVAILABLE | AA1123: https://nvd.nist.gov/vuln/detail/CVE-2025-11848 | AB1123: NONE | AC1123: 0
A1124: CVE | B1124: CVE-2025-13942 | C1124: A command injection vulnerability in the UPnP function of the Zyxel EX3510-B0 firmware versions through 5.17(ABUP.15.1)C0 could allow a remote attacker to execute operating system (OS) commands on an affected device by sending specially crafted UPnP SOAP requests. | D1124: 9.8 | E1124: CRITICAL | F1124: 2 | G1124: 3 | H1124: HIGH | I1124: 15.8 | J1124: NO | K1124: https://nvd.nist.gov/vuln/detail/CVE-2025-13942 | L1124: 2026-02-26 00:15 | M1124: YES | N1124: https://www.zyxel.com/global/en/support/security-advisories/zyxel-security-advisory-for-null-pointer-dereference-and-command-injection-vulnerabilities-in-certain-4g-lte-5g-nr-cpe-dsl-ethernet-cpe-fiber-onts-security-routers-and-wireless-extenders-02-24-2026 | O1124: Apply vendor patches | P1124: zyxel ex5510-b0 - | zyxel dx4510-b1_firmware * | zyxel dx4510-b0 - | Q1124: P3 | R1124: 🚨 URGENT: Apply vendor patches immediately | 🔒 Isolate affected systems if patch unavailable | 🛡️ Enable additional monitoring/IDS rules | S1124: CVE - IP enrichment n/a | T1124: 0 | U1124: 0 | V1124: T1059:Command and Scripting Interpreter | W1124: 1 | X1124: LOW (40%) | Y1124: UNLIKELY | Z1124: PATCH_AVAILABLE | AA1124: https://nvd.nist.gov/vuln/detail/CVE-2025-13942 | AB1124: NONE | AC1124: 0 | AD1124: [SecurityAffairs] Critical Zyxel router flaw exposed devices to remote attacks
A1125: CVE | B1125: CVE-2025-13943 | C1125: A post-authentication command injection vulnerability in the log file download function of the Zyxel EX3301-T0 firmware versions through 5.50(ABVY.7)C0 could allow an authenticated attacker to execute operating system (OS) commands on an affected device. | D1125: 8.8 | E1125: HIGH | F1125: 2 | G1125: 3 | H1125: HIGH | I1125: 14.8 | J1125: NO | K1125: https://nvd.nist.gov/vuln/detail/CVE-2025-13943 | L1125: 2026-02-26 00:15 | M1125: YES | N1125: https://www.zyxel.com/global/en/support/security-advisories/zyxel-security-advisory-for-null-pointer-dereference-and-command-injection-vulnerabilities-in-certain-4g-lte-5g-nr-cpe-dsl-ethernet-cpe-fiber-onts-security-routers-and-wireless-extenders-02-24-2026 | O1125: Apply vendor patches | P1125: zyxel vmg4005-b60a_firmware * | zyxel pm7500-00 - | zyxel ex7501-b0 - | Q1125: P3 | R1125: 🚨 URGENT: Apply vendor patches immediately | 🔒 Isolate affected systems if patch unavailable | 🛡️ Enable additional monitoring/IDS rules | S1125: CVE - IP enrichment n/a | T1125: 0 | U1125: 0 | V1125: T1059:Command and Scripting Interpreter | W1125: 1 | X1125: LOW (40%) | Y1125: UNLIKELY | Z1125: PATCH_AVAILABLE | AA1125: https://nvd.nist.gov/vuln/detail/CVE-2025-13943 | AB1125: NONE | AC1125: 0
A1126: CVE | B1126: CVE-2026-1459 | C1126: A post-authentication command injection vulnerability in the TR-369 certificate download CGI program of the Zyxel VMG3625-T50B firmware versions through 5.50(ABPM.9.7)C0 could allow an authenticated attacker with administrator privileges to execute operating system (OS) commands on an affected device. | D1126: 7.2 | E1126: HIGH | F1126: 2 | G1126: 3 | H1126: HIGH | I1126: 13.2 | J1126: NO | K1126: https://nvd.nist.gov/vuln/detail/CVE-2026-1459 | L1126: 2026-02-26 00:15 | M1126: YES | N1126: https://www.zyxel.com/global/en/support/security-advisories/zyxel-security-advisory-for-null-pointer-dereference-and-command-injection-vulnerabilities-in-certain-4g-lte-5g-nr-cpe-dsl-ethernet-cpe-fiber-onts-security-routers-and-wireless-extenders-02-24-2026 | O1126: Apply vendor patches | P1126: zyxel vmg3625-t50b - | zyxel emg5523-t50b_firmware * | zyxel emg3525-t50b - | Q1126: P3 | R1126: 🚨 URGENT: Apply vendor patches immediately | 🔒 Isolate affected systems if patch unavailable | 🛡️ Enable additional monitoring/IDS rules | S1126: CVE - IP enrichment n/a | T1126: 0 | U1126: 0 | V1126: T1059:Command and Scripting Interpreter | W1126: 1 | X1126: LOW (40%) | Y1126: UNLIKELY | Z1126: PATCH_AVAILABLE | AA1126: https://nvd.nist.gov/vuln/detail/CVE-2026-1459 | AB1126: NONE | AC1126: 0
A1127: CVE | B1127: CVE-2026-25989 | C1127: ImageMagick is free and open-source software used for editing and manipulating digital images. Prior to versions 7.1.2-15 and 6.9.13-40, a crafted SVG file can cause a denial of service. An off-by-one boundary check (`>` instead of `>=`) that allows bypass the guard and reach an undefined `(size_t)` cast. Versions 7.1.2-15 and 6.9.13-40 contain a patch. | D1127: 7.5 | E1127: HIGH | F1127: 2 | G1127: 3 | H1127: HIGH | I1127: 13.5 | J1127: NO | K1127: https://nvd.nist.gov/vuln/detail/CVE-2026-25989 | L1127: 2026-02-26 00:15 | M1127: YES | N1127: https://github.com/ImageMagick/ImageMagick/security/advisories/GHSA-7355-pwx2-pm84 | O1127: Apply vendor patches | P1127: imagemagick imagemagick * | Q1127: P3 | R1127: 🚨 URGENT: Apply vendor patches immediately | 🔒 Isolate affected systems if patch unavailable | 🛡️ Enable additional monitoring/IDS rules | S1127: CVE - IP enrichment n/a | T1127: 0 | U1127: 0 | V1127: T1190:Exploit Public-Facing Application | T1499:Endpoint Denial of Service | W1127: 1 | X1127: LOW (40%) | Y1127: UNLIKELY | Z1127: PATCH_AVAILABLE | AA1127: https://nvd.nist.gov/vuln/detail/CVE-2026-25989 | AB1127: NONE | AC1127: 0
A1128: CVE | B1128: CVE-2026-26066 | C1128: ImageMagick is free and open-source software used for editing and manipulating digital images. Prior to versions 7.1.2-15 and 6.9.13-40, a crafted profile contain invalid IPTC data may cause an infinite loop when writing it with `IPTCTEXT`. Versions 7.1.2-15 and 6.9.13-40 contain a patch. | D1128: 6.2 | E1128: MEDIUM | F1128: 2 | G1128: 2 | H1128: MEDIUM | I1128: 10.2 | J1128: NO | K1128: https://nvd.nist.gov/vuln/detail/CVE-2026-26066 | L1128: 2026-02-26 00:15 | M1128: CHECK_VENDOR | N1128: See NVD references | O1128: Apply vendor patches | P1128: imagemagick imagemagick * | Q1128: P4 | R1128: 📅 Schedule patch deployment within 30 days | 🔍 Monitor for exploitation attempts | S1128: CVE - IP enrichment n/a | T1128: 0 | U1128: 0 | V1128: T1190:Exploit Public-Facing Application | W1128: 1 | X1128: LOW (40%) | Y1128: UNLIKELY | Z1128: CHECK_VENDOR | AA1128: https://nvd.nist.gov/vuln/detail/CVE-2026-26066 | AB1128: NONE | AC1128: 0
A1129: CVE | B1129: CVE-2026-26198 | C1129: Ormar is a async mini ORM for Python. In versions 0.9.9 through 0.22.0, when performing aggregate queries, Ormar ORM constructs SQL expressions by passing user-supplied column names directly into `sqlalchemy.text()` without any validation or sanitization. The `min()` and `max()` methods in the `QuerySet` class accept arbitrary string input as the column parameter. While `sum()` and `avg()` are partially protected by an `is_numeric` type check that rejects non-existent fields, `min()` and `max()` | D1129: 9.8 | E1129: CRITICAL | F1129: 2 | G1129: 3 | H1129: HIGH | I1129: 15.8 | J1129: NO | K1129: https://nvd.nist.gov/vuln/detail/CVE-2026-26198 | L1129: 2026-02-26 00:15 | M1129: YES | N1129: https://github.com/collerek/ormar/commit/a03bae14fe01358d3eaf7e319fcd5db2e4956b16 | https://github.com/collerek/ormar/security/advisories/GHSA-xxh2-68g9-8jqr | O1129: Apply vendor patches | P1129: collerek ormar * | Q1129: P3 | R1129: 🚨 URGENT: Apply vendor patches immediately | 🔒 Isolate affected systems if patch unavailable | 🛡️ Enable additional monitoring/IDS rules | S1129: CVE - IP enrichment n/a | T1129: 0 | U1129: 0 | V1129: T1190:Exploit Public-Facing Application | W1129: 1 | X1129: LOW (40%) | Y1129: UNLIKELY | Z1129: PATCH_AVAILABLE | AA1129: https://nvd.nist.gov/vuln/detail/CVE-2026-26198 | AB1129: NONE | AC1129: 0
A1130: CVE | B1130: CVE-2026-26283 | C1130: ImageMagick is free and open-source software used for editing and manipulating digital images. Prior to versions 7.1.2-15 and 6.9.13-40, a `continue` statement in the JPEG extent binary search loop in the jpeg encoder causes an infinite loop when writing persistently fails. An attacker can trigger a 100% CPU consumption and process hang (Denial of Service) with a crafted image. Versions 7.1.2-15 and 6.9.13-40 contain a patch. | D1130: 6.2 | E1130: MEDIUM | F1130: 2 | G1130: 2 | H1130: MEDIUM | I1130: 10.2 | J1130: NO | K1130: https://nvd.nist.gov/vuln/detail/CVE-2026-26283 | L1130: 2026-02-26 00:15 | M1130: YES | N1130: https://github.com/ImageMagick/ImageMagick/security/advisories/GHSA-gwr3-x37h-h84v | O1130: Apply vendor patches | P1130: imagemagick imagemagick * | Q1130: P4 | R1130: 📅 Schedule patch deployment within 30 days | 🔍 Monitor for exploitation attempts | S1130: CVE - IP enrichment n/a | T1130: 0 | U1130: 0 | V1130: T1190:Exploit Public-Facing Application | T1499:Endpoint Denial of Service | W1130: 1 | X1130: LOW (40%) | Y1130: UNLIKELY | Z1130: PATCH_AVAILABLE | AA1130: https://nvd.nist.gov/vuln/detail/CVE-2026-26283 | AB1130: NONE | AC1130: 0
A1131: CVE | B1131: CVE-2026-26284 | C1131: ImageMagick is free and open-source software used for editing and manipulating digital images. Prior to versions 7.1.2-15 and 6.9.13-40, ImageMagick lacks proper boundary checking when processing Huffman-coded data from PCD (Photo CD) files. The decoder contains an function that has an incorrect initialization that could cause an out of bounds read. Versions 7.1.2-15 and 6.9.13-40 contain a patch. | D1131: 6.5 | E1131: MEDIUM | F1131: 2 | G1131: 2 | H1131: MEDIUM | I1131: 10.5 | J1131: NO | K1131: https://nvd.nist.gov/vuln/detail/CVE-2026-26284 | L1131: 2026-02-26 00:15 | M1131: YES | N1131: https://github.com/ImageMagick/ImageMagick/security/advisories/GHSA-wrhr-rf8j-r842 | O1131: Apply vendor patches | P1131: imagemagick imagemagick * | Q1131: P4 | R1131: 📅 Schedule patch deployment within 30 days | 🔍 Monitor for exploitation attempts | S1131: CVE - IP enrichment n/a | T1131: 0.0004 | U1131: 0.1313 | V1131: T1203:Exploitation for Client Execution | T1190:Exploit Public-Facing Application | W1131: 1 | X1131: LOW (40%) | Y1131: UNLIKELY | Z1131: PATCH_AVAILABLE | AA1131: https://nvd.nist.gov/vuln/detail/CVE-2026-26284 | AB1131: NONE | AC1131: 0
A1132: CVE | B1132: CVE-2026-26331 | C1132: yt-dlp is a command-line audio/video downloader. Starting in version 2023.06.21 and prior to version 2026.02.21, when yt-dlp's `--netrc-cmd` command-line option (or `netrc_cmd` Python API parameter) is used, an attacker could achieve arbitrary command injection on the user's system with a maliciously crafted URL. yt-dlp maintainers assume the impact of this vulnerability to be high for anyone who uses `--netrc-cmd` in their command/configuration or `netrc_cmd` in their Python scripts. Even thoug | D1132: 8.8 | E1132: HIGH | F1132: 2 | G1132: 3 | H1132: HIGH | I1132: 14.8 | J1132: NO | K1132: https://nvd.nist.gov/vuln/detail/CVE-2026-26331 | L1132: 2026-02-26 00:15 | M1132: YES | N1132: https://github.com/yt-dlp/yt-dlp/commit/1fbbe29b99dc61375bf6d786f824d9fcf6ea9c1a | https://github.com/yt-dlp/yt-dlp/security/advisories/GHSA-g3gw-q23r-pgqm | O1132: https://github.com/yt-dlp/yt-dlp/security/advisories/GHSA-g3gw-q23r-pgqm | P1132: yt-dlp_project yt-dlp * | Q1132: P3 | R1132: 🚨 URGENT: Apply vendor patches immediately | 🔒 Isolate affected systems if patch unavailable | 🛡️ Enable additional monitoring/IDS rules | S1132: CVE - IP enrichment n/a | T1132: 0 | U1132: 0 | V1132: T1059:Command and Scripting Interpreter | W1132: 1 | X1132: LOW (40%) | Y1132: UNLIKELY | Z1132: PATCH_AVAILABLE | AA1132: https://nvd.nist.gov/vuln/detail/CVE-2026-26331 | AB1132: NONE | AC1132: 0
A1133: CVE | B1133: CVE-2026-26981 | C1133: OpenEXR provides the specification and reference implementation of the EXR file format, an image storage format for the motion picture industry. In versions 3.3.0 through 3.3.6 and 3.4.0 through 3.4.4, a heap-buffer-overflow (OOB read) occurs in the `istream_nonparallel_read` function in `ImfContextInit.cpp` when parsing a malformed EXR file through a memory-mapped `IStream`. A signed integer subtraction produces a negative value that is implicitly converted to `size_t`, resulting in a massive l | D1133: 6.5 | E1133: MEDIUM | F1133: 2 | G1133: 2 | H1133: MEDIUM | I1133: 10.5 | J1133: NO | K1133: https://nvd.nist.gov/vuln/detail/CVE-2026-26981 | L1133: 2026-02-26 00:15 | M1133: YES | N1133: https://github.com/AcademySoftwareFoundation/openexr/commit/6bb2ddf1068573d073edf81270a015b38cc05cef | https://github.com/AcademySoftwareFoundation/openexr/commit/d2be382758adc3e9ab83a3de35138ec28d93ebd8 | https://github.com/AcademySoftwareFoundation/openexr/security/advisories/GHSA-q6vj-wxvf-5m8c | O1133: Apply vendor patches | P1133: openexr openexr * | Q1133: P4 | R1133: 📅 Schedule patch deployment within 30 days | 🔍 Monitor for exploitation attempts | S1133: CVE - IP enrichment n/a | T1133: 0 | U1133: 0 | V1133: T1190:Exploit Public-Facing Application | W1133: 1 | X1133: LOW (40%) | Y1133: UNLIKELY | Z1133: PATCH_AVAILABLE | AA1133: https://nvd.nist.gov/vuln/detail/CVE-2026-26981 | AB1133: NONE | AC1133: 0
A1134: CVE | B1134: CVE-2026-26983 | C1134: ImageMagick is free and open-source software used for editing and manipulating digital images. Prior to versions 7.1.2-15 and 6.9.13-40, the MSL interpreter crashes when processing a invalid ` ` element that causes it to use an image after it has been freed. Versions 7.1.2-15 and 6.9.13-40 contain a patch. | D1134: 5.3 | E1134: MEDIUM | F1134: 2 | G1134: 2 | H1134: MEDIUM | I1134: 9.3 | J1134: NO | K1134: https://nvd.nist.gov/vuln/detail/CVE-2026-26983 | L1134: 2026-02-26 00:15 | M1134: YES | N1134: https://github.com/ImageMagick/ImageMagick/security/advisories/GHSA-w8mw-frc6-r7m8 | O1134: Apply vendor patches | P1134: imagemagick imagemagick * | Q1134: P4 | R1134: 📅 Schedule patch deployment within 30 days | 🔍 Monitor for exploitation attempts | S1134: CVE - IP enrichment n/a | T1134: 0 | U1134: 0 | V1134: T1499:Endpoint Denial of Service | T1203:Exploitation for Client Execution | T1190:Exploit Public-Facing Application | W1134: 1 | X1134: LOW (40%) | Y1134: UNLIKELY | Z1134: PATCH_AVAILABLE | AA1134: https://nvd.nist.gov/vuln/detail/CVE-2026-26983 | AB1134: NONE | AC1134: 0
A1135: CVE | B1135: CVE-2026-27126 | C1135: Craft is a content management system (CMS). In versions 4.5.0-RC1 through 4.16.18 and 5.0.0-RC1 through 5.8.22, a stored Cross-site Scripting (XSS) vulnerability exists in the `editableTable.twig` component when using the `html` column type. The application fails to sanitize the input, allowing an attacker to execute arbitrary JavaScript when another user views a page with the malicious table field. In order to exploit the vulnerability, an attacker must have an administrator account, and `allow | D1135: 5 | E1135: MEDIUM | F1135: 2 | G1135: 2 | H1135: MEDIUM | I1135: 9 | J1135: NO | K1135: https://nvd.nist.gov/vuln/detail/CVE-2026-27126 | L1135: 2026-02-26 00:15 | M1135: CHECK_VENDOR | N1135: See NVD references | O1135: Apply vendor patches | P1135: See CVE details | Q1135: P4 | R1135: 📅 Schedule patch deployment within 30 days | 🔍 Monitor for exploitation attempts | S1135: CVE - IP enrichment n/a | T1135: 0 | U1135: 0 | V1135: T1189:Drive-by Compromise | W1135: 1 | X1135: LOW (40%) | Y1135: UNLIKELY | Z1135: CHECK_VENDOR | AA1135: https://nvd.nist.gov/vuln/detail/CVE-2026-27126 | AB1135: NONE | AC1135: 0
A1136: CVE | B1136: CVE-2026-27127 | C1136: Craft is a content management system (CMS). In versions 4.5.0-RC1 through 4.16.18 and 5.0.0-RC1 through 5.8.22, the SSRF validation in Craft CMS’s GraphQL Asset mutation performs DNS resolution separately from the HTTP request. This Time-of-Check-Time-of-Use (TOCTOU) vulnerability enables DNS rebinding attacks, where an attacker’s DNS server returns different IP addresses for validation compared to the actual request. This is a bypass of the security fix for CVE-2025-68437 that allows access to | D1136: 6.3 | E1136: MEDIUM | F1136: 2 | G1136: 2 | H1136: MEDIUM | I1136: 10.3 | J1136: NO | K1136: https://nvd.nist.gov/vuln/detail/CVE-2026-27127 | L1136: 2026-02-26 00:15 | M1136: YES | N1136: https://github.com/craftcms/cms/commit/a4cf3fb63bba3249cf1e2882b18a2d29e77a8575 | https://github.com/craftcms/cms/security/advisories/GHSA-gp2f-7wcm-5fhx | https://github.com/craftcms/cms/security/advisories/GHSA-x27p-wfqw-hfcc | O1136: https://github.com/craftcms/cms/security/advisories/GHSA-gp2f-7wcm-5fhx | P1136: craftcms craft_cms * | craftcms craft_cms 3.5.0 | Q1136: P4 | R1136: 📅 Schedule patch deployment within 30 days | 🔍 Monitor for exploitation attempts | S1136: CVE - IP enrichment n/a | T1136: 0 | U1136: 0 | V1136: T1090:Proxy | W1136: 1 | X1136: LOW (40%) | Y1136: UNLIKELY | Z1136: PATCH_AVAILABLE | AA1136: https://nvd.nist.gov/vuln/detail/CVE-2026-27127 | AB1136: NONE | AC1136: 0
... A1152: CVE | B1152: CVE-2026-24314 | C1152: Under certain conditions SAP S/4HANA (Manage Payment Media) allows an authenticated attacker to access information which would otherwise be restricted. This could cause low impact on confidentiality of the application while integrity and availability are not impacted. | D1152: 4.3 | E1152: MEDIUM | F1152: 2 | G1152: 2 | H1152: MEDIUM | I1152: 8.3 | J1152: NO | K1152: https://nvd.nist.gov/vuln/detail/CVE-2026-24314 | L1152: 2026-02-26 00:15 | M1152: CHECK_VENDOR | N1152: See NVD references | O1152: Apply vendor patches | P1152: See CVE details | Q1152: P4 | R1152: 📅 Schedule patch deployment within 30 days | 🔍 Monitor for exploitation attempts | S1152: CVE - IP enrichment n/a | T1152: 0.0003 | U1152: 0.0741 | V1152: T1190:Exploit Public-Facing Application | W1152: 1 | X1152: LOW (40%) | Y1152: UNLIKELY | Z1152: CHECK_VENDOR | AA1152: https://nvd.nist.gov/vuln/detail/CVE-2026-24314 | AB1152: NONE | AC1152: 0
A1153: CVE | B1153: CVE-2025-40538 | C1153: A broken access control vulnerability exists in Serv-U which when exploited, gives a malicious actor the ability to create a system admin user and execute arbitrary code as a privileged account via domain admin or group admin privileges. This issue requires administrative privileges to abuse. On Windows deployments, the risk is scored as a medium because services frequently run under less-privileged service accounts by default. | D1153: 9.1 | E1153: CRITICAL | F1153: 2 | G1153: 3 | H1153: HIGH | I1153: 15.1 | J1153: NO | K1153: https://nvd.nist.gov/vuln/detail/CVE-2025-40538 | L1153: 2026-02-26 00:15 | M1153: YES | N1153: https://documentation.solarwinds.com/en/success_center/servu/content/release_notes/servu_15-5-4_release_notes.htm | https://www.solarwinds.com/trust-center/security-advisories/CVE-2025-40538 | O1153: Apply vendor patches | P1153: solarwinds serv-u * | Q1153: P3 | R1153: 🚨 URGENT: Apply vendor patches immediately | 🔒 Isolate affected systems if patch unavailable | 🛡️ Enable additional monitoring/IDS rules | S1153: CVE - IP enrichment n/a | T1153: 0 | U1153: 0 | V1153: T1203:Exploitation for Client Execution | W1153: 1 | X1153: LOW (40%) | Y1153: UNLIKELY | Z1153: PATCH_AVAILABLE | AA1153: https://nvd.nist.gov/vuln/detail/CVE-2025-40538 | AB1153: NONE | AC1153: 0 | AD1153: [TheHackerNews] SolarWinds Patches 4 Critical Serv-U 15.5 Flaws Allowing Root Code Exe
A1154: CVE | B1154: CVE-2025-40539 | C1154: A type confusion vulnerability exists in Serv-U which when exploited, gives a malicious actor the ability to execute arbitrary native code as privileged account. This issue requires administrative privileges to abuse. On Windows deployments, the risk is scored as a medium because services frequently run under less-privileged service accounts by default. | D1154: 9.1 | E1154: CRITICAL | F1154: 2 | G1154: 3 | H1154: HIGH | I1154: 15.1 | J1154: NO | K1154: https://nvd.nist.gov/vuln/detail/CVE-2025-40539 | L1154: 2026-02-26 00:15 | M1154: YES | N1154: https://documentation.solarwinds.com/en/success_center/servu/content/release_notes/servu_15-5-4_release_notes.htm | https://www.solarwinds.com/trust-center/security-advisories/CVE-2025-40539 | O1154: Apply vendor patches | P1154: solarwinds serv-u * | Q1154: P3 | R1154: 🚨 URGENT: Apply vendor patches immediately | 🔒 Isolate affected systems if patch unavailable | 🛡️ Enable additional monitoring/IDS rules | S1154: CVE - IP enrichment n/a | T1154: 0 | U1154: 0 | V1154: T1190:Exploit Public-Facing Application | W1154: 1 | X1154: LOW (40%) | Y1154: UNLIKELY | Z1154: PATCH_AVAILABLE | AA1154: https://nvd.nist.gov/vuln/detail/CVE-2025-40539 | AB1154: NONE | AC1154: 0
A1155: CVE | B1155: CVE-2025-40540 | C1155: A type confusion vulnerability exists in Serv-U which when exploited, gives a malicious actor the ability to execute arbitrary native code as privileged account. This issue requires administrative privileges to abuse. On Windows deployments, the risk is scored as a medium because services frequently run under less-privileged service accounts by default. | D1155: 9.1 | E1155: CRITICAL | F1155: 2 | G1155: 3 | H1155: HIGH | I1155: 15.1 | J1155: NO | K1155: https://nvd.nist.gov/vuln/detail/CVE-2025-40540 | L1155: 2026-02-26 00:15 | M1155: YES | N1155: https://documentation.solarwinds.com/en/success_center/servu/content/release_notes/servu_15-5-4_release_notes.htm | https://www.solarwinds.com/trust-center/security-advisories/CVE-2025-40540 | O1155: Apply vendor patches | P1155: solarwinds serv-u * | Q1155: P3 | R1155: 🚨 URGENT: Apply vendor patches immediately | 🔒 Isolate affected systems if patch unavailable | 🛡️ Enable additional monitoring/IDS rules | S1155: CVE - IP enrichment n/a | T1155: 0 | U1155: 0 | V1155: T1190:Exploit Public-Facing Application | W1155: 1 | X1155: LOW (40%) | Y1155: UNLIKELY | Z1155: PATCH_AVAILABLE | AA1155: https://nvd.nist.gov/vuln/detail/CVE-2025-40540 | AB1155: NONE | AC1155: 0
A1156: CVE | B1156: CVE-2025-40541 | C1156: An Insecure Direct Object Reference (IDOR) vulnerability exists in Serv-U, which when exploited, gives a malicious actor the ability to execute native code as a privileged account. This issue requires administrative privileges to abuse. On Windows deployments, the risk is scored as a medium because services frequently run under less-privileged service accounts by default. | D1156: 9.1 | E1156: CRITICAL | F1156: 2 | G1156: 3 | H1156: HIGH | I1156: 15.1 | J1156: NO | K1156: https://nvd.nist.gov/vuln/detail/CVE-2025-40541 | L1156: 2026-02-26 00:15 | M1156: YES | N1156: https://documentation.solarwinds.com/en/success_center/servu/content/release_notes/servu_15-5-4_release_notes.htm | https://www.solarwinds.com/trust-center/security-advisories/CVE-2025-40541 | O1156: Apply vendor patches | P1156: solarwinds serv-u * | Q1156: P3 | R1156: 🚨 URGENT: Apply vendor patches immediately | 🔒 Isolate affected systems if patch unavailable | 🛡️ Enable additional monitoring/IDS rules | S1156: CVE - IP enrichment n/a | T1156: 0 | U1156: 0 | V1156: T1190:Exploit Public-Facing Application | W1156: 1 | X1156: LOW (40%) | Y1156: UNLIKELY | Z1156: PATCH_AVAILABLE | AA1156: https://nvd.nist.gov/vuln/detail/CVE-2025-40541 | AB1156: NONE | AC1156: 0
A1157: CVE | B1157: CVE-2026-1229 | C1157: The CombinedMult function in the CIRCL ecc/p384 package (secp384r1 curve) produces an incorrect value for specific inputs. The issue is fixed by using complete addition formulas. ECDH and ECDSA signing relying on this curve are not affected. The bug was fixed in v1.6.3 https://github.com/cloudflare/circl/releases/tag/v1.6.3 . | D1157: 5 | E1157: MEDIUM | F1157: 2 | G1157: 2 | H1157: MEDIUM | I1157: 9 | J1157: NO | K1157: https://nvd.nist.gov/vuln/detail/CVE-2026-1229 | L1157: 2026-02-26 00:15 | M1157: CHECK_VENDOR | N1157: See NVD references | O1157: Apply vendor patches | P1157: See CVE details | Q1157: P4 | R1157: 📅 Schedule patch deployment within 30 days | 🔍 Monitor for exploitation attempts | S1157: CVE - IP enrichment n/a | T1157: 0 | U1157: 0 | V1157: T1190:Exploit Public-Facing Application | W1157: 1 | X1157: LOW (40%) | Y1157: UNLIKELY | Z1157: CHECK_VENDOR | AA1157: https://nvd.nist.gov/vuln/detail/CVE-2026-1229 | AB1157: NONE | AC1157: 0
A1158: CVE | B1158: CVE-2024-1524 | C1158: When the "Silent Just-In-Time Provisioning" feature is enabled for a federated identity provider (IDP) there is a risk that a local user store user's information may be replaced during the account provisioning process in cases where federated users share the same username as local users. There will be no impact on your deployment if any of the preconditions mentioned below are not met. Only when all the preconditions mentioned below are fulfilled could a malicious actor associate a targeted | D1158: 7.7 | E1158: HIGH | F1158: 2 | G1158: 3 | H1158: HIGH | I1158: 13.7 | J1158: NO | K1158: https://nvd.nist.gov/vuln/detail/CVE-2024-1524 | L1158: 2026-02-26 00:15 | M1158: CHECK_VENDOR | N1158: See NVD references | O1158: Apply vendor patches | P1158: See CVE details | Q1158: P3 | R1158: 🚨 URGENT: Apply vendor patches immediately | 🔒 Isolate affected systems if patch unavailable | 🛡️ Enable additional monitoring/IDS rules | S1158: CVE - IP enrichment n/a | T1158: 0.0005 | U1158: 0.1519 | V1158: T1190:Exploit Public-Facing Application | W1158: 1 | X1158: LOW (40%) | Y1158: UNLIKELY | Z1158: CHECK_VENDOR | AA1158: https://nvd.nist.gov/vuln/detail/CVE-2024-1524 | AB1158: NONE | AC1158: 0
A1159: CVE | B1159: CVE-2025-11165 | C1159: A sandbox escape vulnerability exists in dotCMS’s Velocity scripting engine (VTools) that allows authenticated users with scripting privileges to bypass class and package restrictions enforced by SecureUberspectorImpl. By dynamically modifying the Velocity engine’s runtime configuration and reinitializing its Uberspect, a malicious actor can remove the introspector.restrict.classes and introspector.restrict.packages protections. Once these restrictions are cleared, the attacker can access arbi | D1159: 8.5 | E1159: HIGH | F1159: 2 | G1159: 3 | H1159: HIGH | I1159: 14.5 | J1159: NO | K1159: https://nvd.nist.gov/vuln/detail/CVE-2025-11165 | L1159: 2026-02-26 00:15 | M1159: CHECK_VENDOR | N1159: See NVD references | O1159: Apply vendor patches | P1159: See CVE details | Q1159: P3 | R1159: 🚨 URGENT: Apply vendor patches immediately | 🔒 Isolate affected systems if patch unavailable | 🛡️ Enable additional monitoring/IDS rules | S1159: CVE - IP enrichment n/a | T1159: 0 | U1159: 0 | V1159: T1190:Exploit Public-Facing Application | W1159: 1 | X1159: LOW (40%) | Y1159: UNLIKELY | Z1159: CHECK_VENDOR | AA1159: https://nvd.nist.gov/vuln/detail/CVE-2025-11165 | AB1159: NONE | AC1159: 0
A1160: CVE | B1160: CVE-2024-56373 | C1160: DAG Author (who already has quite a lot of permissions) could manipulate database of Airflow 2 in the way to execute arbitrary code in the web-server context, which they should normally not be able to do, leading to potentially remote code execution in the context of web-server (server-side) as a result of a user viewing historical task information. The functionality responsible for that (log template history) has been disabled by default in 2.11.1 and users should upgrade to Airflow 3 if they | D1160: 8.4 | E1160: HIGH | F1160: 2 | G1160: 3 | H1160: HIGH | I1160: 14.4 | J1160: NO | K1160: https://nvd.nist.gov/vuln/detail/CVE-2024-56373 | L1160: 2026-02-26 00:15 | M1160: YES | N1160: https://lists.apache.org/thread/2vrmrhcht6g7cp5yjxpnrk2wtrncm6cy | O1160: Apply vendor patches | P1160: apache airflow * | Q1160: P1 | R1160: 🚨 URGENT: Apply vendor patches immediately | 🔒 Isolate affected systems if patch unavailable | 🛡️ Enable additional monitoring/IDS rules | S1160: CVE - IP enrichment n/a | T1160: 0 | U1160: 0 | V1160: T1059:Command and Scripting Interpreter | T1190:Exploit Public-Facing Application | T1210:Exploitation of Remote Services | W1160: 2 | X1160: HIGH (72%) | Y1160: HIGH | Z1160: PATCH_AVAILABLE | AA1160: https://nvd.nist.gov/vuln/detail/CVE-2024-56373 | AB1160: http://www.zerodayinitiative.com/advisories/ZDI-26-123/ | AC1160: 0
A1161: CVE | B1161: CVE-2025-27555 | C1161: Airflow versions before 2.11.1 have a vulnerability that allows authenticated users with audit log access to see sensitive values in audit logs which they should not see. When sensitive connection parameters were set via airflow CLI, values of those variables appeared in the audit log and were stored unencrypted in the Airflow database. While this risk is limited to users with audit log access, it is recommended to upgrade to Airflow 2.11.1 or a later version, which addresses this issue. Users w | D1161: 6.5 | E1161: MEDIUM | F1161: 2 | G1161: 2 | H1161: MEDIUM | I1161: 10.5 | J1161: NO | K1161: https://nvd.nist.gov/vuln/detail/CVE-2025-27555 | L1161: 2026-02-26 00:15 | M1161: YES | N1161: https://lists.apache.org/thread/nxovkp319jo8vg498gql1yswtb2frbkw | O1161: Apply vendor patches | P1161: apache airflow * | Q1161: P1 | R1161: 📅 Schedule patch deployment within 30 days | 🔍 Monitor for exploitation attempts | S1161: CVE - IP enrichment n/a | T1161: 0.0003 | U1161: 0.0968 | V1161: T1190:Exploit Public-Facing Application | W1161: 2 | X1161: HIGH (72%) | Y1161: HIGH | Z1161: PATCH_AVAILABLE | AA1161: https://nvd.nist.gov/vuln/detail/CVE-2025-27555 | AB1161: http://www.zerodayinitiative.com/advisories/ZDI-26-123/ | AC1161: 0
A1162: CVE | B1162: CVE-2026-2664 | C1162: An out of bounds read vulnerability in the grpcfuse kernel module present in the Linux VM in Docker Desktop for Windows, Linux and macOS up to version 4.61.0 could allow a local attacker to cause an unspecified impact by writing to /proc/docker entries. The issue has been fixed in Docker Desktop 4.62.0 . | D1162: 5 | E1162: MEDIUM | F1162: 2 | G1162: 2 | H1162: MEDIUM | I1162: 9 | J1162: NO | K1162: https://nvd.nist.gov/vuln/detail/CVE-2026-2664 | L1162: 2026-02-26 00:15 | M1162: CHECK_VENDOR | N1162: See NVD references | O1162: Apply vendor patches | P1162: See CVE details | Q1162: P1 | R1162: 📅 Schedule patch deployment within 30 days | 🔍 Monitor for exploitation attempts | S1162: CVE - IP enrichment n/a | T1162: 0 | U1162: 0 | V1162: T1203:Exploitation for Client Execution | W1162: 2 | X1162: HIGH (72%) | Y1162: HIGH | Z1162: CHECK_VENDOR | AA1162: https://nvd.nist.gov/vuln/detail/CVE-2026-2664 | AB1162: http://www.zerodayinitiative.com/advisories/ZDI-26-125/ | AC1162: 0
A1163: CVE | B1163: CVE-2025-14577 | C1163: Slican NCP/IPL/IPM/IPU devices are vulnerable to PHP Function Injection. An unauthenticated remote attacker is able to execute arbitrary PHP commands by sending specially crafted requests to /webcti/session_ajax.php endpoint. This issue was fixed in version 1.24.0190 (Slican NCP) and 6.61.0010 (Slican IPL/IPM/IPU). | D1163: 8.5 | E1163: HIGH | F1163: 2 | G1163: 3 | H1163: HIGH | I1163: 14.5 | J1163: NO | K1163: https://nvd.nist.gov/vuln/detail/CVE-2025-14577 | L1163: 2026-02-26 00:15 | M1163: CHECK_VENDOR | N1163: See NVD references | O1163: Apply vendor patches | P1163: See CVE details | Q1163: P3 | R1163: 🚨 URGENT: Apply vendor patches immediately | 🔒 Isolate affected systems if patch unavailable | 🛡️ Enable additional monitoring/IDS rules | S1163: CVE - IP enrichment n/a | T1163: 0 | U1163: 0 | V1163: T1078:Valid Accounts | W1163: 1 | X1163: LOW (40%) | Y1163: UNLIKELY | Z1163: CHECK_VENDOR | AA1163: https://nvd.nist.gov/vuln/detail/CVE-2025-14577 | AB1163: NONE | AC1163: 0
A1164: CVE | B1164: CVE-2026-1772 | C1164: RTU500 web interface: An unprivileged user can read user management information. The information cannot be accessed via the RTU500 web user interface but requires further tools like browser development utilities to access them without required privileges. | D1164: 5 | E1164: MEDIUM | F1164: 2 | G1164: 2 | H1164: MEDIUM | I1164: 9 | J1164: NO | K1164: https://nvd.nist.gov/vuln/detail/CVE-2026-1772 | L1164: 2026-02-26 00:15 | M1164: CHECK_VENDOR | N1164: See NVD references | O1164: Apply vendor patches | P1164: See CVE details | Q1164: P4 | R1164: 📅 Schedule patch deployment within 30 days | 🔍 Monitor for exploitation attempts | S1164: CVE - IP enrichment n/a | T1164: 0 | U1164: 0 | V1164: T1190:Exploit Public-Facing Application | W1164: 1 | X1164: LOW (40%) | Y1164: UNLIKELY | Z1164: CHECK_VENDOR | AA1164: https://nvd.nist.gov/vuln/detail/CVE-2026-1772 | AB1164: NONE | AC1164: 0
A1165: CVE | B1165: CVE-2026-1773 | C1165: IEC 60870-5-104: Potential Denial of Service impact on reception of invalid U-format frame. Product is only affected if IEC 60870-5-104 bi-directional functionality is configured. Enabling secure communication following IEC 62351-3 does not remediate the vulnerability but mitigates the risk of exploitation. | D1165: 5 | E1165: MEDIUM | F1165: 2 | G1165: 2 | H1165: MEDIUM | I1165: 9 | J1165: NO | K1165: https://nvd.nist.gov/vuln/detail/CVE-2026-1773 | L1165: 2026-02-26 00:15 | M1165: CHECK_VENDOR | N1165: See NVD references | O1165: Apply vendor patches | P1165: See CVE details | Q1165: P4 | R1165: 📅 Schedule patch deployment within 30 days | 🔍 Monitor for exploitation attempts | S1165: CVE - IP enrichment n/a | T1165: 0 | U1165: 0 | V1165: T1499:Endpoint Denial of Service | W1165: 1 | X1165: LOW (40%) | Y1165: UNLIKELY | Z1165: CHECK_VENDOR | AA1165: https://nvd.nist.gov/vuln/detail/CVE-2026-1773 | AB1165: NONE | AC1165: 0
... A1428: CVE | B1428: CVE-2026-20126 | C1428: A vulnerability in Cisco Catalyst SD-WAN Manager could allow an authenticated, local attacker with low privileges to gain root privileges on the underlying operating system. This vulnerability is due to an insufficient user authentication mechanism in the REST API. An attacker could exploit this vulnerability by sending a request to the REST API of the affected system. A successful exploit could allow the attacker to&nbsp;gain root privileges on the underlying operating system. | D1428: 8.8 | E1428: HIGH | F1428: 2 | G1428: 3 | H1428: HIGH | I1428: 14.8 | J1428: NO | K1428: https://nvd.nist.gov/vuln/detail/CVE-2026-20126 | L1428: 2026-02-26 00:15 | M1428: CHECK_VENDOR | N1428: See NVD references | O1428: Apply vendor patches | P1428: See CVE details | Q1428: P3 | R1428: 🚨 URGENT: Apply vendor patches immediately | 🔒 Isolate affected systems if patch unavailable | 🛡️ Enable additional monitoring/IDS rules | S1428: CVE - IP enrichment n/a | T1428: 0 | U1428: 0 | V1428: T1190:Exploit Public-Facing Application | W1428: 1 | X1428: LOW (40%) | Y1428: UNLIKELY | Z1428: CHECK_VENDOR | AA1428: https://nvd.nist.gov/vuln/detail/CVE-2026-20126 | AB1428: NONE | AC1428: 0
A1429: CVE | B1429: CVE-2026-20127 | C1429: A vulnerability in the peering authentication in Cisco Catalyst SD-WAN Controller, formerly SD-WAN vSmart, and Cisco Catalyst SD-WAN Manager, formerly SD-WAN vManage, could allow an unauthenticated, remote attacker to bypass authentication and obtain administrative privileges on an affected system. This vulnerability exists because the peering authentication mechanism in an affected system is not working properly. An attacker could exploit this vulnerability by sending crafted requests to an | D1429: 10 | E1429: CRITICAL | F1429: 3 | G1429: 3 | H1429: CRITICAL | I1429: 19 | J1429: YES | K1429: https://nvd.nist.gov/vuln/detail/CVE-2026-20127 | L1429: 2026-02-26 00:15 | M1429: CHECK_VENDOR | N1429: See NVD references | O1429: Apply vendor patches | P1429: See CVE details | Q1429: P1 | R1429: 🚨 URGENT: Apply vendor patches immediately | 🔒 Isolate affected systems if patch unavailable | 🛡️ Enable additional monitoring/IDS rules | S1429: CVE - IP enrichment n/a | T1429: 0 | U1429: 0 | V1429: T1078:Valid Accounts | T1110:Brute Force | W1429: 2 | X1429: HIGH (72%) | Y1429: CONFIRMED | Z1429: CHECK_VENDOR | AA1429: https://nvd.nist.gov/vuln/detail/CVE-2026-20127 | AB1429: NONE | AC1429: 0 | AD1429: [BleepingComputer] Critical Cisco SD-WAN bug exploited in zero-day attacks since 2023
A1430: CVE | B1430: CVE-2026-20128 | C1430: A vulnerability in the Data Collection Agent (DCA) feature of Cisco Catalyst SD-WAN Manager could allow an authenticated, local attacker to gain DCA user privileges on an affected system. To exploit this vulnerability, the attacker must have valid&nbsp;vmanage credentials on the affected system. This vulnerability is due to the presence of a credential file for the DCA user on an affected system. An attacker could exploit this vulnerability by accessing the filesystem as a low-privileged user | D1430: 7.5 | E1430: HIGH | F1430: 2 | G1430: 3 | H1430: HIGH | I1430: 13.5 | J1430: NO | K1430: https://nvd.nist.gov/vuln/detail/CVE-2026-20128 | L1430: 2026-02-26 00:15 | M1430: CHECK_VENDOR | N1430: See NVD references | O1430: Apply vendor patches | P1430: See CVE details | Q1430: P3 | R1430: 🚨 URGENT: Apply vendor patches immediately | 🔒 Isolate affected systems if patch unavailable | 🛡️ Enable additional monitoring/IDS rules | S1430: CVE - IP enrichment n/a | T1430: 0 | U1430: 0 | V1430: T1552:Unsecured Credentials | W1430: 1 | X1430: LOW (40%) | Y1430: UNLIKELY | Z1430: CHECK_VENDOR | AA1430: https://nvd.nist.gov/vuln/detail/CVE-2026-20128 | AB1430: NONE | AC1430: 0
A1431: CVE | B1431: CVE-2026-20129 | C1431: A vulnerability in the API user authentication of Cisco Catalyst SD-WAN Manager could allow an unauthenticated, remote attacker to gain access to an affected system as a user who has the&nbsp;netadmin role. The vulnerability is due to improper authentication for requests that are sent to the API. An attacker could exploit this vulnerability by sending a crafted request to the API of an affected system. A successful exploit could allow the attacker to execute commands with the privileges of th | D1431: 9.8 | E1431: CRITICAL | F1431: 2 | G1431: 3 | H1431: HIGH | I1431: 15.8 | J1431: NO | K1431: https://nvd.nist.gov/vuln/detail/CVE-2026-20129 | L1431: 2026-02-26 00:15 | M1431: CHECK_VENDOR | N1431: See NVD references | O1431: Apply vendor patches | P1431: See CVE details | Q1431: P3 | R1431: 🚨 URGENT: Apply vendor patches immediately | 🔒 Isolate affected systems if patch unavailable | 🛡️ Enable additional monitoring/IDS rules | S1431: CVE - IP enrichment n/a | T1431: 0 | U1431: 0 | V1431: T1078:Valid Accounts | T1110:Brute Force | W1431: 1 | X1431: LOW (40%) | Y1431: UNLIKELY | Z1431: CHECK_VENDOR | AA1431: https://nvd.nist.gov/vuln/detail/CVE-2026-20129 | AB1431: NONE | AC1431: 0
A1432: CVE | B1432: CVE-2026-20133 | C1432: A vulnerability in Cisco Catalyst SD-WAN Manager could allow an unauthenticated, remote attacker to view sensitive information on an affected system. This vulnerability is due to insufficient file system access restrictions. An attacker could exploit this vulnerability by accessing the API of an affected system. A successful exploit could allow the attacker to read sensitive information on the underlying operating system. | D1432: 6.5 | E1432: MEDIUM | F1432: 2 | G1432: 2 | H1432: MEDIUM | I1432: 10.5 | J1432: NO | K1432: https://nvd.nist.gov/vuln/detail/CVE-2026-20133 | L1432: 2026-02-26 00:15 | M1432: CHECK_VENDOR | N1432: See NVD references | O1432: Apply vendor patches | P1432: See CVE details | Q1432: P4 | R1432: 📅 Schedule patch deployment within 30 days | 🔍 Monitor for exploitation attempts | S1432: CVE - IP enrichment n/a | T1432: 0 | U1432: 0 | V1432: T1213:Data from Information Repositories | W1432: 1 | X1432: LOW (40%) | Y1432: UNLIKELY | Z1432: CHECK_VENDOR | AA1432: https://nvd.nist.gov/vuln/detail/CVE-2026-20133 | AB1432: NONE | AC1432: 0
A1433: CVE | B1433: CVE-2026-26717 | C1433: An issue in OpenFUN Richie (LMS) in src/richie/apps/courses/api.py. The application used the non-constant time == operator for HMAC signature verification in the sync_course_run_from_request function. This allows remote attackers to forge valid signatures and bypass authentication by measuring response time discrepancies | D1433: 5 | E1433: MEDIUM | F1433: 2 | G1433: 2 | H1433: MEDIUM | I1433: 9 | J1433: NO | K1433: https://nvd.nist.gov/vuln/detail/CVE-2026-26717 | L1433: 2026-02-26 00:15 | M1433: CHECK_VENDOR | N1433: See NVD references | O1433: Apply vendor patches | P1433: See CVE details | Q1433: P4 | R1433: 📅 Schedule patch deployment within 30 days | 🔍 Monitor for exploitation attempts | S1433: CVE - IP enrichment n/a | T1433: 0 | U1433: 0 | V1433: T1190:Exploit Public-Facing Application | W1433: 1 | X1433: LOW (40%) | Y1433: UNLIKELY | Z1433: CHECK_VENDOR | AA1433: https://nvd.nist.gov/vuln/detail/CVE-2026-26717 | AB1433: NONE | AC1433: 0
A1434: CVE | B1434: CVE-2026-27705 | C1434: Plane is an an open-source project management tool. Prior to version 1.2.2, the `ProjectAssetEndpoint.patch()` method in `apps/api/plane/app/views/asset/v2.py` (lines 579–593) performs a global asset lookup using only the asset ID (`pk`) via `FileAsset.objects.get(id=pk)`, without verifying that the asset belongs to the workspace and project specified in the URL path. This allows any authenticated user (including those with the GUEST role) to modify the `attributes` and `is_uploaded` status of a | D1434: 8.5 | E1434: HIGH | F1434: 2 | G1434: 3 | H1434: HIGH | I1434: 14.5 | J1434: NO | K1434: https://nvd.nist.gov/vuln/detail/CVE-2026-27705 | L1434: 2026-02-26 00:15 | M1434: CHECK_VENDOR | N1434: See NVD references | O1434: Apply vendor patches | P1434: See CVE details | Q1434: P3 | R1434: 🚨 URGENT: Apply vendor patches immediately | 🔒 Isolate affected systems if patch unavailable | 🛡️ Enable additional monitoring/IDS rules | S1434: CVE - IP enrichment n/a | T1434: 0 | U1434: 0 | V1434: T1190:Exploit Public-Facing Application | W1434: 1 | X1434: LOW (40%) | Y1434: UNLIKELY | Z1434: CHECK_VENDOR | AA1434: https://nvd.nist.gov/vuln/detail/CVE-2026-27705 | AB1434: NONE | AC1434: 0
A1435: CVE | B1435: CVE-2026-27706 | C1435: Plane is an an open-source project management tool. Prior to version 1.2.2, a Full Read Server-Side Request Forgery (SSRF) vulnerability has been identified in the "Add Link" feature. This flaw allows an authenticated attacker with general user privileges to send arbitrary GET requests to the internal network and exfiltrate the full response body. By exploiting this vulnerability, an attacker can steal sensitive data from internal services and cloud metadata endpoints. Version 1.2.2 fixes the is | D1435: 7.7 | E1435: HIGH | F1435: 2 | G1435: 3 | H1435: HIGH | I1435: 13.7 | J1435: NO | K1435: https://nvd.nist.gov/vuln/detail/CVE-2026-27706 | L1435: 2026-02-26 00:15 | M1435: CHECK_VENDOR | N1435: See NVD references | O1435: Apply vendor patches | P1435: See CVE details | Q1435: P3 | R1435: 🚨 URGENT: Apply vendor patches immediately | 🔒 Isolate affected systems if patch unavailable | 🛡️ Enable additional monitoring/IDS rules | S1435: CVE - IP enrichment n/a | T1435: 0 | U1435: 0 | V1435: T1090:Proxy | T1190:Exploit Public-Facing Application | W1435: 1 | X1435: LOW (40%) | Y1435: UNLIKELY | Z1435: CHECK_VENDOR | AA1435: https://nvd.nist.gov/vuln/detail/CVE-2026-27706 | AB1435: NONE | AC1435: 0
A1436: CVE | B1436: CVE-2026-27727 | C1436: mchange-commons-java, a library that provides Java utilities, includes code that mirrors early implementations of JNDI functionality, including support for remote `factoryClassLocation` values, by which code can be downloaded and invoked within a running application. If an attacker can provoke an application to read a maliciously crafted `jaxax.naming.Reference` or serialized object, they can provoke the download and execution of malicious code. Implementations of this functionality within the J | D1436: 5 | E1436: MEDIUM | F1436: 2 | G1436: 2 | H1436: MEDIUM | I1436: 9 | J1436: NO | K1436: https://nvd.nist.gov/vuln/detail/CVE-2026-27727 | L1436: 2026-02-26 00:15 | M1436: CHECK_VENDOR | N1436: See NVD references | O1436: Apply vendor patches | P1436: See CVE details | Q1436: P4 | R1436: 📅 Schedule patch deployment within 30 days | 🔍 Monitor for exploitation attempts | S1436: CVE - IP enrichment n/a | T1436: 0 | U1436: 0 | V1436: T1190:Exploit Public-Facing Application | W1436: 1 | X1436: LOW (40%) | Y1436: UNLIKELY | Z1436: CHECK_VENDOR | AA1436: https://nvd.nist.gov/vuln/detail/CVE-2026-27727 | AB1436: NONE | AC1436: 0
A1437: CVE | B1437: CVE-2026-27728 | C1437: OneUptime is a solution for monitoring and managing online services. Prior to version 10.0.7, an OS command injection vulnerability in `NetworkPathMonitor.performTraceroute()` allows any authenticated project user to execute arbitrary operating system commands on the Probe server by injecting shell metacharacters into a monitor's destination field. Version 10.0.7 fixes the vulnerability. | D1437: 9.9 | E1437: CRITICAL | F1437: 2 | G1437: 3 | H1437: HIGH | I1437: 15.9 | J1437: NO | K1437: https://nvd.nist.gov/vuln/detail/CVE-2026-27728 | L1437: 2026-02-26 00:15 | M1437: CHECK_VENDOR | N1437: See NVD references | O1437: Apply vendor patches | P1437: See CVE details | Q1437: P3 | R1437: 🚨 URGENT: Apply vendor patches immediately | 🔒 Isolate affected systems if patch unavailable | 🛡️ Enable additional monitoring/IDS rules | S1437: CVE - IP enrichment n/a | T1437: 0 | U1437: 0 | V1437: T1059:Command and Scripting Interpreter | W1437: 1 | X1437: LOW (40%) | Y1437: UNLIKELY | Z1437: CHECK_VENDOR | AA1437: https://nvd.nist.gov/vuln/detail/CVE-2026-27728 | AB1437: NONE | AC1437: 0
A1438: CVE | B1438: CVE-2026-27736 | C1438: BigBlueButton is an open-source virtual classroom. In versions on the 3.x branch prior to 3.0.20, the string received with errorRedirectUrl lacks validation, using it directly in the respondWithRedirect function leads to an Open Redirect vulnerability. BigBlueButton 3.0.20 patches the issue. No known workarounds are available. | D1438: 6.1 | E1438: MEDIUM | F1438: 2 | G1438: 2 | H1438: MEDIUM | I1438: 10.1 | J1438: NO | K1438: https://nvd.nist.gov/vuln/detail/CVE-2026-27736 | L1438: 2026-02-26 00:15 | M1438: CHECK_VENDOR | N1438: See NVD references | O1438: Apply vendor patches | P1438: See CVE details | Q1438: P4 | R1438: 📅 Schedule patch deployment within 30 days | 🔍 Monitor for exploitation attempts | S1438: CVE - IP enrichment n/a | T1438: 0 | U1438: 0 | V1438: T1189:Drive-by Compromise | T1190:Exploit Public-Facing Application | W1438: 1 | X1438: LOW (40%) | Y1438: UNLIKELY | Z1438: CHECK_VENDOR | AA1438: https://nvd.nist.gov/vuln/detail/CVE-2026-27736 | AB1438: NONE | AC1438: 0
A1439: CVE | B1439: CVE-2026-27738 | C1439: The Angular SSR is a server-rise rendering tool for Angular applications. An Open Redirect vulnerability exists in the internal URL processing logic in versions on the 19.x branch prior to 19.2.21, the 20.x branch prior to 20.3.17, and the 21.x branch prior to 21.1.5 and 21.2.0-rc.1. The logic normalizes URL segments by stripping leading slashes; however, it only removes a single leading slash. When an Angular SSR application is deployed behind a proxy that passes the `X-Forwarded-Prefix` header | D1439: 5 | E1439: MEDIUM | F1439: 2 | G1439: 2 | H1439: MEDIUM | I1439: 9 | J1439: NO | K1439: https://nvd.nist.gov/vuln/detail/CVE-2026-27738 | L1439: 2026-02-26 00:15 | M1439: CHECK_VENDOR | N1439: See NVD references | O1439: Apply vendor patches | P1439: See CVE details | Q1439: P4 | R1439: 📅 Schedule patch deployment within 30 days | 🔍 Monitor for exploitation attempts | S1439: CVE - IP enrichment n/a | T1439: 0 | U1439: 0 | V1439: T1189:Drive-by Compromise | T1566:Phishing | W1439: 1 | X1439: LOW (40%) | Y1439: UNLIKELY | Z1439: CHECK_VENDOR | AA1439: https://nvd.nist.gov/vuln/detail/CVE-2026-27738 | AB1439: NONE | AC1439: 0
A1440: CVE | B1440: CVE-2026-27849 | C1440: Due to missing neutralization of special elements, OS commands can be injected via the update functionality of a TLS-SRP connection, which is normally used for configuring devices inside the mesh network. This issue affects MR9600: 1.0.4.205530; MX4200: 1.0.13.210200. | D1440: 5 | E1440: MEDIUM | F1440: 2 | G1440: 2 | H1440: MEDIUM | I1440: 9 | J1440: NO | K1440: https://nvd.nist.gov/vuln/detail/CVE-2026-27849 | L1440: 2026-02-26 00:15 | M1440: CHECK_VENDOR | N1440: See NVD references | O1440: Apply vendor patches | P1440: See CVE details | Q1440: P4 | R1440: 📅 Schedule patch deployment within 30 days | 🔍 Monitor for exploitation attempts | S1440: CVE - IP enrichment n/a | T1440: 0 | U1440: 0 | V1440: T1059:Command and Scripting Interpreter | W1440: 1 | X1440: LOW (40%) | Y1440: UNLIKELY | Z1440: CHECK_VENDOR | AA1440: https://nvd.nist.gov/vuln/detail/CVE-2026-27849 | AB1440: NONE | AC1440: 0
A1441: CVE | B1441: CVE-2026-3189 | C1441: A weakness has been identified in feiyuchuixue sz-boot-parent up to 1.3.2-beta. This vulnerability affects unknown code of the file /api/admin/common/files/download. Executing a manipulation of the argument url can lead to server-side request forgery. The attack can be executed remotely. Attacks of this nature are highly complex. It is stated that the exploitability is difficult. Upgrading to version 1.3.3-beta is able to resolve this issue. This patch is called aefaabfd7527188bfba3c8c9eee17c316 | D1441: 3.1 | E1441: LOW | F1441: 2 | G1441: 1 | H1441: LOW | I1441: 5.1 | J1441: NO | K1441: https://nvd.nist.gov/vuln/detail/CVE-2026-3189 | L1441: 2026-02-26 00:15 | M1441: CHECK_VENDOR | N1441: See NVD references | O1441: Apply vendor patches | P1441: See CVE details | Q1441: P4 | R1441: 📅 Schedule patch deployment within 30 days | 🔍 Monitor for exploitation attempts | S1441: CVE - IP enrichment n/a | T1441: 0 | U1441: 0 | V1441: T1090:Proxy | W1441: 1 | X1441: LOW (40%) | Y1441: UNLIKELY | Z1441: CHECK_VENDOR | AA1441: https://nvd.nist.gov/vuln/detail/CVE-2026-3189 | AB1441: NONE | AC1441: 0
... A1561: MAL_URL | B1561: 3785687 | C1561: Malware Host [online]: http://118.107.41.238:808/linux_amd64 | Threat: malware_download | Tags: Kaiji,mirai,opendir | D1561: 7.5 | E1561: HIGH | F1561: 3 | G1561: 2 | H1561: HIGH | I1561: 13.5 | J1561: NO | K1561: https://urlhaus.abuse.ch/url/3785687/ | L1561: 2026-02-25 20:23:57 | M1561: Block URL | N1561: https://urlhaus.abuse.ch/url/3785687/ | O1561: Block URL in proxy/firewall: http://118.107.41.238:808/linux_amd64 | P1561: Network/Web Proxy | Q1561: P3 | R1561: 🚫 Block URLs in web proxy/firewall | 📧 Update email security filters | 👥 User awareness training recommended | S1561: URL IOC - check host IP separately | T1561: 0 | U1561: 0 | V1561: T1189:Drive-by Compromise | T1566:Phishing | W1561: 1 | X1561: LOW (40%) | Y1561: YES | Z1561: Block URL | AA1561: https://urlhaus.abuse.ch/url/3785687/ | AB1561: NONE | AC1561: 0
A1562: PHISH | C1562: Phishing site targeting: www.roblox.com.ml | URL: https://www.roblox.com.ml/users/5374857739/profile | D1562: 6 | E1562: MEDIUM | F1562: 3 | G1562: 1 | H1562: MEDIUM | I1562: 9 | J1562: NO | K1562: https://www.roblox.com.ml/users/5374857739/profile | L1562: 2026-02-25T22:13:13+00:00 | M1562: Block URL | N1562: https://www.roblox.com.ml/users/5374857739/profile | O1562: Block phishing URL | Warn users about www.roblox.com.ml impersonation | P1562: Email users / www.roblox.com.ml | Q1562: P4 | R1562: 🚫 Block URLs in web proxy/firewall | 📧 Update email security filters | 👥 User awareness training recommended | S1562: Phishing URL | T1562: 0 | U1562: 0 | V1562: T1566:Phishing | T1566.002:Spearphishing Link | W1562: 1 | X1562: LOW (40%) | Y1562: NONE | Z1562: NONE | AA1562: https://www.roblox.com.ml/users/5374857739/profile | AB1562: NONE | AC1562: 0
A1563: PHISH | C1563: Phishing site targeting: chhayajat.github.io | URL: http://chhayajat.github.io/Netflix-Clone | D1563: 6 | E1563: MEDIUM | F1563: 3 | G1563: 1 | H1563: MEDIUM | I1563: 9 | J1563: NO | K1563: http://chhayajat.github.io/Netflix-Clone | L1563: 2026-02-25T22:13:13+00:00 | M1563: Block URL | N1563: http://chhayajat.github.io/Netflix-Clone | O1563: Block phishing URL | Warn users about chhayajat.github.io impersonation | P1563: Email users / chhayajat.github.io | Q1563: P4 | R1563: 🚫 Block URLs in web proxy/firewall | 📧 Update email security filters | 👥 User awareness training recommended | S1563: Phishing URL | T1563: 0 | U1563: 0 | V1563: T1566:Phishing | T1566.002:Spearphishing Link | W1563: 1 | X1563: LOW (40%) | Y1563: NONE | Z1563: NONE | AA1563: http://chhayajat.github.io/Netflix-Clone | AB1563: NONE | AC1563: 0
A1564: PHISH | C1564: Phishing site targeting: meetbatra.github.io | URL: http://meetbatra.github.io/netflix-clone | D1564: 6 | E1564: MEDIUM | F1564: 3 | G1564: 1 | H1564: MEDIUM | I1564: 9 | J1564: NO | K1564: http://meetbatra.github.io/netflix-clone | L1564: 2026-02-25T22:13:13+00:00 | M1564: Block URL | N1564: http://meetbatra.github.io/netflix-clone | O1564: Block phishing URL | Warn users about meetbatra.github.io impersonation | P1564: Email users / meetbatra.github.io | Q1564: P4 | R1564: 🚫 Block URLs in web proxy/firewall | 📧 Update email security filters | 👥 User awareness training recommended | S1564: Phishing URL | T1564: 0 | U1564: 0 | V1564: T1566:Phishing | T1566.002:Spearphishing Link | W1564: 1 | X1564: LOW (40%) | Y1564: NONE | Z1564: NONE | AA1564: http://meetbatra.github.io/netflix-clone | AB1564: NONE | AC1564: 0
A1565: PHISH | C1565: Phishing site targeting: ashutoshp-dev.github.io | URL: http://ashutoshp-dev.github.io/NetFlix-Home-UI-Clone | D1565: 6 | E1565: MEDIUM | F1565: 3 | G1565: 1 | H1565: MEDIUM | I1565: 9 | J1565: NO | K1565: http://ashutoshp-dev.github.io/NetFlix-Home-UI-Clone | L1565: 2026-02-25T22:13:13+00:00 | M1565: Block URL | N1565: http://ashutoshp-dev.github.io/NetFlix-Home-UI-Clone | O1565: Block phishing URL | Warn users about ashutoshp-dev.github.io impersonation | P1565: Email users / ashutoshp-dev.github.io | Q1565: P4 | R1565: 🚫 Block URLs in web proxy/firewall | 📧 Update email security filters | 👥 User awareness training recommended | S1565: Phishing URL | T1565: 0 | U1565: 0 | V1565: T1566:Phishing | T1566.002:Spearphishing Link | W1565: 1 | X1565: LOW (40%) | Y1565: NONE | Z1565: NONE | AA1565: http://ashutoshp-dev.github.io/NetFlix-Home-UI-Clone | AB1565: NONE | AC1565: 0
A1566: PHISH | C1566: Phishing site targeting: lzrstbg6gtre5.af849df.workers.dev | URL: http://lzrstbg6gtre5.af849df.workers.dev/ | D1566: 6 | E1566: MEDIUM | F1566: 3 | G1566: 1 | H1566: MEDIUM | I1566: 9 | J1566: NO | K1566: http://lzrstbg6gtre5.af849df.workers.dev/ | L1566: 2026-02-25T22:13:13+00:00 | M1566: Block URL | N1566: http://lzrstbg6gtre5.af849df.workers.dev/ | O1566: Block phishing URL | Warn users about lzrstbg6gtre5.af849df.workers.dev impersonation | P1566: Email users / lzrstbg6gtre5.af849df.workers.dev | Q1566: P4 | R1566: 🚫 Block URLs in web proxy/firewall | 📧 Update email security filters | 👥 User awareness training recommended | S1566: Phishing URL | T1566: 0 | U1566: 0 | V1566: T1566:Phishing | T1566.002:Spearphishing Link | W1566: 1 | X1566: LOW (40%) | Y1566: NONE | Z1566: NONE | AA1566: http://lzrstbg6gtre5.af849df.workers.dev/ | AB1566: NONE | AC1566: 0
A1567: PHISH | C1567: Phishing site targeting: www.e135k.xyz | URL: http://www.e135k.xyz/ | D1567: 6 | E1567: MEDIUM | F1567: 3 | G1567: 1 | H1567: MEDIUM | I1567: 9 | J1567: NO | K1567: http://www.e135k.xyz/ | L1567: 2026-02-25T22:13:13+00:00 | M1567: Block URL | N1567: http://www.e135k.xyz/ | O1567: Block phishing URL | Warn users about www.e135k.xyz impersonation | P1567: Email users / www.e135k.xyz | Q1567: P4 | R1567: 🚫 Block URLs in web proxy/firewall | 📧 Update email security filters | 👥 User awareness training recommended | S1567: Phishing URL | T1567: 0 | U1567: 0 | V1567: T1566:Phishing | T1566.002:Spearphishing Link | W1567: 1 | X1567: LOW (40%) | Y1567: NONE | Z1567: NONE | AA1567: http://www.e135k.xyz/ | AB1567: NONE | AC1567: 0
A1568: PHISH | C1568: Phishing site targeting: chaitanybhute.github.io | URL: http://chaitanybhute.github.io/Netflix_Frontend | D1568: 6 | E1568: MEDIUM | F1568: 3 | G1568: 1 | H1568: MEDIUM | I1568: 9 | J1568: NO | K1568: http://chaitanybhute.github.io/Netflix_Frontend | L1568: 2026-02-25T22:13:13+00:00 | M1568: Block URL | N1568: http://chaitanybhute.github.io/Netflix_Frontend | O1568: Block phishing URL | Warn users about chaitanybhute.github.io impersonation | P1568: Email users / chaitanybhute.github.io | Q1568: P4 | R1568: 🚫 Block URLs in web proxy/firewall | 📧 Update email security filters | 👥 User awareness training recommended | S1568: Phishing URL | T1568: 0 | U1568: 0 | V1568: T1566:Phishing | T1566.002:Spearphishing Link | W1568: 1 | X1568: LOW (40%) | Y1568: NONE | Z1568: NONE | AA1568: http://chaitanybhute.github.io/Netflix_Frontend | AB1568: NONE | AC1568: 0
A1569: PHISH | C1569: Phishing site targeting: swisspost.photocollect.io | URL: https://swisspost.photocollect.io/auth/login | D1569: 6 | E1569: MEDIUM | F1569: 3 | G1569: 1 | H1569: MEDIUM | I1569: 9 | J1569: NO | K1569: https://swisspost.photocollect.io/auth/login | L1569: 2026-02-25T22:13:13+00:00 | M1569: Block URL | N1569: https://swisspost.photocollect.io/auth/login | O1569: Block phishing URL | Warn users about swisspost.photocollect.io impersonation | P1569: Email users / swisspost.photocollect.io | Q1569: P4 | R1569: 🚫 Block URLs in web proxy/firewall | 📧 Update email security filters | 👥 User awareness training recommended | S1569: Phishing URL | T1569: 0 | U1569: 0 | V1569: T1566:Phishing | T1566.002:Spearphishing Link | W1569: 1 | X1569: LOW (40%) | Y1569: NONE | Z1569: NONE | AA1569: https://swisspost.photocollect.io/auth/login | AB1569: NONE | AC1569: 0
A1570: PHISH | C1570: Phishing site targeting: swisspost.photocollect.io | URL: https://swisspost.photocollect.io/ | D1570: 6 | E1570: MEDIUM | F1570: 3 | G1570: 1 | H1570: MEDIUM | I1570: 9 | J1570: NO | K1570: https://swisspost.photocollect.io/ | L1570: 2026-02-25T22:13:13+00:00 | M1570: Block URL | N1570: https://swisspost.photocollect.io/ | O1570: Block phishing URL | Warn users about swisspost.photocollect.io impersonation | P1570: Email users / swisspost.photocollect.io | Q1570: P4 | R1570: 🚫 Block URLs in web proxy/firewall | 📧 Update email security filters | 👥 User awareness training recommended | S1570: Phishing URL | T1570: 0 | U1570: 0 | V1570: T1566:Phishing | T1566.002:Spearphishing Link | W1570: 1 | X1570: LOW (40%) | Y1570: NONE | Z1570: NONE | AA1570: https://swisspost.photocollect.io/ | AB1570: NONE | AC1570: 0
A1571: PHISH | C1571: Phishing site targeting: kucoin_x_logi.godaddysites.com | URL: https://kucoin_x_logi.godaddysites.com/ | D1571: 6 | E1571: MEDIUM | F1571: 3 | G1571: 1 | H1571: MEDIUM | I1571: 9 | J1571: NO | K1571: https://kucoin_x_logi.godaddysites.com/ | L1571: 2026-02-25T22:13:13+00:00 | M1571: Block URL | N1571: https://kucoin_x_logi.godaddysites.com/ | O1571: Block phishing URL | Warn users about kucoin_x_logi.godaddysites.com impersonation | P1571: Email users / kucoin_x_logi.godaddysites.com | Q1571: P4 | R1571: 🚫 Block URLs in web proxy/firewall | 📧 Update email security filters | 👥 User awareness training recommended | S1571: Phishing URL | T1571: 0 | U1571: 0 | V1571: T1566:Phishing | T1566.002:Spearphishing Link | W1571: 1 | X1571: LOW (40%) | Y1571: NONE | Z1571: NONE | AA1571: https://kucoin_x_logi.godaddysites.com/ | AB1571: NONE | AC1571: 0
A1572: PHISH | C1572: Phishing site targeting: roblox.com.ge | URL: https://roblox.com.ge/users/4587284650/profile | D1572: 6 | E1572: MEDIUM | F1572: 3 | G1572: 1 | H1572: MEDIUM | I1572: 9 | J1572: NO | K1572: https://roblox.com.ge/users/4587284650/profile | L1572: 2026-02-25T22:13:13+00:00 | M1572: Block URL | N1572: https://roblox.com.ge/users/4587284650/profile | O1572: Block phishing URL | Warn users about roblox.com.ge impersonation | P1572: Email users / roblox.com.ge | Q1572: P4 | R1572: 🚫 Block URLs in web proxy/firewall | 📧 Update email security filters | 👥 User awareness training recommended | S1572: Phishing URL | T1572: 0 | U1572: 0 | V1572: T1566:Phishing | T1566.002:Spearphishing Link | W1572: 1 | X1572: LOW (40%) | Y1572: NONE | Z1572: NONE | AA1572: https://roblox.com.ge/users/4587284650/profile | AB1572: NONE | AC1572: 0
A1573: PHISH | C1573: Phishing site targeting: www.robiox.com.ua | URL: https://www.robiox.com.ua/communities/9764817946/KHMER | D1573: 6 | E1573: MEDIUM | F1573: 3 | G1573: 1 | H1573: MEDIUM | I1573: 9 | J1573: NO | K1573: https://www.robiox.com.ua/communities/9764817946/KHMER | L1573: 2026-02-25T22:13:13+00:00 | M1573: Block URL | N1573: https://www.robiox.com.ua/communities/9764817946/KHMER | O1573: Block phishing URL | Warn users about www.robiox.com.ua impersonation | P1573: Email users / www.robiox.com.ua | Q1573: P4 | R1573: 🚫 Block URLs in web proxy/firewall | 📧 Update email security filters | 👥 User awareness training recommended | S1573: Phishing URL | T1573: 0 | U1573: 0 | V1573: T1566:Phishing | T1566.002:Spearphishing Link | W1573: 1 | X1573: LOW (40%) | Y1573: NONE | Z1573: NONE | AA1573: https://www.robiox.com.ua/communities/9764817946/KHMER | AB1573: NONE | AC1573: 0
... A1591: PHISH | C1591: Phishing site targeting: www.roblox.com.py | URL: https://www.roblox.com.py/upgrades/robux?ctx=navpopover | D1591: 6 | E1591: MEDIUM | F1591: 3 | G1591: 1 | H1591: MEDIUM | I1591: 9 | J1591: NO | K1591: https://www.roblox.com.py/upgrades/robux?ctx=navpopover | L1591: 2026-02-25T22:13:13+00:00 | M1591: Block URL | N1591: https://www.roblox.com.py/upgrades/robux?ctx=navpopover | O1591: Block phishing URL | Warn users about www.roblox.com.py impersonation | P1591: Email users / www.roblox.com.py | Q1591: P4 | R1591: 🚫 Block URLs in web proxy/firewall | 📧 Update email security filters | 👥 User awareness training recommended | S1591: Phishing URL | T1591: 0 | U1591: 0 | V1591: T1566:Phishing | T1566.002:Spearphishing Link | W1591: 1 | X1591: LOW (40%) | Y1591: NONE | Z1591: NONE | AA1591: https://www.roblox.com.py/upgrades/robux?ctx=navpopover | AB1591: NONE | AC1591: 0
A1592: OTX_PULSE | B1592: 699f5536e9f0860107bbaba7 | C1592: Unmasking Agent Tesla: A Deep Dive into a Multi-Stage Campaign: This analysis examines a sophisticated multi-stage infection chain utilizing Agent Tesla malware. The attack begins with a phishing email containing a RAR file, which includes an obfuscated JSE file. This initial stage triggers a series of script-based evasions, leading to the download and decryption of a PowerShell script. The malware then employs process hollowing to inject its payload into a legitimate Windows process, evading de | D1592: 7 | E1592: HIGH | F1592: 3 | G1592: 2 | H1592: HIGH | I1592: 13 | J1592: NO | K1592: https://www.fortinet.com/blog/threat-research/unmasking-agent-tesla-deep-dive-into-multi-stage-campaign | L1592: 2026-02-25T20:01:58.886000 | M1592: SEE_PULSE | N1592: https://www.fortinet.com/blog/threat-research/unmasking-agent-tesla-deep-dive-into-multi-stage-campaign | O1592: Block IOCs from pulse | Review pulse for indicators | P1592: credential harvesting, smtp, data exfiltration, anti-analysis, phishing, process hollowing, in-memory execution, agent tesla, multi-stage attack | Q1592: P3 | R1592: 🔍 Investigate and apply appropriate controls | S1592: OTX Pulse - check IP IOCs separately | T1592: 0 | U1592: 0 | V1592: See OTX pulse tags | W1592: 1 | X1592: LOW (40%) | Y1592: NONE | Z1592: NONE | AA1592: NONE | AB1592: NONE | AC1592: 0
A1593: OTX_PULSE | B1593: 6894566bd94b79b7fbdbade1 | C1593: Infrastructure of Interest: Medium Confidence InfoStealer: These indicators of compromise (IOCs) were identified through LevelBlue Labs' proprietary collection and threat hunting processes, leveraging AI-driven heuristics to detect anomalous patterns, behavioral analysis of malicious activity, and cross-referenced intelligence from endpoint telemetry and external sources. The IOCs included in this pulse are associated with infostealer malware, designed to harvest sensitive data such as credentia | D1593: 7 | E1593: HIGH | F1593: 3 | G1593: 2 | H1593: HIGH | I1593: 13 | J1593: NO | K1593: https://otx.alienvault.com | L1593: 2025-08-07T07:31:55.617000 | M1593: SEE_PULSE | N1593: https://otx.alienvault.com | O1593: Block IOCs from pulse | Review pulse for indicators | P1593: Various | Q1593: P3 | R1593: 🔍 Investigate and apply appropriate controls | S1593: OTX Pulse - check IP IOCs separately | T1593: 0 | U1593: 0 | V1593: See OTX pulse tags | W1593: 1 | X1593: LOW (40%) | Y1593: NONE | Z1593: NONE | AA1593: NONE | AB1593: NONE | AC1593: 0
A1594: OTX_PULSE | B1594: 689455e11e25236fe810364b | C1594: Infrastructure of Interest: Medium Confidence Command And Control: These indicators of compromise (IOCs) were identified through LevelBlue Labs' proprietary collection and threat hunting processes, leveraging AI-driven heuristics to detect anomalous patterns, behavioral analysis of malicious activity, and cross-referenced intelligence from endpoint telemetry and external sources. The IOCs included in this pulse are associated with command and control (C2) infrastructure, facilitating malware com | D1594: 7 | E1594: HIGH | F1594: 3 | G1594: 2 | H1594: HIGH | I1594: 13 | J1594: NO | K1594: https://otx.alienvault.com | L1594: 2025-08-07T07:29:37.542000 | M1594: SEE_PULSE | N1594: https://otx.alienvault.com | O1594: Block IOCs from pulse | Review pulse for indicators | P1594: Various | Q1594: P3 | R1594: 🔍 Investigate and apply appropriate controls | S1594: OTX Pulse - check IP IOCs separately | T1594: 0 | U1594: 0 | V1594: See OTX pulse tags | W1594: 1 | X1594: LOW (40%) | Y1594: NONE | Z1594: NONE | AA1594: NONE | AB1594: NONE | AC1594: 0
A1595: OTX_PULSE | B1595: 689453a1603f3d4b93557f2a | C1595: Infrastructure of Interest: Medium Confidence Phishing: These indicators of compromise (IOCs) were identified through LevelBlue Labs' proprietary collection and threat hunting processes, leveraging AI-driven heuristics to detect anomalous patterns, behavioral analysis of malicious activity, and cross-referenced intelligence from endpoint telemetry and external sources. The IOCs included in this pulse are associated with phishing campaigns, targeting credential theft and fraudulent resource acces | D1595: 7 | E1595: HIGH | F1595: 3 | G1595: 2 | H1595: HIGH | I1595: 13 | J1595: NO | K1595: https://otx.alienvault.com | L1595: 2025-08-07T07:20:01.253000 | M1595: SEE_PULSE | N1595: https://otx.alienvault.com | O1595: Block IOCs from pulse | Review pulse for indicators | P1595: Various | Q1595: P3 | R1595: 🔍 Investigate and apply appropriate controls | S1595: OTX Pulse - check IP IOCs separately | T1595: 0 | U1595: 0 | V1595: See OTX pulse tags | W1595: 1 | X1595: LOW (40%) | Y1595: NONE | Z1595: NONE | AA1595: NONE | AB1595: NONE | AC1595: 0
A1596: OTX_PULSE | B1596: 69778aef872cffc134e67ace | C1596: Chrome Extensions: Are you getting more than you bargained for?: This analysis reveals the hidden dangers of certain Chrome extensions available on the Google Chrome Web Store. Despite the store's vetting process, some malicious extensions have slipped through, compromising user security. The study examines four examples of extensions with combined user bases exceeding 100,000, showcasing various security risks. These include undisclosed clipboard access to remote domains, data exfiltration, rem | D1596: 7 | E1596: HIGH | F1596: 3 | G1596: 2 | H1596: HIGH | I1596: 13 | J1596: NO | K1596: https://www.security.com/threat-intelligence/chrome-extensions-are-you-getting-more-you-bargained | L1596: 2026-01-26T15:40:31.078000 | M1596: SEE_PULSE | N1596: https://www.security.com/threat-intelligence/chrome-extensions-are-you-getting-more-you-bargained | O1596: Block IOCs from pulse | Review pulse for indicators | P1596: data exfiltration, malicious extensions, xss vulnerability, security risks, cve-2020-28707, search hijacking, chrome extensions, remote code execution, clipboard access | Q1596: P3 | R1596: 🔍 Investigate and apply appropriate controls | S1596: OTX Pulse - check IP IOCs separately | T1596: 0 | U1596: 0 | V1596: See OTX pulse tags | W1596: 1 | X1596: LOW (40%) | Y1596: NONE | Z1596: NONE | AA1596: NONE | AB1596: NONE | AC1596: 0
A1597: OTX_PULSE | B1597: 69777a203745e70e7425106f | C1597: Malware MoonPeak Executed via LNK Files: In January 2026, IIJ observed malicious LNK files targeting Korean users to execute the MoonPeak malware, attributed to North Korean threat actors. The infection chain begins with a LNK file that runs an obfuscated PowerShell script, which checks for analysis environments, creates additional scripts, and sets up persistence. The second stage downloads and executes a payload from GitHub, which is actually the MoonPeak malware. MoonPeak is obfuscated using | D1597: 7 | E1597: HIGH | F1597: 3 | G1597: 2 | H1597: HIGH | I1597: 13 | J1597: NO | K1597: https://sect.iij.ad.jp/blog/2026/01/dprk-moonpeak-executed-via-malicious-lnk-file | L1597: 2026-01-26T14:28:48.027000 | M1597: SEE_PULSE | N1597: https://sect.iij.ad.jp/blog/2026/01/dprk-moonpeak-executed-via-malicious-lnk-file | O1597: Block IOCs from pulse | Review pulse for indicators | P1597: lots, korea, persistence, github, lnk files, xenorat, powershell, moonpeak, confuserex | Q1597: P3 | R1597: 🔍 Investigate and apply appropriate controls | S1597: OTX Pulse - check IP IOCs separately | T1597: 0 | U1597: 0 | V1597: See OTX pulse tags | W1597: 1 | X1597: LOW (40%) | Y1597: NONE | Z1597: NONE | AA1597: NONE | AB1597: NONE | AC1597: 0
A1598: OTX_PULSE | B1598: 699ee10d4bfa4e5fcf71399d | C1598: Inside the Fix: Analysis of In-the-Wild Exploit of CVE-2026-21513: This analysis examines CVE-2026-21513, a security bypass vulnerability in Microsoft's MSHTML framework, patched in February 2026. The flaw, actively exploited by Russian state-sponsored actor APT28, affects all Windows versions and has a CVSS score of 8.8. Using PatchDiff-AI, researchers identified the root cause in ieframe.dll's hyperlink navigation handling, allowing arbitrary file execution outside the browser's security conte | D1598: 7 | E1598: HIGH | F1598: 3 | G1598: 2 | H1598: HIGH | I1598: 13 | J1598: NO | K1598: https://www.akamai.com/blog/security-research/2026/feb/inside-the-fix-cve-2026-21513-mshtml-exploit-analysis | L1598: 2026-02-25T11:46:21.970000 | M1598: SEE_PULSE | N1598: https://www.akamai.com/blog/security-research/2026/feb/inside-the-fix-cve-2026-21513-mshtml-exploit-analysis | O1598: Block IOCs from pulse | Review pulse for indicators | P1598: exploit, patchdiff-ai, windows, ieframe.dll, cve-2026-21513, shellexecuteexw, mshtml, zero-day | Q1598: P3 | R1598: 🔍 Investigate and apply appropriate controls | S1598: OTX Pulse - check IP IOCs separately | T1598: 0 | U1598: 0 | V1598: See OTX pulse tags | W1598: 1 | X1598: LOW (40%) | Y1598: NONE | Z1598: NONE | AA1598: NONE | AB1598: NONE | AC1598: 0
A1599: OTX_PULSE | B1599: 689456eba72f618e9d63e8dd | C1599: Infrastructure of Interest: Medium Confidence FastFlux: These indicators of compromise (IOCs) were identified through LevelBlue Labs' proprietary collection and threat hunting processes, leveraging AI-driven heuristics to detect anomalous DNS patterns, behavioral analysis of rapid IP rotation, and cross-referenced intelligence from global sinkhole data and network telemetry. The IOCs included in this pulse are associated with Fastflux networks, characterized by constantly changing IP addresses a | D1599: 7 | E1599: HIGH | F1599: 3 | G1599: 2 | H1599: HIGH | I1599: 13 | J1599: NO | K1599: https://otx.alienvault.com | L1599: 2025-08-07T07:34:03.778000 | M1599: SEE_PULSE | N1599: https://otx.alienvault.com | O1599: Block IOCs from pulse | Review pulse for indicators | P1599: Various | Q1599: P3 | R1599: 🔍 Investigate and apply appropriate controls | S1599: OTX Pulse - check IP IOCs separately | T1599: 0 | U1599: 0 | V1599: See OTX pulse tags | W1599: 1 | X1599: LOW (40%) | Y1599: NONE | Z1599: NONE | AA1599: NONE | AB1599: NONE | AC1599: 0
A1600: OTX_PULSE | B1600: 699ede794dd30674f7d583d5 | C1600: Mercenary Akula Hits Ukraine-Supporting Financial...: A European financial institution involved in regional development and reconstruction initiatives was targeted by a social engineering attack attributed to the Russia-aligned Mercenary Akula. The attack used a spoofed Ukrainian judicial domain to deliver an email containing a link to a remote access payload. The target was a senior legal and policy advisor involved in procurement. The attack employed a multi-stage extraction process and deploy | D1600: 7 | E1600: HIGH | F1600: 3 | G1600: 2 | H1600: HIGH | I1600: 13 | J1600: NO | K1600: https://www.bluevoyant.com/blog/mercenary-akula-hits-financial-institution | L1600: 2026-02-25T11:35:21.172000 | M1600: SEE_PULSE | N1600: https://www.bluevoyant.com/blog/mercenary-akula-hits-financial-institution | O1600: Block IOCs from pulse | Review pulse for indicators | P1600: remote manipulator system, quasarrat, fire cells group, uac-0050, spearphishing, remote access, cyber espionage, financial theft, remcos, social engineering, davinci group | Q1600: P3 | R1600: 🔍 Investigate and apply appropriate controls | S1600: OTX Pulse - check IP IOCs separately | T1600: 0 | U1600: 0 | V1600: See OTX pulse tags | W1600: 1 | X1600: LOW (40%) | Y1600: NONE | Z1600: NONE | AA1600: NONE | AB1600: NONE | AC1600: 0
A1601: OTX_PULSE | B1601: 699edea96aa1a8d035261fc9 | C1601: The Latest PlugX Variant Executed by STATICPLUGIN: In January 2026, a new variant of the PlugX malware was observed being used in targeted attacks. Analysis suggests involvement of the UNC6384 APT group, linked to Mustang Panda, targeting government agencies in Southeast Asia. The malware uses a browser updater disguise to download and execute a malicious MSI file, leading to PlugX infection. The STATICPLUGIN downloader uses a revoked code-signing certificate from a Chinese company. The PlugX va | D1601: 7 | E1601: HIGH | F1601: 3 | G1601: 2 | H1601: HIGH | I1601: 13 | J1601: NO | K1601: https://sect.iij.ad.jp/blog/2026/02/plugx-executed-via-staticplugin/ | L1601: 2026-02-25T11:36:09.887000 | M1601: SEE_PULSE | N1601: https://sect.iij.ad.jp/blog/2026/02/plugx-executed-via-staticplugin/ | O1601: Block IOCs from pulse | Review pulse for indicators | P1601: rc4-encryption, apt, targeted-attack, plugx, staticplugin, valleyrat, dll-sideloading, code-signing | Q1601: P3 | R1601: 🔍 Investigate and apply appropriate controls | S1601: OTX Pulse - check IP IOCs separately | T1601: 0 | U1601: 0 | V1601: See OTX pulse tags | W1601: 1 | X1601: LOW (40%) | Y1601: NONE | Z1601: NONE | AA1601: NONE | AB1601: NONE | AC1601: 0
A1602: OTX_PULSE | B1602: 69772b44fe2e1c30ec984e32 | C1602: A $6,000 Russian Malware Toolkit with Chrome Web Store Guarantee: A new malware-as-a-service toolkit called 'Stanley' is being sold on Russian cybercrime forums for $2,000 to $6,000. It provides a turnkey website-spoofing operation disguised as a Chrome extension, with the premium tier promising guaranteed publication on the Chrome Web Store. The toolkit allows full-page website spoofing, element injection, push notifications, and backup domain rotation. It uses victims' IP addresses for trackin | D1602: 7 | E1602: HIGH | F1602: 3 | G1602: 2 | H1602: HIGH | I1602: 13 | J1602: NO | K1602: https://www.varonis.com/blog/stanley-malware-kit | L1602: 2026-01-26T08:52:20.218000 | M1602: SEE_PULSE | N1602: https://www.varonis.com/blog/stanley-malware-kit | O1602: Block IOCs from pulse | Review pulse for indicators | P1602: chrome web store, phishing, credential theft, browser extension, malware-as-service, website spoofing, russian cybercrime, stanley | Q1602: P3 | R1602: 🔍 Investigate and apply appropriate controls | S1602: OTX Pulse - check IP IOCs separately | T1602: 0 | U1602: 0 | V1602: See OTX pulse tags | W1602: 1 | X1602: LOW (40%) | Y1602: NONE | Z1602: NONE | AA1602: NONE | AB1602: NONE | AC1602: 0
A1603: OTX_PULSE | B1603: 699e18510d30e21605243f81 | C1603: Developer-targeting campaign using malicious Next.js repositories: A coordinated campaign is targeting developers through malicious repositories disguised as legitimate Next.js projects and technical assessment materials. The attack uses multiple entry points that lead to runtime retrieval and local execution of attacker-controlled JavaScript, transitioning into staged command-and-control. The campaign employs three main execution paths: Visual Studio Code workspace automation, build-time execut | D1603: 7 | E1603: HIGH | F1603: 3 | G1603: 2 | H1603: HIGH | I1603: 13 | J1603: NO | K1603: https://www.microsoft.com/en-us/security/blog/2026/02/24/c2-developer-targeting-campaign/ | L1603: 2026-02-24T21:29:53.984000 | M1603: SEE_PULSE | N1603: https://www.microsoft.com/en-us/security/blog/2026/02/24/c2-developer-targeting-campaign/ | O1603: Block IOCs from pulse | Review pulse for indicators | P1603: next.js, command-and-control, javascript, remote code execution, node.js, developer-targeting, visual studio code, environment variable exfiltration | Q1603: P3 | R1603: 🔍 Investigate and apply appropriate controls | S1603: OTX Pulse - check IP IOCs separately | T1603: 0 | U1603: 0 | V1603: See OTX pulse tags | W1603: 1 | X1603: LOW (40%) | Y1603: NONE | Z1603: NONE | AA1603: NONE | AB1603: NONE | AC1603: 0
... A1641: THREATFOX_IOC | B1641: 1754850 | C1641: ip:port IOC: | Malware: DCRat | Confidence: 100% | D1641: 7.5 | E1641: HIGH | F1641: 3 | G1641: 2 | H1641: HIGH | I1641: 13.5 | J1641: NO | K1641: https://threatfox.abuse.ch/ioc/1754850/ | L1641: 2026-02-25 20:05:15 UTC | M1641: Block IOC | N1641: https://threatfox.abuse.ch/ioc/1754850/ | O1641: Block ip:port: | P1641: botnet_cc | Q1641: P3 | R1641: 🚫 Block IOC at network perimeter | 🔎 Hunt for IOC across environment | 📋 Document and share with threat intel team | S1641: Classification: skipped | Context: Skipped (20/run IOC cap) | Name: N/A | T1641: 0 | U1641: 0 | V1641: T1071:Application Layer Protocol | T1102:Web Service | W1641: 1 | X1641: LOW (40%) | Y1641: NONE | Z1641: NONE | AA1641: NONE | AB1641: NONE | AC1641: 0
A1642: THREATMINER | B1642: d41d8cd98f00 | C1642: Malicious domain: | IP: 91.224.92.78 | Last seen: | D1642: 6.5 | E1642: MEDIUM | F1642: 2 | G1642: 2 | H1642: MEDIUM | I1642: 10.5 | J1642: NO | K1642: https://www.threatminer.org/domain.php?q= | M1642: Block domain | N1642: https://www.threatminer.org/domain.php?q= | O1642: Block domain at DNS/firewall | P1642: DNS/Network | Q1642: P4 | R1642: 🔍 Investigate and apply appropriate controls | S1642: Domain IOC - check IP separately | T1642: 0 | U1642: 0 | V1642: T1071.001:Web Protocols | T1568:Dynamic Resolution | W1642: 1 | X1642: LOW (40%) | Y1642: NONE | Z1642: NONE | AA1642: NONE | AB1642: NONE | AC1642: 0
A1643: THREATMINER | B1643: d41d8cd98f00 | C1643: Malicious domain: | IP: 91.224.92.190 | Last seen: | D1643: 6.5 | E1643: MEDIUM | F1643: 2 | G1643: 2 | H1643: MEDIUM | I1643: 10.5 | J1643: NO | K1643: https://www.threatminer.org/domain.php?q= | M1643: Block domain | N1643: https://www.threatminer.org/domain.php?q= | O1643: Block domain at DNS/firewall | P1643: DNS/Network | Q1643: P4 | R1643: 🔍 Investigate and apply appropriate controls | S1643: Domain IOC - check IP separately | T1643: 0 | U1643: 0 | V1643: T1071.001:Web Protocols | T1568:Dynamic Resolution | W1643: 1 | X1643: LOW (40%) | Y1643: NONE | Z1643: NONE | AA1643: NONE | AB1643: NONE | AC1643: 0
A1644: THREATMINER | B1644: d41d8cd98f00 | C1644: Malicious domain: | IP: 103.218.241.106 | Last seen: | D1644: 6.5 | E1644: MEDIUM | F1644: 2 | G1644: 2 | H1644: MEDIUM | I1644: 10.5 | J1644: NO | K1644: https://www.threatminer.org/domain.php?q= | M1644: Block domain | N1644: https://www.threatminer.org/domain.php?q= | O1644: Block domain at DNS/firewall | P1644: DNS/Network | Q1644: P4 | R1644: 🔍 Investigate and apply appropriate controls | S1644: Domain IOC - check IP separately | T1644: 0 | U1644: 0 | V1644: T1071.001:Web Protocols | T1568:Dynamic Resolution | W1644: 1 | X1644: LOW (40%) | Y1644: NONE | Z1644: NONE | AA1644: NONE | AB1644: NONE | AC1644: 0
A1645: THREATMINER | B1645: d41d8cd98f00 | C1645: Malicious domain: | IP: 185.91.69.217 | Last seen: | D1645: 6.5 | E1645: MEDIUM | F1645: 2 | G1645: 2 | H1645: MEDIUM | I1645: 10.5 | J1645: NO | K1645: https://www.threatminer.org/domain.php?q= | M1645: Block domain | N1645: https://www.threatminer.org/domain.php?q= | O1645: Block domain at DNS/firewall | P1645: DNS/Network | Q1645: P4 | R1645: 🔍 Investigate and apply appropriate controls | S1645: Domain IOC - check IP separately | T1645: 0 | U1645: 0 | V1645: T1071.001:Web Protocols | T1568:Dynamic Resolution | W1645: 1 | X1645: LOW (40%) | Y1645: NONE | Z1645: NONE | AA1645: NONE | AB1645: NONE | AC1645: 0
A1646: THREATMINER | B1646: d41d8cd98f00 | C1646: Malicious domain: | IP: 2.57.121.25 | Last seen: | D1646: 6.5 | E1646: MEDIUM | F1646: 2 | G1646: 2 | H1646: MEDIUM | I1646: 10.5 | J1646: NO | K1646: https://www.threatminer.org/domain.php?q= | M1646: Block domain | N1646: https://www.threatminer.org/domain.php?q= | O1646: Block domain at DNS/firewall | P1646: DNS/Network | Q1646: P4 | R1646: 🔍 Investigate and apply appropriate controls | S1646: Domain IOC - check IP separately | T1646: 0 | U1646: 0 | V1646: T1071.001:Web Protocols | T1568:Dynamic Resolution | W1646: 1 | X1646: LOW (40%) | Y1646: NONE | Z1646: NONE | AA1646: NONE | AB1646: NONE | AC1646: 0
A1647: THREATMINER | B1647: d41d8cd98f00 | C1647: Malicious domain: | IP: 2.57.122.238 | Last seen: | D1647: 6.5 | E1647: MEDIUM | F1647: 2 | G1647: 2 | H1647: MEDIUM | I1647: 10.5 | J1647: NO | K1647: https://www.threatminer.org/domain.php?q= | M1647: Block domain | N1647: https://www.threatminer.org/domain.php?q= | O1647: Block domain at DNS/firewall | P1647: DNS/Network | Q1647: P4 | R1647: 🔍 Investigate and apply appropriate controls | S1647: Domain IOC - check IP separately | T1647: 0 | U1647: 0 | V1647: T1071.001:Web Protocols | T1568:Dynamic Resolution | W1647: 1 | X1647: LOW (40%) | Y1647: NONE | Z1647: NONE | AA1647: NONE | AB1647: NONE | AC1647: 0
A1648: THREATMINER | B1648: d41d8cd98f00 | C1648: Malicious domain: | IP: 45.148.10.141 | Last seen: | D1648: 6.5 | E1648: MEDIUM | F1648: 2 | G1648: 2 | H1648: MEDIUM | I1648: 10.5 | J1648: NO | K1648: https://www.threatminer.org/domain.php?q= | M1648: Block domain | N1648: https://www.threatminer.org/domain.php?q= | O1648: Block domain at DNS/firewall | P1648: DNS/Network | Q1648: P4 | R1648: 🔍 Investigate and apply appropriate controls | S1648: Domain IOC - check IP separately | T1648: 0 | U1648: 0 | V1648: T1071.001:Web Protocols | T1568:Dynamic Resolution | W1648: 1 | X1648: LOW (40%) | Y1648: NONE | Z1648: NONE | AA1648: NONE | AB1648: NONE | AC1648: 0
A1649: THREATMINER | B1649: d41d8cd98f00 | C1649: Malicious domain: | IP: 45.148.10.147 | Last seen: | D1649: 6.5 | E1649: MEDIUM | F1649: 2 | G1649: 2 | H1649: MEDIUM | I1649: 10.5 | J1649: NO | K1649: https://www.threatminer.org/domain.php?q= | M1649: Block domain | N1649: https://www.threatminer.org/domain.php?q= | O1649: Block domain at DNS/firewall | P1649: DNS/Network | Q1649: P4 | R1649: 🔍 Investigate and apply appropriate controls | S1649: Domain IOC - check IP separately | T1649: 0 | U1649: 0 | V1649: T1071.001:Web Protocols | T1568:Dynamic Resolution | W1649: 1 | X1649: LOW (40%) | Y1649: NONE | Z1649: NONE | AA1649: NONE | AB1649: NONE | AC1649: 0
A1650: THREATMINER | B1650: d41d8cd98f00 | C1650: Malicious domain: | IP: 45.148.10.151 | Last seen: | D1650: 6.5 | E1650: MEDIUM | F1650: 2 | G1650: 2 | H1650: MEDIUM | I1650: 10.5 | J1650: NO | K1650: https://www.threatminer.org/domain.php?q= | M1650: Block domain | N1650: https://www.threatminer.org/domain.php?q= | O1650: Block domain at DNS/firewall | P1650: DNS/Network | Q1650: P4 | R1650: 🔍 Investigate and apply appropriate controls | S1650: Domain IOC - check IP separately | T1650: 0 | U1650: 0 | V1650: T1071.001:Web Protocols | T1568:Dynamic Resolution | W1650: 1 | X1650: LOW (40%) | Y1650: NONE | Z1650: NONE | AA1650: NONE | AB1650: NONE | AC1650: 0
A1651: THREATMINER | B1651: d41d8cd98f00 | C1651: Malicious domain: | IP: 45.148.10.152 | Last seen: | D1651: 6.5 | E1651: MEDIUM | F1651: 2 | G1651: 2 | H1651: MEDIUM | I1651: 10.5 | J1651: NO | K1651: https://www.threatminer.org/domain.php?q= | M1651: Block domain | N1651: https://www.threatminer.org/domain.php?q= | O1651: Block domain at DNS/firewall | P1651: DNS/Network | Q1651: P4 | R1651: 🔍 Investigate and apply appropriate controls | S1651: Domain IOC - check IP separately | T1651: 0 | U1651: 0 | V1651: T1071.001:Web Protocols | T1568:Dynamic Resolution | W1651: 1 | X1651: LOW (40%) | Y1651: NONE | Z1651: NONE | AA1651: NONE | AB1651: NONE | AC1651: 0
A1652: THREATMINER | B1652: d41d8cd98f00 | C1652: Malicious domain: | IP: 45.148.10.157 | Last seen: | D1652: 6.5 | E1652: MEDIUM | F1652: 2 | G1652: 2 | H1652: MEDIUM | I1652: 10.5 | J1652: NO | K1652: https://www.threatminer.org/domain.php?q= | M1652: Block domain | N1652: https://www.threatminer.org/domain.php?q= | O1652: Block domain at DNS/firewall | P1652: DNS/Network | Q1652: P4 | R1652: 🔍 Investigate and apply appropriate controls | S1652: Domain IOC - check IP separately | T1652: 0 | U1652: 0 | V1652: T1071.001:Web Protocols | T1568:Dynamic Resolution | W1652: 1 | X1652: LOW (40%) | Y1652: NONE | Z1652: NONE | AA1652: NONE | AB1652: NONE | AC1652: 0
A1653: THREATMINER | B1653: d41d8cd98f00 | C1653: Malicious domain: | IP: 45.249.244.185 | Last seen: | D1653: 6.5 | E1653: MEDIUM | F1653: 2 | G1653: 2 | H1653: MEDIUM | I1653: 10.5 | J1653: NO | K1653: https://www.threatminer.org/domain.php?q= | M1653: Block domain | N1653: https://www.threatminer.org/domain.php?q= | O1653: Block domain at DNS/firewall | P1653: DNS/Network | Q1653: P4 | R1653: 🔍 Investigate and apply appropriate controls | S1653: Domain IOC - check IP separately | T1653: 0 | U1653: 0 | V1653: T1071.001:Web Protocols | T1568:Dynamic Resolution | W1653: 1 | X1653: LOW (40%) | Y1653: NONE | Z1653: NONE | AA1653: NONE | AB1653: NONE | AC1653: 0
... A1671: THREATMINER | B1671: d41d8cd98f00 | C1671: Malicious domain: | IP: 2.57.121.112 | Last seen: | D1671: 6.5 | E1671: MEDIUM | F1671: 2 | G1671: 2 | H1671: MEDIUM | I1671: 10.5 | J1671: NO | K1671: https://www.threatminer.org/domain.php?q= | M1671: Block domain | N1671: https://www.threatminer.org/domain.php?q= | O1671: Block domain at DNS/firewall | P1671: DNS/Network | Q1671: P4 | R1671: 🔍 Investigate and apply appropriate controls | S1671: Domain IOC - check IP separately | T1671: 0 | U1671: 0 | V1671: T1071.001:Web Protocols | T1568:Dynamic Resolution | W1671: 1 | X1671: LOW (40%) | Y1671: NONE | Z1671: NONE | AA1671: NONE | AB1671: NONE | AC1671: 0
A1672: SHODAN_VULN | B1672: 7270e450f7f1 | C1672: InternetDB: 162.243.103.246 | Ports: 22, 80, 443, 8080 | wearoddball.com | CVE: CVE-2014-3470 | Tags: cloud | D1672: 7.5 | E1672: HIGH | F1672: 2 | G1672: 2 | H1672: MEDIUM | I1672: 11.5 | J1672: NO | K1672: https://www.shodan.io/host/162.243.103.246 | L1672: 2026-02-26 00:15 | M1672: Apply patch and restrict exposed ports | N1672: https://www.shodan.io/host/162.243.103.246 | O1672: Close or firewall port(s) 22, 80, 443, 8080 on 162.243.103.246 | P1672: wearoddball.com | Q1672: P4 | R1672: 🔍 Investigate and apply appropriate controls | S1672: Shodan InternetDB — see ip-api.com context for scanner classification | T1672: 0 | U1672: 0 | V1672: T1190:Exploit Public-Facing Application | T1046:Network Service Discovery | W1672: 1 | X1672: LOW (40%) | Y1672: CHECK_VULNS | Z1672: Restrict access | AA1672: https://www.shodan.io/host/162.243.103.246 | AB1672: NONE | AC1672: 0
A1673: SHODAN_VULN | B1673: ff59c7fe2f68 | C1673: InternetDB: 162.243.103.246 | Ports: 22, 80, 443, 8080 | wearoddball.com | CVE: CVE-2014-2497 | Tags: cloud | D1673: 7.5 | E1673: HIGH | F1673: 2 | G1673: 2 | H1673: MEDIUM | I1673: 11.5 | J1673: NO | K1673: https://www.shodan.io/host/162.243.103.246 | L1673: 2026-02-26 00:15 | M1673: Apply patch and restrict exposed ports | N1673: https://www.shodan.io/host/162.243.103.246 | O1673: Close or firewall port(s) 22, 80, 443, 8080 on 162.243.103.246 | P1673: wearoddball.com | Q1673: P4 | R1673: 🔍 Investigate and apply appropriate controls | S1673: Shodan InternetDB — see ip-api.com context for scanner classification | T1673: 0 | U1673: 0 | V1673: T1190:Exploit Public-Facing Application | T1046:Network Service Discovery | W1673: 1 | X1673: LOW (40%) | Y1673: CHECK_VULNS | Z1673: Restrict access | AA1673: https://www.shodan.io/host/162.243.103.246 | AB1673: NONE | AC1673: 0
A1674: SHODAN_VULN | B1674: 5551873c0fb5 | C1674: InternetDB: 162.243.103.246 | Ports: 22, 80, 443, 8080 | wearoddball.com | CVE: CVE-2019-9641 | Tags: cloud | D1674: 7.5 | E1674: HIGH | F1674: 2 | G1674: 2 | H1674: MEDIUM | I1674: 11.5 | J1674: NO | K1674: https://www.shodan.io/host/162.243.103.246 | L1674: 2026-02-26 00:15 | M1674: Apply patch and restrict exposed ports | N1674: https://www.shodan.io/host/162.243.103.246 | O1674: Close or firewall port(s) 22, 80, 443, 8080 on 162.243.103.246 | P1674: wearoddball.com | Q1674: P4 | R1674: 🔍 Investigate and apply appropriate controls | S1674: Shodan InternetDB — see ip-api.com context for scanner classification | T1674: 0 | U1674: 0 | V1674: T1190:Exploit Public-Facing Application | T1046:Network Service Discovery | W1674: 1 | X1674: LOW (40%) | Y1674: CHECK_VULNS | Z1674: Restrict access | AA1674: https://www.shodan.io/host/162.243.103.246 | AB1674: NONE | AC1674: 0
A1675: SHODAN_VULN | B1675: f357a582e404 | C1675: InternetDB: 178.62.3.223 | Ports: 22, 25, 53, 80, 443, 587, 993, 995 | box.nautadb.com | Tags: starttls, cloud | D1675: 5 | E1675: MEDIUM | F1675: 1 | G1675: 2 | H1675: LOW | I1675: 7 | J1675: NO | K1675: https://www.shodan.io/host/178.62.3.223 | L1675: 2026-02-26 00:15 | M1675: Review and firewall exposed ports | N1675: https://www.shodan.io/host/178.62.3.223 | O1675: Review and restrict port(s) 22, 25, 53, 80, 443, 587, 993, 995 on 178.62.3.223 | P1675: box.nautadb.com | Q1675: P4 | R1675: 🔍 Investigate and apply appropriate controls | S1675: Shodan InternetDB — open ports, no known CVEs indexed | T1675: 0 | U1675: 0 | V1675: T1046:Network Service Discovery | W1675: 1 | X1675: LOW (40%) | Y1675: NONE | Z1675: Restrict access | AA1675: https://www.shodan.io/host/178.62.3.223 | AB1675: NONE | AC1675: 0
A1676: SHODAN_VULN | B1676: 126704e0a40b | C1676: InternetDB: 34.204.119.63 | Ports: 80, 443 | ec2-34-204-119-63.compute-1.amazonaws.com | Tags: cloud | D1676: 5 | E1676: MEDIUM | F1676: 1 | G1676: 2 | H1676: LOW | I1676: 7 | J1676: NO | K1676: https://www.shodan.io/host/34.204.119.63 | L1676: 2026-02-26 00:15 | M1676: Review and firewall exposed ports | N1676: https://www.shodan.io/host/34.204.119.63 | O1676: Review and restrict port(s) 80, 443 on 34.204.119.63 | P1676: ec2-34-204-119-63.compute-1.amazonaws.com | Q1676: P4 | R1676: 🔍 Investigate and apply appropriate controls | S1676: Shodan InternetDB — open ports, no known CVEs indexed | T1676: 0 | U1676: 0 | V1676: T1046:Network Service Discovery | W1676: 1 | X1676: LOW (40%) | Y1676: NONE | Z1676: Restrict access | AA1676: https://www.shodan.io/host/34.204.119.63 | AB1676: NONE | AC1676: 0
...

Sheet PowerBI_Export
A1: Type | B1: ID | C1: Description | D1: CVSS | E1: Severity | F1: Likelihood | G1: Impact | H1: Risk_Level | I1: Final_Score | J1: CISA_KEV | K1: Timestamp | L1: Patch_Available | M1: Affected_Products | N1: Remediation_Priority | O1: GreyNoise_Context | P1: EPSS_Score | Q1: EPSS_Percentile | R1: MITRE_Techniques | S1: Source_Count | T1: Confidence_Score | U1: Exploit_Status | V1: Fix_Available | W1: Intel_URL | X1: ZDI_Advisory | Y1: AttackerKB_Score | Z1: News_Coverage | AA1: Link
A2: CVE | B2: CVE-2019-25326 | C2: ipPulse 1.92 contains a denial of service vulnerability that allows local attackers to crash the application by providing an oversized input in the Enter Key field. Attackers can generate a 256-byte buffer of repeated 'A' characters to trigger an application crash when pasting the malicious content. | D2: 6.2 | E2: MEDIUM | F2: 2 | G2: 2 | H2: MEDIUM | I2: 10.2 | J2: NO | K2: 2026-02-26 00:15 | L2: CHECK_VENDOR | M2: nwpsw ippulse * | N2: P4 | O2: CVE - IP enrichment n/a | P2: 0.0001 | Q2: 0.0199 | R2: T1203:Exploitation for Client Execution | T1499:Endpoint Denial of Service | S2: 1 | T2: LOW (40%) | U2: UNLIKELY | V2: CHECK_VENDOR | W2: https://nvd.nist.gov/vuln/detail/CVE-2019-25326 | X2: NONE | Y2: 0 | AA2: https://nvd.nist.gov/vuln/detail/CVE-2019-25326
A3: CVE | B3: CVE-2019-25349 | C3: ScadaApp for iOS 1.1.4.0 contains a denial of service vulnerability that allows attackers to crash the application by inputting an oversized buffer in the Servername field. Attackers can paste a 257-character buffer during login to trigger an application crash on iOS devices. | D3: 7.5 | E3: HIGH | F3: 2 | G3: 3 | H3: HIGH | I3: 13.5 | J3: NO | K3: 2026-02-26 00:15 | L3: CHECK_VENDOR | M3: See CVE details | N3: P2 | O3: CVE - IP enrichment n/a | P3: 0 | Q3: 0 | R3: T1203:Exploitation for Client Execution | T1499:Endpoint Denial of Service | S3: 2 | T3: HIGH (72%) | U3: POSSIBLE | V3: CHECK_VENDOR | W3: https://nvd.nist.gov/vuln/detail/CVE-2019-25349 | X3: NONE | Y3: 3.75 | AA3: https://nvd.nist.gov/vuln/detail/CVE-2019-25349
A4: CVE | B4: CVE-2019-25350 | C4: XMedia Recode 3.4.8.6 contains a denial of service vulnerability that allows attackers to crash the application by loading a specially crafted .m3u playlist file. Attackers can create a malicious .m3u file with an oversized buffer to trigger an application crash when the file is opened. | D4: 7.5 | E4: HIGH | F4: 2 | G4: 3 | H4: HIGH | I4: 13.5 | J4: NO | K4: 2026-02-26 00:15 | L4: CHECK_VENDOR | M4: See CVE details | N4: P3 | O4: CVE - IP enrichment n/a | P4: 0 | Q4: 0 | R4: T1499:Endpoint Denial of Service | S4: 1 | T4: LOW (40%) | U4: UNLIKELY | V4: CHECK_VENDOR | W4: https://nvd.nist.gov/vuln/detail/CVE-2019-25350 | X4: NONE | Y4: 0 | AA4: https://nvd.nist.gov/vuln/detail/CVE-2019-25350
A5: CVE | B5: CVE-2019-25351 | C5: Centova Cast 3.2.11 contains a file download vulnerability that allows authenticated attackers to retrieve arbitrary system files through the server.copyfile API endpoint. Attackers can exploit the vulnerability by supplying crafted parameters to download sensitive files like /etc/passwd using curl and wget requests. | D5: 8.8 | E5: HIGH | F5: 2 | G5: 3 | H5: HIGH | I5: 14.8 | J5: NO | K5: 2026-02-26 00:15 | L5: CHECK_VENDOR | M5: See CVE details | N5: P3 | O5: CVE - IP enrichment n/a | P5: 0.0005 | Q5: 0.1573 | R5: T1190:Exploit Public-Facing Application | S5: 1 | T5: LOW (40%) | U5: UNLIKELY | V5: CHECK_VENDOR | W5: https://nvd.nist.gov/vuln/detail/CVE-2019-25351 | X5: NONE | Y5: 0 | AA5: https://nvd.nist.gov/vuln/detail/CVE-2019-25351
A6: CVE | B6: CVE-2019-25352 | C6: Crystal Live HTTP Server 6.01 contains a directory traversal vulnerability that allows remote attackers to access system files by manipulating URL path segments. Attackers can use multiple '../' sequences to navigate outside the web root and retrieve sensitive configuration files like Windows system files. | D6: 7.5 | E6: HIGH | F6: 2 | G6: 3 | H6: HIGH | I6: 13.5 | J6: NO | K6: 2026-02-26 00:15 | L6: CHECK_VENDOR | M6: See CVE details | N6: P2 | O6: CVE - IP enrichment n/a | P6: 0 | Q6: 0 | R6: T1083:File and Directory Discovery | S6: 2 | T6: HIGH (72%) | U6: POSSIBLE | V6: CHECK_VENDOR | W6: https://nvd.nist.gov/vuln/detail/CVE-2019-25352 | X6: NONE | Y6: 3.75 | AA6: https://nvd.nist.gov/vuln/detail/CVE-2019-25352
A7: CVE | B7: CVE-2019-25353 | C7: Foscam Video Management System 1.1.4.9 contains a denial of service vulnerability in the username input field that allows attackers to crash the application. Attackers can overwrite the username with a 520-byte buffer of repeated 'A' characters to trigger an application crash during device login. | D7: 7.5 | E7: HIGH | F7: 2 | G7: 3 | H7: HIGH | I7: 13.5 | J7: NO | K7: 2026-02-26 00:15 | L7: CHECK_VENDOR | M7: See CVE details | N7: P3 | O7: CVE - IP enrichment n/a | P7: 0 | Q7: 0 | R7: T1203:Exploitation for Client Execution | T1499:Endpoint Denial of Service | S7: 1 | T7: LOW (40%) | U7: UNLIKELY | V7: CHECK_VENDOR | W7: https://nvd.nist.gov/vuln/detail/CVE-2019-25353 | X7: NONE | Y7: 0 | AA7: https://nvd.nist.gov/vuln/detail/CVE-2019-25353
A8: CVE | B8: CVE-2019-25354 | C8: iSmartViewPro 1.3.34 contains a denial of service vulnerability that allows attackers to crash the application by overflowing the camera ID input field. Attackers can paste a 257-character buffer into the camera DID and password fields to trigger an application crash on iOS devices. | D8: 7.5 | E8: HIGH | F8: 2 | G8: 3 | H8: HIGH | I8: 13.5 | J8: NO | K8: 2026-02-26 00:15 | L8: CHECK_VENDOR | M8: See CVE details | N8: P2 | O8: CVE - IP enrichment n/a | P8: 0 | Q8: 0 | R8: T1203:Exploitation for Client Execution | T1499:Endpoint Denial of Service | S8: 2 | T8: HIGH (72%) | U8: POSSIBLE | V8: CHECK_VENDOR | W8: https://nvd.nist.gov/vuln/detail/CVE-2019-25354 | X8: NONE | Y8: 3.75 | AA8: https://nvd.nist.gov/vuln/detail/CVE-2019-25354
A9: CVE | B9: CVE-2019-25355 | C9: gSOAP 2.8 contains a directory traversal vulnerability that allows unauthenticated attackers to access system files by manipulating HTTP path traversal techniques. Attackers can retrieve sensitive files like /etc/passwd by sending crafted GET requests with multiple '../' directory traversal sequences. | D9: 7.5 | E9: HIGH | F9: 2 | G9: 3 | H9: HIGH | I9: 13.5 | J9: NO | K9: 2026-02-26 00:15 | L9: CHECK_VENDOR | M9: See CVE details | N9: P2 | O9: CVE - IP enrichment n/a | P9: 0 | Q9: 0 | R9: T1083:File and Directory Discovery | S9: 2 | T9: HIGH (72%) | U9: POSSIBLE | V9: CHECK_VENDOR | W9: https://nvd.nist.gov/vuln/detail/CVE-2019-25355 | X9: NONE | Y9: 3.75 | AA9: https://nvd.nist.gov/vuln/detail/CVE-2019-25355
A10: CVE | B10: CVE-2019-25356 | C10: Bematech (formerly Logic Controls, now Elgin) MP-4200 TH printer contains a cross-site scripting vulnerability in the admin configuration page. Attackers can inject malicious scripts via crafted POST requests with malformed 'admin' and 'person' parameters, allowing execution of arbitrary JavaScript in the context of an authenticated user's browser session. | D10: 6.1 | E10: MEDIUM | F10: 2 | G10: 2 | H10: MEDIUM | I10: 10.1 | J10: NO | K10: 2026-02-26 00:15 | L10: CHECK_VENDOR | M10: See CVE details | N10: P4 | O10: CVE - IP enrichment n/a | P10: 0.0004 | Q10: 0.1135 | R10: T1189:Drive-by Compromise | S10: 1 | T10: LOW (40%) | U10: UNLIKELY | V10: CHECK_VENDOR | W10: https://nvd.nist.gov/vuln/detail/CVE-2019-25356 | X10: NONE | Y10: 0 | AA10: https://nvd.nist.gov/vuln/detail/CVE-2019-25356
A11: CVE | B11: CVE-2019-25357 | C11: Control Center PRO 6.2.9 contains a stack-based buffer overflow vulnerability in the user creation module's username field that allows attackers to overwrite Structured Exception Handler (SEH). Attackers can craft a malicious payload exceeding 664 bytes to inject shellcode and potentially execute arbitrary code on vulnerable Windows systems. | D11: 8.4 | E11: HIGH | F11: 2 | G11: 3 | H11: HIGH | I11: 14.4 | J11: NO | K11: 2026-02-26 00:15 | L11: CHECK_VENDOR | M11: See CVE details | N11: P3 | O11: CVE - IP enrichment n/a | P11: 0 | Q11: 0 | R11: T1190:Exploit Public-Facing Application | T1203:Exploitation for Client Execution | S11: 1 | T11: LOW (40%) | U11: UNLIKELY | V11: CHECK_VENDOR | W11: https://nvd.nist.gov/vuln/detail/CVE-2019-25357 | X11: NONE | Y11: 0 | AA11: https://nvd.nist.gov/vuln/detail/CVE-2019-25357
A12: CVE | B12: CVE-2019-25358 | C12: FileOptimizer 14.00.2524 contains a denial of service vulnerability that allows attackers to crash the application by manipulating the FileOptimizer32.ini configuration file. Attackers can overwrite the TempDirectory parameter with a 5000-character buffer to cause the application to crash when opening options. | D12: 7.5 | E12: HIGH | F12: 2 | G12: 3 | H12: HIGH | I12: 13.5 | J12: NO | K12: 2026-02-26 00:15 | L12: CHECK_VENDOR | M12: See CVE details | N12: P3 | O12: CVE - IP enrichment n/a | P12: 0 | Q12: 0 | R12: T1499:Endpoint Denial of Service | S12: 1 | T12: LOW (40%) | U12: UNLIKELY | V12: CHECK_VENDOR | W12: https://nvd.nist.gov/vuln/detail/CVE-2019-25358 | X12: NONE | Y12: 0 | AA12: https://nvd.nist.gov/vuln/detail/CVE-2019-25358
A13: CVE | B13: CVE-2019-25359 | C13: SD.NET RIM versions before 4.7.3c contain a SQL injection vulnerability that allows attackers to inject malicious SQL statements through POST parameters 'idtyp' and 'idgremium'. Attackers can exploit this vulnerability by crafting specially formed POST requests to the /vorlagen/ endpoint, enabling unauthorized database manipulation and potential information disclosure. | D13: 8.2 | E13: HIGH | F13: 2 | G13: 3 | H13: HIGH | I13: 14.2 | J13: NO | K13: 2026-02-26 00:15 | L13: CHECK_VENDOR | M13: See CVE details | N13: P3 | O13: CVE - IP enrichment n/a | P13: 0 | Q13: 0 | R13: T1185:Browser Session Hijacking | T1190:Exploit Public-Facing Application | T1213:Data from Information Repositories | S13: 1 | T13: LOW (40%) | U13: UNLIKELY | V13: CHECK_VENDOR | W13: https://nvd.nist.gov/vuln/detail/CVE-2019-25359 | X13: NONE | Y13: 0 | AA13: https://nvd.nist.gov/vuln/detail/CVE-2019-25359
... A1123: CVE | B1123: CVE-2025-11848 | C1123: A null pointer dereference vulnerability in the Wake-on-LAN CGI program of the Zyxel VMG3625-T50B firmware version through 5.50(ABPM.9.6)C0 and the Zyxel WX3100-T0 firmware versions through 5.50(ABVL.4.8)C0 could allow an authenticated attacker with administrator privileges to trigger a denial-of-service (DoS) condition by sending a crafted HTTP request. | D1123: 4.9 | E1123: MEDIUM | F1123: 2 | G1123: 2 | H1123: MEDIUM | I1123: 8.9 | J1123: NO | K1123: 2026-02-26 00:15 | L1123: YES | M1123: zyxel vmg4005-b60a_firmware * | zyxel pm7500-00 - | zyxel ex7501-b0 - | N1123: P4 | O1123: CVE - IP enrichment n/a | P1123: 0.0018 | Q1123: 0.3897 | R1123: T1499:Endpoint Denial of Service | S1123: 1 | T1123: LOW (40%) | U1123: UNLIKELY | V1123: PATCH_AVAILABLE | W1123: https://nvd.nist.gov/vuln/detail/CVE-2025-11848 | X1123: NONE | Y1123: 0 | AA1123: https://nvd.nist.gov/vuln/detail/CVE-2025-11848
A1124: CVE | B1124: CVE-2025-13942 | C1124: A command injection vulnerability in the UPnP function of the Zyxel EX3510-B0 firmware versions through 5.17(ABUP.15.1)C0 could allow a remote attacker to execute operating system (OS) commands on an affected device by sending specially crafted UPnP SOAP requests. | D1124: 9.8 | E1124: CRITICAL | F1124: 2 | G1124: 3 | H1124: HIGH | I1124: 15.8 | J1124: NO | K1124: 2026-02-26 00:15 | L1124: YES | M1124: zyxel ex5510-b0 - | zyxel dx4510-b1_firmware * | zyxel dx4510-b0 - | N1124: P3 | O1124: CVE - IP enrichment n/a | P1124: 0 | Q1124: 0 | R1124: T1059:Command and Scripting Interpreter | S1124: 1 | T1124: LOW (40%) | U1124: UNLIKELY | V1124: PATCH_AVAILABLE | W1124: https://nvd.nist.gov/vuln/detail/CVE-2025-13942 | X1124: NONE | Y1124: 0 | Z1124: [SecurityAffairs] Critical Zyxel router flaw exposed devices to remote attacks | AA1124: https://nvd.nist.gov/vuln/detail/CVE-2025-13942
A1125: CVE | B1125: CVE-2025-13943 | C1125: A post-authentication command injection vulnerability in the log file download function of the Zyxel EX3301-T0 firmware versions through 5.50(ABVY.7)C0 could allow an authenticated attacker to execute operating system (OS) commands on an affected device. | D1125: 8.8 | E1125: HIGH | F1125: 2 | G1125: 3 | H1125: HIGH | I1125: 14.8 | J1125: NO | K1125: 2026-02-26 00:15 | L1125: YES | M1125: zyxel vmg4005-b60a_firmware * | zyxel pm7500-00 - | zyxel ex7501-b0 - | N1125: P3 | O1125: CVE - IP enrichment n/a | P1125: 0 | Q1125: 0 | R1125: T1059:Command and Scripting Interpreter | S1125: 1 | T1125: LOW (40%) | U1125: UNLIKELY | V1125: PATCH_AVAILABLE | W1125: https://nvd.nist.gov/vuln/detail/CVE-2025-13943 | X1125: NONE | Y1125: 0 | AA1125: https://nvd.nist.gov/vuln/detail/CVE-2025-13943
A1126: CVE | B1126: CVE-2026-1459 | C1126: A post-authentication command injection vulnerability in the TR-369 certificate download CGI program of the Zyxel VMG3625-T50B firmware versions through 5.50(ABPM.9.7)C0 could allow an authenticated attacker with administrator privileges to execute operating system (OS) commands on an affected device. | D1126: 7.2 | E1126: HIGH | F1126: 2 | G1126: 3 | H1126: HIGH | I1126: 13.2 | J1126: NO | K1126: 2026-02-26 00:15 | L1126: YES | M1126: zyxel vmg3625-t50b - | zyxel emg5523-t50b_firmware * | zyxel emg3525-t50b - | N1126: P3 | O1126: CVE - IP enrichment n/a | P1126: 0 | Q1126: 0 | R1126: T1059:Command and Scripting Interpreter | S1126: 1 | T1126: LOW (40%) | U1126: UNLIKELY | V1126: PATCH_AVAILABLE | W1126: https://nvd.nist.gov/vuln/detail/CVE-2026-1459 | X1126: NONE | Y1126: 0 | AA1126: https://nvd.nist.gov/vuln/detail/CVE-2026-1459
A1127: CVE | B1127: CVE-2026-25989 | C1127: ImageMagick is free and open-source software used for editing and manipulating digital images. Prior to versions 7.1.2-15 and 6.9.13-40, a crafted SVG file can cause a denial of service. An off-by-one boundary check (`>` instead of `>=`) that allows bypass the guard and reach an undefined `(size_t)` cast. Versions 7.1.2-15 and 6.9.13-40 contain a patch. | D1127: 7.5 | E1127: HIGH | F1127: 2 | G1127: 3 | H1127: HIGH | I1127: 13.5 | J1127: NO | K1127: 2026-02-26 00:15 | L1127: YES | M1127: imagemagick imagemagick * | N1127: P3 | O1127: CVE - IP enrichment n/a | P1127: 0 | Q1127: 0 | R1127: T1190:Exploit Public-Facing Application | T1499:Endpoint Denial of Service | S1127: 1 | T1127: LOW (40%) | U1127: UNLIKELY | V1127: PATCH_AVAILABLE | W1127: https://nvd.nist.gov/vuln/detail/CVE-2026-25989 | X1127: NONE | Y1127: 0 | AA1127: https://nvd.nist.gov/vuln/detail/CVE-2026-25989
A1128: CVE | B1128: CVE-2026-26066 | C1128: ImageMagick is free and open-source software used for editing and manipulating digital images. Prior to versions 7.1.2-15 and 6.9.13-40, a crafted profile contain invalid IPTC data may cause an infinite loop when writing it with `IPTCTEXT`. Versions 7.1.2-15 and 6.9.13-40 contain a patch. | D1128: 6.2 | E1128: MEDIUM | F1128: 2 | G1128: 2 | H1128: MEDIUM | I1128: 10.2 | J1128: NO | K1128: 2026-02-26 00:15 | L1128: CHECK_VENDOR | M1128: imagemagick imagemagick * | N1128: P4 | O1128: CVE - IP enrichment n/a | P1128: 0 | Q1128: 0 | R1128: T1190:Exploit Public-Facing Application | S1128: 1 | T1128: LOW (40%) | U1128: UNLIKELY | V1128: CHECK_VENDOR | W1128: https://nvd.nist.gov/vuln/detail/CVE-2026-26066 | X1128: NONE | Y1128: 0 | AA1128: https://nvd.nist.gov/vuln/detail/CVE-2026-26066
A1129: CVE | B1129: CVE-2026-26198 | C1129: Ormar is a async mini ORM for Python. In versions 0.9.9 through 0.22.0, when performing aggregate queries, Ormar ORM constructs SQL expressions by passing user-supplied column names directly into `sqlalchemy.text()` without any validation or sanitization. The `min()` and `max()` methods in the `QuerySet` class accept arbitrary string input as the column parameter. While `sum()` and `avg()` are partially protected by an `is_numeric` type check that rejects non-existent fields, `min()` and `max()` | D1129: 9.8 | E1129: CRITICAL | F1129: 2 | G1129: 3 | H1129: HIGH | I1129: 15.8 | J1129: NO | K1129: 2026-02-26 00:15 | L1129: YES | M1129: collerek ormar * | N1129: P3 | O1129: CVE - IP enrichment n/a | P1129: 0 | Q1129: 0 | R1129: T1190:Exploit Public-Facing Application | S1129: 1 | T1129: LOW (40%) | U1129: UNLIKELY | V1129: PATCH_AVAILABLE | W1129: https://nvd.nist.gov/vuln/detail/CVE-2026-26198 | X1129: NONE | Y1129: 0 | AA1129: https://nvd.nist.gov/vuln/detail/CVE-2026-26198
A1130: CVE | B1130: CVE-2026-26283 | C1130: ImageMagick is free and open-source software used for editing and manipulating digital images. Prior to versions 7.1.2-15 and 6.9.13-40, a `continue` statement in the JPEG extent binary search loop in the jpeg encoder causes an infinite loop when writing persistently fails. An attacker can trigger a 100% CPU consumption and process hang (Denial of Service) with a crafted image. Versions 7.1.2-15 and 6.9.13-40 contain a patch. | D1130: 6.2 | E1130: MEDIUM | F1130: 2 | G1130: 2 | H1130: MEDIUM | I1130: 10.2 | J1130: NO | K1130: 2026-02-26 00:15 | L1130: YES | M1130: imagemagick imagemagick * | N1130: P4 | O1130: CVE - IP enrichment n/a | P1130: 0 | Q1130: 0 | R1130: T1190:Exploit Public-Facing Application | T1499:Endpoint Denial of Service | S1130: 1 | T1130: LOW (40%) | U1130: UNLIKELY | V1130: PATCH_AVAILABLE | W1130: https://nvd.nist.gov/vuln/detail/CVE-2026-26283 | X1130: NONE | Y1130: 0 | AA1130: https://nvd.nist.gov/vuln/detail/CVE-2026-26283
A1131: CVE | B1131: CVE-2026-26284 | C1131: ImageMagick is free and open-source software used for editing and manipulating digital images. Prior to versions 7.1.2-15 and 6.9.13-40, ImageMagick lacks proper boundary checking when processing Huffman-coded data from PCD (Photo CD) files. The decoder contains an function that has an incorrect initialization that could cause an out of bounds read. Versions 7.1.2-15 and 6.9.13-40 contain a patch. | D1131: 6.5 | E1131: MEDIUM | F1131: 2 | G1131: 2 | H1131: MEDIUM | I1131: 10.5 | J1131: NO | K1131: 2026-02-26 00:15 | L1131: YES | M1131: imagemagick imagemagick * | N1131: P4 | O1131: CVE - IP enrichment n/a | P1131: 0.0004 | Q1131: 0.1313 | R1131: T1203:Exploitation for Client Execution | T1190:Exploit Public-Facing Application | S1131: 1 | T1131: LOW (40%) | U1131: UNLIKELY | V1131: PATCH_AVAILABLE | W1131: https://nvd.nist.gov/vuln/detail/CVE-2026-26284 | X1131: NONE | Y1131: 0 | AA1131: https://nvd.nist.gov/vuln/detail/CVE-2026-26284
A1132: CVE | B1132: CVE-2026-26331 | C1132: yt-dlp is a command-line audio/video downloader. Starting in version 2023.06.21 and prior to version 2026.02.21, when yt-dlp's `--netrc-cmd` command-line option (or `netrc_cmd` Python API parameter) is used, an attacker could achieve arbitrary command injection on the user's system with a maliciously crafted URL. yt-dlp maintainers assume the impact of this vulnerability to be high for anyone who uses `--netrc-cmd` in their command/configuration or `netrc_cmd` in their Python scripts. Even thoug | D1132: 8.8 | E1132: HIGH | F1132: 2 | G1132: 3 | H1132: HIGH | I1132: 14.8 | J1132: NO | K1132: 2026-02-26 00:15 | L1132: YES | M1132: yt-dlp_project yt-dlp * | N1132: P3 | O1132: CVE - IP enrichment n/a | P1132: 0 | Q1132: 0 | R1132: T1059:Command and Scripting Interpreter | S1132: 1 | T1132: LOW (40%) | U1132: UNLIKELY | V1132: PATCH_AVAILABLE | W1132: https://nvd.nist.gov/vuln/detail/CVE-2026-26331 | X1132: NONE | Y1132: 0 | AA1132: https://nvd.nist.gov/vuln/detail/CVE-2026-26331
A1133: CVE | B1133: CVE-2026-26981 | C1133: OpenEXR provides the specification and reference implementation of the EXR file format, an image storage format for the motion picture industry. In versions 3.3.0 through 3.3.6 and 3.4.0 through 3.4.4, a heap-buffer-overflow (OOB read) occurs in the `istream_nonparallel_read` function in `ImfContextInit.cpp` when parsing a malformed EXR file through a memory-mapped `IStream`. A signed integer subtraction produces a negative value that is implicitly converted to `size_t`, resulting in a massive l | D1133: 6.5 | E1133: MEDIUM | F1133: 2 | G1133: 2 | H1133: MEDIUM | I1133: 10.5 | J1133: NO | K1133: 2026-02-26 00:15 | L1133: YES | M1133: openexr openexr * | N1133: P4 | O1133: CVE - IP enrichment n/a | P1133: 0 | Q1133: 0 | R1133: T1190:Exploit Public-Facing Application | S1133: 1 | T1133: LOW (40%) | U1133: UNLIKELY | V1133: PATCH_AVAILABLE | W1133: https://nvd.nist.gov/vuln/detail/CVE-2026-26981 | X1133: NONE | Y1133: 0 | AA1133: https://nvd.nist.gov/vuln/detail/CVE-2026-26981
A1134: CVE | B1134: CVE-2026-26983 | C1134: ImageMagick is free and open-source software used for editing and manipulating digital images. Prior to versions 7.1.2-15 and 6.9.13-40, the MSL interpreter crashes when processing a invalid ` ` element that causes it to use an image after it has been freed. Versions 7.1.2-15 and 6.9.13-40 contain a patch. | D1134: 5.3 | E1134: MEDIUM | F1134: 2 | G1134: 2 | H1134: MEDIUM | I1134: 9.3 | J1134: NO | K1134: 2026-02-26 00:15 | L1134: YES | M1134: imagemagick imagemagick * | N1134: P4 | O1134: CVE - IP enrichment n/a | P1134: 0 | Q1134: 0 | R1134: T1499:Endpoint Denial of Service | T1203:Exploitation for Client Execution | T1190:Exploit Public-Facing Application | S1134: 1 | T1134: LOW (40%) | U1134: UNLIKELY | V1134: PATCH_AVAILABLE | W1134: https://nvd.nist.gov/vuln/detail/CVE-2026-26983 | X1134: NONE | Y1134: 0 | AA1134: https://nvd.nist.gov/vuln/detail/CVE-2026-26983
A1135: CVE | B1135: CVE-2026-27126 | C1135: Craft is a content management system (CMS). In versions 4.5.0-RC1 through 4.16.18 and 5.0.0-RC1 through 5.8.22, a stored Cross-site Scripting (XSS) vulnerability exists in the `editableTable.twig` component when using the `html` column type. The application fails to sanitize the input, allowing an attacker to execute arbitrary JavaScript when another user views a page with the malicious table field. In order to exploit the vulnerability, an attacker must have an administrator account, and `allow | D1135: 5 | E1135: MEDIUM | F1135: 2 | G1135: 2 | H1135: MEDIUM | I1135: 9 | J1135: NO | K1135: 2026-02-26 00:15 | L1135: CHECK_VENDOR | M1135: See CVE details | N1135: P4 | O1135: CVE - IP enrichment n/a | P1135: 0 | Q1135: 0 | R1135: T1189:Drive-by Compromise | S1135: 1 | T1135: LOW (40%) | U1135: UNLIKELY | V1135: CHECK_VENDOR | W1135: https://nvd.nist.gov/vuln/detail/CVE-2026-27126 | X1135: NONE | Y1135: 0 | AA1135: https://nvd.nist.gov/vuln/detail/CVE-2026-27126
A1136: CVE | B1136: CVE-2026-27127 | C1136: Craft is a content management system (CMS). In versions 4.5.0-RC1 through 4.16.18 and 5.0.0-RC1 through 5.8.22, the SSRF validation in Craft CMS’s GraphQL Asset mutation performs DNS resolution separately from the HTTP request. This Time-of-Check-Time-of-Use (TOCTOU) vulnerability enables DNS rebinding attacks, where an attacker’s DNS server returns different IP addresses for validation compared to the actual request. This is a bypass of the security fix for CVE-2025-68437 that allows access to | D1136: 6.3 | E1136: MEDIUM | F1136: 2 | G1136: 2 | H1136: MEDIUM | I1136: 10.3 | J1136: NO | K1136: 2026-02-26 00:15 | L1136: YES | M1136: craftcms craft_cms * | craftcms craft_cms 3.5.0 | N1136: P4 | O1136: CVE - IP enrichment n/a | P1136: 0 | Q1136: 0 | R1136: T1090:Proxy | S1136: 1 | T1136: LOW (40%) | U1136: UNLIKELY | V1136: PATCH_AVAILABLE | W1136: https://nvd.nist.gov/vuln/detail/CVE-2026-27127 | X1136: NONE | Y1136: 0 | AA1136: https://nvd.nist.gov/vuln/detail/CVE-2026-27127
... A1152: CVE | B1152: CVE-2026-24314 | C1152: Under certain conditions SAP S/4HANA (Manage Payment Media) allows an authenticated attacker to access information which would otherwise be restricted. This could cause low impact on confidentiality of the application while integrity and availability are not impacted. | D1152: 4.3 | E1152: MEDIUM | F1152: 2 | G1152: 2 | H1152: MEDIUM | I1152: 8.3 | J1152: NO | K1152: 2026-02-26 00:15 | L1152: CHECK_VENDOR | M1152: See CVE details | N1152: P4 | O1152: CVE - IP enrichment n/a | P1152: 0.0003 | Q1152: 0.0741 | R1152: T1190:Exploit Public-Facing Application | S1152: 1 | T1152: LOW (40%) | U1152: UNLIKELY | V1152: CHECK_VENDOR | W1152: https://nvd.nist.gov/vuln/detail/CVE-2026-24314 | X1152: NONE | Y1152: 0 | AA1152: https://nvd.nist.gov/vuln/detail/CVE-2026-24314
A1153: CVE | B1153: CVE-2025-40538 | C1153: A broken access control vulnerability exists in Serv-U which when exploited, gives a malicious actor the ability to create a system admin user and execute arbitrary code as a privileged account via domain admin or group admin privileges. This issue requires administrative privileges to abuse. On Windows deployments, the risk is scored as a medium because services frequently run under less-privileged service accounts by default. | D1153: 9.1 | E1153: CRITICAL | F1153: 2 | G1153: 3 | H1153: HIGH | I1153: 15.1 | J1153: NO | K1153: 2026-02-26 00:15 | L1153: YES | M1153: solarwinds serv-u * | N1153: P3 | O1153: CVE - IP enrichment n/a | P1153: 0 | Q1153: 0 | R1153: T1203:Exploitation for Client Execution | S1153: 1 | T1153: LOW (40%) | U1153: UNLIKELY | V1153: PATCH_AVAILABLE | W1153: https://nvd.nist.gov/vuln/detail/CVE-2025-40538 | X1153: NONE | Y1153: 0 | Z1153: [TheHackerNews] SolarWinds Patches 4 Critical Serv-U 15.5 Flaws Allowing Root Code Exe | AA1153: https://nvd.nist.gov/vuln/detail/CVE-2025-40538
A1154: CVE | B1154: CVE-2025-40539 | C1154: A type confusion vulnerability exists in Serv-U which when exploited, gives a malicious actor the ability to execute arbitrary native code as privileged account. This issue requires administrative privileges to abuse. On Windows deployments, the risk is scored as a medium because services frequently run under less-privileged service accounts by default. | D1154: 9.1 | E1154: CRITICAL | F1154: 2 | G1154: 3 | H1154: HIGH | I1154: 15.1 | J1154: NO | K1154: 2026-02-26 00:15 | L1154: YES | M1154: solarwinds serv-u * | N1154: P3 | O1154: CVE - IP enrichment n/a | P1154: 0 | Q1154: 0 | R1154: T1190:Exploit Public-Facing Application | S1154: 1 | T1154: LOW (40%) | U1154: UNLIKELY | V1154: PATCH_AVAILABLE | W1154: https://nvd.nist.gov/vuln/detail/CVE-2025-40539 | X1154: NONE | Y1154: 0 | AA1154: https://nvd.nist.gov/vuln/detail/CVE-2025-40539
A1155: CVE | B1155: CVE-2025-40540 | C1155: A type confusion vulnerability exists in Serv-U which when exploited, gives a malicious actor the ability to execute arbitrary native code as privileged account. This issue requires administrative privileges to abuse. On Windows deployments, the risk is scored as a medium because services frequently run under less-privileged service accounts by default. | D1155: 9.1 | E1155: CRITICAL | F1155: 2 | G1155: 3 | H1155: HIGH | I1155: 15.1 | J1155: NO | K1155: 2026-02-26 00:15 | L1155: YES | M1155: solarwinds serv-u * | N1155: P3 | O1155: CVE - IP enrichment n/a | P1155: 0 | Q1155: 0 | R1155: T1190:Exploit Public-Facing Application | S1155: 1 | T1155: LOW (40%) | U1155: UNLIKELY | V1155: PATCH_AVAILABLE | W1155: https://nvd.nist.gov/vuln/detail/CVE-2025-40540 | X1155: NONE | Y1155: 0 | AA1155: https://nvd.nist.gov/vuln/detail/CVE-2025-40540
A1156: CVE | B1156: CVE-2025-40541 | C1156: An Insecure Direct Object Reference (IDOR) vulnerability exists in Serv-U, which when exploited, gives a malicious actor the ability to execute native code as a privileged account. This issue requires administrative privileges to abuse. On Windows deployments, the risk is scored as a medium because services frequently run under less-privileged service accounts by default. | D1156: 9.1 | E1156: CRITICAL | F1156: 2 | G1156: 3 | H1156: HIGH | I1156: 15.1 | J1156: NO | K1156: 2026-02-26 00:15 | L1156: YES | M1156: solarwinds serv-u * | N1156: P3 | O1156: CVE - IP enrichment n/a | P1156: 0 | Q1156: 0 | R1156: T1190:Exploit Public-Facing Application | S1156: 1 | T1156: LOW (40%) | U1156: UNLIKELY | V1156: PATCH_AVAILABLE | W1156: https://nvd.nist.gov/vuln/detail/CVE-2025-40541 | X1156: NONE | Y1156: 0 | AA1156: https://nvd.nist.gov/vuln/detail/CVE-2025-40541
A1157: CVE | B1157: CVE-2026-1229 | C1157: The CombinedMult function in the CIRCL ecc/p384 package (secp384r1 curve) produces an incorrect value for specific inputs. The issue is fixed by using complete addition formulas. ECDH and ECDSA signing relying on this curve are not affected. The bug was fixed in v1.6.3 https://github.com/cloudflare/circl/releases/tag/v1.6.3 . | D1157: 5 | E1157: MEDIUM | F1157: 2 | G1157: 2 | H1157: MEDIUM | I1157: 9 | J1157: NO | K1157: 2026-02-26 00:15 | L1157: CHECK_VENDOR | M1157: See CVE details | N1157: P4 | O1157: CVE - IP enrichment n/a | P1157: 0 | Q1157: 0 | R1157: T1190:Exploit Public-Facing Application | S1157: 1 | T1157: LOW (40%) | U1157: UNLIKELY | V1157: CHECK_VENDOR | W1157: https://nvd.nist.gov/vuln/detail/CVE-2026-1229 | X1157: NONE | Y1157: 0 | AA1157: https://nvd.nist.gov/vuln/detail/CVE-2026-1229
A1158: CVE | B1158: CVE-2024-1524 | C1158: When the "Silent Just-In-Time Provisioning" feature is enabled for a federated identity provider (IDP) there is a risk that a local user store user's information may be replaced during the account provisioning process in cases where federated users share the same username as local users. There will be no impact on your deployment if any of the preconditions mentioned below are not met. Only when all the preconditions mentioned below are fulfilled could a malicious actor associate a targeted | D1158: 7.7 | E1158: HIGH | F1158: 2 | G1158: 3 | H1158: HIGH | I1158: 13.7 | J1158: NO | K1158: 2026-02-26 00:15 | L1158: CHECK_VENDOR | M1158: See CVE details | N1158: P3 | O1158: CVE - IP enrichment n/a | P1158: 0.0005 | Q1158: 0.1519 | R1158: T1190:Exploit Public-Facing Application | S1158: 1 | T1158: LOW (40%) | U1158: UNLIKELY | V1158: CHECK_VENDOR | W1158: https://nvd.nist.gov/vuln/detail/CVE-2024-1524 | X1158: NONE | Y1158: 0 | AA1158: https://nvd.nist.gov/vuln/detail/CVE-2024-1524
A1159: CVE | B1159: CVE-2025-11165 | C1159: A sandbox escape vulnerability exists in dotCMS’s Velocity scripting engine (VTools) that allows authenticated users with scripting privileges to bypass class and package restrictions enforced by SecureUberspectorImpl. By dynamically modifying the Velocity engine’s runtime configuration and reinitializing its Uberspect, a malicious actor can remove the introspector.restrict.classes and introspector.restrict.packages protections. Once these restrictions are cleared, the attacker can access arbi | D1159: 8.5 | E1159: HIGH | F1159: 2 | G1159: 3 | H1159: HIGH | I1159: 14.5 | J1159: NO | K1159: 2026-02-26 00:15 | L1159: CHECK_VENDOR | M1159: See CVE details | N1159: P3 | O1159: CVE - IP enrichment n/a | P1159: 0 | Q1159: 0 | R1159: T1190:Exploit Public-Facing Application | S1159: 1 | T1159: LOW (40%) | U1159: UNLIKELY | V1159: CHECK_VENDOR | W1159: https://nvd.nist.gov/vuln/detail/CVE-2025-11165 | X1159: NONE | Y1159: 0 | AA1159: https://nvd.nist.gov/vuln/detail/CVE-2025-11165
A1160: CVE | B1160: CVE-2024-56373 | C1160: DAG Author (who already has quite a lot of permissions) could manipulate database of Airflow 2 in the way to execute arbitrary code in the web-server context, which they should normally not be able to do, leading to potentially remote code execution in the context of web-server (server-side) as a result of a user viewing historical task information. The functionality responsible for that (log template history) has been disabled by default in 2.11.1 and users should upgrade to Airflow 3 if they | D1160: 8.4 | E1160: HIGH | F1160: 2 | G1160: 3 | H1160: HIGH | I1160: 14.4 | J1160: NO | K1160: 2026-02-26 00:15 | L1160: YES | M1160: apache airflow * | N1160: P1 | O1160: CVE - IP enrichment n/a | P1160: 0 | Q1160: 0 | R1160: T1059:Command and Scripting Interpreter | T1190:Exploit Public-Facing Application | T1210:Exploitation of Remote Services | S1160: 2 | T1160: HIGH (72%) | U1160: HIGH | V1160: PATCH_AVAILABLE | W1160: https://nvd.nist.gov/vuln/detail/CVE-2024-56373 | X1160: http://www.zerodayinitiative.com/advisories/ZDI-26-123/ | Y1160: 0 | AA1160: https://nvd.nist.gov/vuln/detail/CVE-2024-56373
A1161: CVE | B1161: CVE-2025-27555 | C1161: Airflow versions before 2.11.1 have a vulnerability that allows authenticated users with audit log access to see sensitive values in audit logs which they should not see. When sensitive connection parameters were set via airflow CLI, values of those variables appeared in the audit log and were stored unencrypted in the Airflow database. While this risk is limited to users with audit log access, it is recommended to upgrade to Airflow 2.11.1 or a later version, which addresses this issue. Users w | D1161: 6.5 | E1161: MEDIUM | F1161: 2 | G1161: 2 | H1161: MEDIUM | I1161: 10.5 | J1161: NO | K1161: 2026-02-26 00:15 | L1161: YES | M1161: apache airflow * | N1161: P1 | O1161: CVE - IP enrichment n/a | P1161: 0.0003 | Q1161: 0.0968 | R1161: T1190:Exploit Public-Facing Application | S1161: 2 | T1161: HIGH (72%) | U1161: HIGH | V1161: PATCH_AVAILABLE | W1161: https://nvd.nist.gov/vuln/detail/CVE-2025-27555 | X1161: http://www.zerodayinitiative.com/advisories/ZDI-26-123/ | Y1161: 0 | AA1161: https://nvd.nist.gov/vuln/detail/CVE-2025-27555
A1162: CVE | B1162: CVE-2026-2664 | C1162: An out of bounds read vulnerability in the grpcfuse kernel module present in the Linux VM in Docker Desktop for Windows, Linux and macOS up to version 4.61.0 could allow a local attacker to cause an unspecified impact by writing to /proc/docker entries. The issue has been fixed in Docker Desktop 4.62.0 . | D1162: 5 | E1162: MEDIUM | F1162: 2 | G1162: 2 | H1162: MEDIUM | I1162: 9 | J1162: NO | K1162: 2026-02-26 00:15 | L1162: CHECK_VENDOR | M1162: See CVE details | N1162: P1 | O1162: CVE - IP enrichment n/a | P1162: 0 | Q1162: 0 | R1162: T1203:Exploitation for Client Execution | S1162: 2 | T1162: HIGH (72%) | U1162: HIGH | V1162: CHECK_VENDOR | W1162: https://nvd.nist.gov/vuln/detail/CVE-2026-2664 | X1162: http://www.zerodayinitiative.com/advisories/ZDI-26-125/ | Y1162: 0 | AA1162: https://nvd.nist.gov/vuln/detail/CVE-2026-2664
A1163: CVE | B1163: CVE-2025-14577 | C1163: Slican NCP/IPL/IPM/IPU devices are vulnerable to PHP Function Injection. An unauthenticated remote attacker is able to execute arbitrary PHP commands by sending specially crafted requests to /webcti/session_ajax.php endpoint. This issue was fixed in version 1.24.0190 (Slican NCP) and 6.61.0010 (Slican IPL/IPM/IPU). | D1163: 8.5 | E1163: HIGH | F1163: 2 | G1163: 3 | H1163: HIGH | I1163: 14.5 | J1163: NO | K1163: 2026-02-26 00:15 | L1163: CHECK_VENDOR | M1163: See CVE details | N1163: P3 | O1163: CVE - IP enrichment n/a | P1163: 0 | Q1163: 0 | R1163: T1078:Valid Accounts | S1163: 1 | T1163: LOW (40%) | U1163: UNLIKELY | V1163: CHECK_VENDOR | W1163: https://nvd.nist.gov/vuln/detail/CVE-2025-14577 | X1163: NONE | Y1163: 0 | AA1163: https://nvd.nist.gov/vuln/detail/CVE-2025-14577
A1164: CVE | B1164: CVE-2026-1772 | C1164: RTU500 web interface: An unprivileged user can read user management information. The information cannot be accessed via the RTU500 web user interface but requires further tools like browser development utilities to access them without required privileges. | D1164: 5 | E1164: MEDIUM | F1164: 2 | G1164: 2 | H1164: MEDIUM | I1164: 9 | J1164: NO | K1164: 2026-02-26 00:15 | L1164: CHECK_VENDOR | M1164: See CVE details | N1164: P4 | O1164: CVE - IP enrichment n/a | P1164: 0 | Q1164: 0 | R1164: T1190:Exploit Public-Facing Application | S1164: 1 | T1164: LOW (40%) | U1164: UNLIKELY | V1164: CHECK_VENDOR | W1164: https://nvd.nist.gov/vuln/detail/CVE-2026-1772 | X1164: NONE | Y1164: 0 | AA1164: https://nvd.nist.gov/vuln/detail/CVE-2026-1772
A1165: CVE | B1165: CVE-2026-1773 | C1165: IEC 60870-5-104: Potential Denial of Service impact on reception of invalid U-format frame. Product is only affected if IEC 60870-5-104 bi-directional functionality is configured. Enabling secure communication following IEC 62351-3 does not remediate the vulnerability but mitigates the risk of exploitation. | D1165: 5 | E1165: MEDIUM | F1165: 2 | G1165: 2 | H1165: MEDIUM | I1165: 9 | J1165: NO | K1165: 2026-02-26 00:15 | L1165: CHECK_VENDOR | M1165: See CVE details | N1165: P4 | O1165: CVE - IP enrichment n/a | P1165: 0 | Q1165: 0 | R1165: T1499:Endpoint Denial of Service | S1165: 1 | T1165: LOW (40%) | U1165: UNLIKELY | V1165: CHECK_VENDOR | W1165: https://nvd.nist.gov/vuln/detail/CVE-2026-1773 | X1165: NONE | Y1165: 0 | AA1165: https://nvd.nist.gov/vuln/detail/CVE-2026-1773
... A1428: CVE | B1428: CVE-2026-20126 | C1428: A vulnerability in Cisco Catalyst SD-WAN Manager could allow an authenticated, local attacker with low privileges to gain root privileges on the underlying operating system. This vulnerability is due to an insufficient user authentication mechanism in the REST API. An attacker could exploit this vulnerability by sending a request to the REST API of the affected system. A successful exploit could allow the attacker to&nbsp;gain root privileges on the underlying operating system. | D1428: 8.8 | E1428: HIGH | F1428: 2 | G1428: 3 | H1428: HIGH | I1428: 14.8 | J1428: NO | K1428: 2026-02-26 00:15 | L1428: CHECK_VENDOR | M1428: See CVE details | N1428: P3 | O1428: CVE - IP enrichment n/a | P1428: 0 | Q1428: 0 | R1428: T1190:Exploit Public-Facing Application | S1428: 1 | T1428: LOW (40%) | U1428: UNLIKELY | V1428: CHECK_VENDOR | W1428: https://nvd.nist.gov/vuln/detail/CVE-2026-20126 | X1428: NONE | Y1428: 0 | AA1428: https://nvd.nist.gov/vuln/detail/CVE-2026-20126
A1429: CVE | B1429: CVE-2026-20127 | C1429: A vulnerability in the peering authentication in Cisco Catalyst SD-WAN Controller, formerly SD-WAN vSmart, and Cisco Catalyst SD-WAN Manager, formerly SD-WAN vManage, could allow an unauthenticated, remote attacker to bypass authentication and obtain administrative privileges on an affected system. This vulnerability exists because the peering authentication mechanism in an affected system is not working properly. An attacker could exploit this vulnerability by sending crafted requests to an | D1429: 10 | E1429: CRITICAL | F1429: 3 | G1429: 3 | H1429: CRITICAL | I1429: 19 | J1429: YES | K1429: 2026-02-26 00:15 | L1429: CHECK_VENDOR | M1429: See CVE details | N1429: P1 | O1429: CVE - IP enrichment n/a | P1429: 0 | Q1429: 0 | R1429: T1078:Valid Accounts | T1110:Brute Force | S1429: 2 | T1429: HIGH (72%) | U1429: CONFIRMED | V1429: CHECK_VENDOR | W1429: https://nvd.nist.gov/vuln/detail/CVE-2026-20127 | X1429: NONE | Y1429: 0 | Z1429: [BleepingComputer] Critical Cisco SD-WAN bug exploited in zero-day attacks since 2023 | AA1429: https://nvd.nist.gov/vuln/detail/CVE-2026-20127
A1430: CVE | B1430: CVE-2026-20128 | C1430: A vulnerability in the Data Collection Agent (DCA) feature of Cisco Catalyst SD-WAN Manager could allow an authenticated, local attacker to gain DCA user privileges on an affected system. To exploit this vulnerability, the attacker must have valid&nbsp;vmanage credentials on the affected system. This vulnerability is due to the presence of a credential file for the DCA user on an affected system. An attacker could exploit this vulnerability by accessing the filesystem as a low-privileged user | D1430: 7.5 | E1430: HIGH | F1430: 2 | G1430: 3 | H1430: HIGH | I1430: 13.5 | J1430: NO | K1430: 2026-02-26 00:15 | L1430: CHECK_VENDOR | M1430: See CVE details | N1430: P3 | O1430: CVE - IP enrichment n/a | P1430: 0 | Q1430: 0 | R1430: T1552:Unsecured Credentials | S1430: 1 | T1430: LOW (40%) | U1430: UNLIKELY | V1430: CHECK_VENDOR | W1430: https://nvd.nist.gov/vuln/detail/CVE-2026-20128 | X1430: NONE | Y1430: 0 | AA1430: https://nvd.nist.gov/vuln/detail/CVE-2026-20128
A1431: CVE | B1431: CVE-2026-20129 | C1431: A vulnerability in the API user authentication of Cisco Catalyst SD-WAN Manager could allow an unauthenticated, remote attacker to gain access to an affected system as a user who has the&nbsp;netadmin role. The vulnerability is due to improper authentication for requests that are sent to the API. An attacker could exploit this vulnerability by sending a crafted request to the API of an affected system. A successful exploit could allow the attacker to execute commands with the privileges of th | D1431: 9.8 | E1431: CRITICAL | F1431: 2 | G1431: 3 | H1431: HIGH | I1431: 15.8 | J1431: NO | K1431: 2026-02-26 00:15 | L1431: CHECK_VENDOR | M1431: See CVE details | N1431: P3 | O1431: CVE - IP enrichment n/a | P1431: 0 | Q1431: 0 | R1431: T1078:Valid Accounts | T1110:Brute Force | S1431: 1 | T1431: LOW (40%) | U1431: UNLIKELY | V1431: CHECK_VENDOR | W1431: https://nvd.nist.gov/vuln/detail/CVE-2026-20129 | X1431: NONE | Y1431: 0 | AA1431: https://nvd.nist.gov/vuln/detail/CVE-2026-20129
A1432: CVE | B1432: CVE-2026-20133 | C1432: A vulnerability in Cisco Catalyst SD-WAN Manager could allow an unauthenticated, remote attacker to view sensitive information on an affected system. This vulnerability is due to insufficient file system access restrictions. An attacker could exploit this vulnerability by accessing the API of an affected system. A successful exploit could allow the attacker to read sensitive information on the underlying operating system. | D1432: 6.5 | E1432: MEDIUM | F1432: 2 | G1432: 2 | H1432: MEDIUM | I1432: 10.5 | J1432: NO | K1432: 2026-02-26 00:15 | L1432: CHECK_VENDOR | M1432: See CVE details | N1432: P4 | O1432: CVE - IP enrichment n/a | P1432: 0 | Q1432: 0 | R1432: T1213:Data from Information Repositories | S1432: 1 | T1432: LOW (40%) | U1432: UNLIKELY | V1432: CHECK_VENDOR | W1432: https://nvd.nist.gov/vuln/detail/CVE-2026-20133 | X1432: NONE | Y1432: 0 | AA1432: https://nvd.nist.gov/vuln/detail/CVE-2026-20133
A1433: CVE | B1433: CVE-2026-26717 | C1433: An issue in OpenFUN Richie (LMS) in src/richie/apps/courses/api.py. The application used the non-constant time == operator for HMAC signature verification in the sync_course_run_from_request function. This allows remote attackers to forge valid signatures and bypass authentication by measuring response time discrepancies | D1433: 5 | E1433: MEDIUM | F1433: 2 | G1433: 2 | H1433: MEDIUM | I1433: 9 | J1433: NO | K1433: 2026-02-26 00:15 | L1433: CHECK_VENDOR | M1433: See CVE details | N1433: P4 | O1433: CVE - IP enrichment n/a | P1433: 0 | Q1433: 0 | R1433: T1190:Exploit Public-Facing Application | S1433: 1 | T1433: LOW (40%) | U1433: UNLIKELY | V1433: CHECK_VENDOR | W1433: https://nvd.nist.gov/vuln/detail/CVE-2026-26717 | X1433: NONE | Y1433: 0 | AA1433: https://nvd.nist.gov/vuln/detail/CVE-2026-26717
A1434: CVE | B1434: CVE-2026-27705 | C1434: Plane is an an open-source project management tool. Prior to version 1.2.2, the `ProjectAssetEndpoint.patch()` method in `apps/api/plane/app/views/asset/v2.py` (lines 579–593) performs a global asset lookup using only the asset ID (`pk`) via `FileAsset.objects.get(id=pk)`, without verifying that the asset belongs to the workspace and project specified in the URL path. This allows any authenticated user (including those with the GUEST role) to modify the `attributes` and `is_uploaded` status of a | D1434: 8.5 | E1434: HIGH | F1434: 2 | G1434: 3 | H1434: HIGH | I1434: 14.5 | J1434: NO | K1434: 2026-02-26 00:15 | L1434: CHECK_VENDOR | M1434: See CVE details | N1434: P3 | O1434: CVE - IP enrichment n/a | P1434: 0 | Q1434: 0 | R1434: T1190:Exploit Public-Facing Application | S1434: 1 | T1434: LOW (40%) | U1434: UNLIKELY | V1434: CHECK_VENDOR | W1434: https://nvd.nist.gov/vuln/detail/CVE-2026-27705 | X1434: NONE | Y1434: 0 | AA1434: https://nvd.nist.gov/vuln/detail/CVE-2026-27705
A1435: CVE | B1435: CVE-2026-27706 | C1435: Plane is an an open-source project management tool. Prior to version 1.2.2, a Full Read Server-Side Request Forgery (SSRF) vulnerability has been identified in the "Add Link" feature. This flaw allows an authenticated attacker with general user privileges to send arbitrary GET requests to the internal network and exfiltrate the full response body. By exploiting this vulnerability, an attacker can steal sensitive data from internal services and cloud metadata endpoints. Version 1.2.2 fixes the is | D1435: 7.7 | E1435: HIGH | F1435: 2 | G1435: 3 | H1435: HIGH | I1435: 13.7 | J1435: NO | K1435: 2026-02-26 00:15 | L1435: CHECK_VENDOR | M1435: See CVE details | N1435: P3 | O1435: CVE - IP enrichment n/a | P1435: 0 | Q1435: 0 | R1435: T1090:Proxy | T1190:Exploit Public-Facing Application | S1435: 1 | T1435: LOW (40%) | U1435: UNLIKELY | V1435: CHECK_VENDOR | W1435: https://nvd.nist.gov/vuln/detail/CVE-2026-27706 | X1435: NONE | Y1435: 0 | AA1435: https://nvd.nist.gov/vuln/detail/CVE-2026-27706
A1436: CVE | B1436: CVE-2026-27727 | C1436: mchange-commons-java, a library that provides Java utilities, includes code that mirrors early implementations of JNDI functionality, including support for remote `factoryClassLocation` values, by which code can be downloaded and invoked within a running application. If an attacker can provoke an application to read a maliciously crafted `jaxax.naming.Reference` or serialized object, they can provoke the download and execution of malicious code. Implementations of this functionality within the J | D1436: 5 | E1436: MEDIUM | F1436: 2 | G1436: 2 | H1436: MEDIUM | I1436: 9 | J1436: NO | K1436: 2026-02-26 00:15 | L1436: CHECK_VENDOR | M1436: See CVE details | N1436: P4 | O1436: CVE - IP enrichment n/a | P1436: 0 | Q1436: 0 | R1436: T1190:Exploit Public-Facing Application | S1436: 1 | T1436: LOW (40%) | U1436: UNLIKELY | V1436: CHECK_VENDOR | W1436: https://nvd.nist.gov/vuln/detail/CVE-2026-27727 | X1436: NONE | Y1436: 0 | AA1436: https://nvd.nist.gov/vuln/detail/CVE-2026-27727
A1437: CVE | B1437: CVE-2026-27728 | C1437: OneUptime is a solution for monitoring and managing online services. Prior to version 10.0.7, an OS command injection vulnerability in `NetworkPathMonitor.performTraceroute()` allows any authenticated project user to execute arbitrary operating system commands on the Probe server by injecting shell metacharacters into a monitor's destination field. Version 10.0.7 fixes the vulnerability. | D1437: 9.9 | E1437: CRITICAL | F1437: 2 | G1437: 3 | H1437: HIGH | I1437: 15.9 | J1437: NO | K1437: 2026-02-26 00:15 | L1437: CHECK_VENDOR | M1437: See CVE details | N1437: P3 | O1437: CVE - IP enrichment n/a | P1437: 0 | Q1437: 0 | R1437: T1059:Command and Scripting Interpreter | S1437: 1 | T1437: LOW (40%) | U1437: UNLIKELY | V1437: CHECK_VENDOR | W1437: https://nvd.nist.gov/vuln/detail/CVE-2026-27728 | X1437: NONE | Y1437: 0 | AA1437: https://nvd.nist.gov/vuln/detail/CVE-2026-27728
A1438: CVE | B1438: CVE-2026-27736 | C1438: BigBlueButton is an open-source virtual classroom. In versions on the 3.x branch prior to 3.0.20, the string received with errorRedirectUrl lacks validation, using it directly in the respondWithRedirect function leads to an Open Redirect vulnerability. BigBlueButton 3.0.20 patches the issue. No known workarounds are available. | D1438: 6.1 | E1438: MEDIUM | F1438: 2 | G1438: 2 | H1438: MEDIUM | I1438: 10.1 | J1438: NO | K1438: 2026-02-26 00:15 | L1438: CHECK_VENDOR | M1438: See CVE details | N1438: P4 | O1438: CVE - IP enrichment n/a | P1438: 0 | Q1438: 0 | R1438: T1189:Drive-by Compromise | T1190:Exploit Public-Facing Application | S1438: 1 | T1438: LOW (40%) | U1438: UNLIKELY | V1438: CHECK_VENDOR | W1438: https://nvd.nist.gov/vuln/detail/CVE-2026-27736 | X1438: NONE | Y1438: 0 | AA1438: https://nvd.nist.gov/vuln/detail/CVE-2026-27736
A1439: CVE | B1439: CVE-2026-27738 | C1439: The Angular SSR is a server-rise rendering tool for Angular applications. An Open Redirect vulnerability exists in the internal URL processing logic in versions on the 19.x branch prior to 19.2.21, the 20.x branch prior to 20.3.17, and the 21.x branch prior to 21.1.5 and 21.2.0-rc.1. The logic normalizes URL segments by stripping leading slashes; however, it only removes a single leading slash. When an Angular SSR application is deployed behind a proxy that passes the `X-Forwarded-Prefix` header | D1439: 5 | E1439: MEDIUM | F1439: 2 | G1439: 2 | H1439: MEDIUM | I1439: 9 | J1439: NO | K1439: 2026-02-26 00:15 | L1439: CHECK_VENDOR | M1439: See CVE details | N1439: P4 | O1439: CVE - IP enrichment n/a | P1439: 0 | Q1439: 0 | R1439: T1189:Drive-by Compromise | T1566:Phishing | S1439: 1 | T1439: LOW (40%) | U1439: UNLIKELY | V1439: CHECK_VENDOR | W1439: https://nvd.nist.gov/vuln/detail/CVE-2026-27738 | X1439: NONE | Y1439: 0 | AA1439: https://nvd.nist.gov/vuln/detail/CVE-2026-27738
A1440: CVE | B1440: CVE-2026-27849 | C1440: Due to missing neutralization of special elements, OS commands can be injected via the update functionality of a TLS-SRP connection, which is normally used for configuring devices inside the mesh network. This issue affects MR9600: 1.0.4.205530; MX4200: 1.0.13.210200. | D1440: 5 | E1440: MEDIUM | F1440: 2 | G1440: 2 | H1440: MEDIUM | I1440: 9 | J1440: NO | K1440: 2026-02-26 00:15 | L1440: CHECK_VENDOR | M1440: See CVE details | N1440: P4 | O1440: CVE - IP enrichment n/a | P1440: 0 | Q1440: 0 | R1440: T1059:Command and Scripting Interpreter | S1440: 1 | T1440: LOW (40%) | U1440: UNLIKELY | V1440: CHECK_VENDOR | W1440: https://nvd.nist.gov/vuln/detail/CVE-2026-27849 | X1440: NONE | Y1440: 0 | AA1440: https://nvd.nist.gov/vuln/detail/CVE-2026-27849
A1441: CVE | B1441: CVE-2026-3189 | C1441: A weakness has been identified in feiyuchuixue sz-boot-parent up to 1.3.2-beta. This vulnerability affects unknown code of the file /api/admin/common/files/download. Executing a manipulation of the argument url can lead to server-side request forgery. The attack can be executed remotely. Attacks of this nature are highly complex. It is stated that the exploitability is difficult. Upgrading to version 1.3.3-beta is able to resolve this issue. This patch is called aefaabfd7527188bfba3c8c9eee17c316 | D1441: 3.1 | E1441: LOW | F1441: 2 | G1441: 1 | H1441: LOW | I1441: 5.1 | J1441: NO | K1441: 2026-02-26 00:15 | L1441: CHECK_VENDOR | M1441: See CVE details | N1441: P4 | O1441: CVE - IP enrichment n/a | P1441: 0 | Q1441: 0 | R1441: T1090:Proxy | S1441: 1 | T1441: LOW (40%) | U1441: UNLIKELY | V1441: CHECK_VENDOR | W1441: https://nvd.nist.gov/vuln/detail/CVE-2026-3189 | X1441: NONE | Y1441: 0 | AA1441: https://nvd.nist.gov/vuln/detail/CVE-2026-3189
... A1561: MAL_URL | B1561: 3785687 | C1561: Malware Host [online]: http://118.107.41.238:808/linux_amd64 | Threat: malware_download | Tags: Kaiji,mirai,opendir | D1561: 7.5 | E1561: HIGH | F1561: 3 | G1561: 2 | H1561: HIGH | I1561: 13.5 | J1561: NO | K1561: 2026-02-25 20:23:57 | L1561: Block URL | M1561: Network/Web Proxy | N1561: P3 | O1561: URL IOC - check host IP separately | P1561: 0 | Q1561: 0 | R1561: T1189:Drive-by Compromise | T1566:Phishing | S1561: 1 | T1561: LOW (40%) | U1561: YES | V1561: Block URL | W1561: https://urlhaus.abuse.ch/url/3785687/ | X1561: NONE | Y1561: 0 | AA1561: https://urlhaus.abuse.ch/url/3785687/
A1562: PHISH | C1562: Phishing site targeting: www.roblox.com.ml | URL: https://www.roblox.com.ml/users/5374857739/profile | D1562: 6 | E1562: MEDIUM | F1562: 3 | G1562: 1 | H1562: MEDIUM | I1562: 9 | J1562: NO | K1562: 2026-02-25T22:13:13+00:00 | L1562: Block URL | M1562: Email users / www.roblox.com.ml | N1562: P4 | O1562: Phishing URL | P1562: 0 | Q1562: 0 | R1562: T1566:Phishing | T1566.002:Spearphishing Link | S1562: 1 | T1562: LOW (40%) | U1562: NONE | V1562: NONE | W1562: https://www.roblox.com.ml/users/5374857739/profile | X1562: NONE | Y1562: 0 | AA1562: https://www.roblox.com.ml/users/5374857739/profile
A1563: PHISH | C1563: Phishing site targeting: chhayajat.github.io | URL: http://chhayajat.github.io/Netflix-Clone | D1563: 6 | E1563: MEDIUM | F1563: 3 | G1563: 1 | H1563: MEDIUM | I1563: 9 | J1563: NO | K1563: 2026-02-25T22:13:13+00:00 | L1563: Block URL | M1563: Email users / chhayajat.github.io | N1563: P4 | O1563: Phishing URL | P1563: 0 | Q1563: 0 | R1563: T1566:Phishing | T1566.002:Spearphishing Link | S1563: 1 | T1563: LOW (40%) | U1563: NONE | V1563: NONE | W1563: http://chhayajat.github.io/Netflix-Clone | X1563: NONE | Y1563: 0 | AA1563: http://chhayajat.github.io/Netflix-Clone
A1564: PHISH | C1564: Phishing site targeting: meetbatra.github.io | URL: http://meetbatra.github.io/netflix-clone | D1564: 6 | E1564: MEDIUM | F1564: 3 | G1564: 1 | H1564: MEDIUM | I1564: 9 | J1564: NO | K1564: 2026-02-25T22:13:13+00:00 | L1564: Block URL | M1564: Email users / meetbatra.github.io | N1564: P4 | O1564: Phishing URL | P1564: 0 | Q1564: 0 | R1564: T1566:Phishing | T1566.002:Spearphishing Link | S1564: 1 | T1564: LOW (40%) | U1564: NONE | V1564: NONE | W1564: http://meetbatra.github.io/netflix-clone | X1564: NONE | Y1564: 0 | AA1564: http://meetbatra.github.io/netflix-clone
A1565: PHISH | C1565: Phishing site targeting: ashutoshp-dev.github.io | URL: http://ashutoshp-dev.github.io/NetFlix-Home-UI-Clone | D1565: 6 | E1565: MEDIUM | F1565: 3 | G1565: 1 | H1565: MEDIUM | I1565: 9 | J1565: NO | K1565: 2026-02-25T22:13:13+00:00 | L1565: Block URL | M1565: Email users / ashutoshp-dev.github.io | N1565: P4 | O1565: Phishing URL | P1565: 0 | Q1565: 0 | R1565: T1566:Phishing | T1566.002:Spearphishing Link | S1565: 1 | T1565: LOW (40%) | U1565: NONE | V1565: NONE | W1565: http://ashutoshp-dev.github.io/NetFlix-Home-UI-Clone | X1565: NONE | Y1565: 0 | AA1565: http://ashutoshp-dev.github.io/NetFlix-Home-UI-Clone
A1566: PHISH | C1566: Phishing site targeting: lzrstbg6gtre5.af849df.workers.dev | URL: http://lzrstbg6gtre5.af849df.workers.dev/ | D1566: 6 | E1566: MEDIUM | F1566: 3 | G1566: 1 | H1566: MEDIUM | I1566: 9 | J1566: NO | K1566: 2026-02-25T22:13:13+00:00 | L1566: Block URL | M1566: Email users / lzrstbg6gtre5.af849df.workers.dev | N1566: P4 | O1566: Phishing URL | P1566: 0 | Q1566: 0 | R1566: T1566:Phishing | T1566.002:Spearphishing Link | S1566: 1 | T1566: LOW (40%) | U1566: NONE | V1566: NONE | W1566: http://lzrstbg6gtre5.af849df.workers.dev/ | X1566: NONE | Y1566: 0 | AA1566: http://lzrstbg6gtre5.af849df.workers.dev/
A1567: PHISH | C1567: Phishing site targeting: www.e135k.xyz | URL: http://www.e135k.xyz/ | D1567: 6 | E1567: MEDIUM | F1567: 3 | G1567: 1 | H1567: MEDIUM | I1567: 9 | J1567: NO | K1567: 2026-02-25T22:13:13+00:00 | L1567: Block URL | M1567: Email users / www.e135k.xyz | N1567: P4 | O1567: Phishing URL | P1567: 0 | Q1567: 0 | R1567: T1566:Phishing | T1566.002:Spearphishing Link | S1567: 1 | T1567: LOW (40%) | U1567: NONE | V1567: NONE | W1567: http://www.e135k.xyz/ | X1567: NONE | Y1567: 0 | AA1567: http://www.e135k.xyz/
A1568: PHISH | C1568: Phishing site targeting: chaitanybhute.github.io | URL: http://chaitanybhute.github.io/Netflix_Frontend | D1568: 6 | E1568: MEDIUM | F1568: 3 | G1568: 1 | H1568: MEDIUM | I1568: 9 | J1568: NO | K1568: 2026-02-25T22:13:13+00:00 | L1568: Block URL | M1568: Email users / chaitanybhute.github.io | N1568: P4 | O1568: Phishing URL | P1568: 0 | Q1568: 0 | R1568: T1566:Phishing | T1566.002:Spearphishing Link | S1568: 1 | T1568: LOW (40%) | U1568: NONE | V1568: NONE | W1568: http://chaitanybhute.github.io/Netflix_Frontend | X1568: NONE | Y1568: 0 | AA1568: http://chaitanybhute.github.io/Netflix_Frontend
A1569: PHISH | C1569: Phishing site targeting: swisspost.photocollect.io | URL: https://swisspost.photocollect.io/auth/login | D1569: 6 | E1569: MEDIUM | F1569: 3 | G1569: 1 | H1569: MEDIUM | I1569: 9 | J1569: NO | K1569: 2026-02-25T22:13:13+00:00 | L1569: Block URL | M1569: Email users / swisspost.photocollect.io | N1569: P4 | O1569: Phishing URL | P1569: 0 | Q1569: 0 | R1569: T1566:Phishing | T1566.002:Spearphishing Link | S1569: 1 | T1569: LOW (40%) | U1569: NONE | V1569: NONE | W1569: https://swisspost.photocollect.io/auth/login | X1569: NONE | Y1569: 0 | AA1569: https://swisspost.photocollect.io/auth/login
A1570: PHISH | C1570: Phishing site targeting: swisspost.photocollect.io | URL: https://swisspost.photocollect.io/ | D1570: 6 | E1570: MEDIUM | F1570: 3 | G1570: 1 | H1570: MEDIUM | I1570: 9 | J1570: NO | K1570: 2026-02-25T22:13:13+00:00 | L1570: Block URL | M1570: Email users / swisspost.photocollect.io | N1570: P4 | O1570: Phishing URL | P1570: 0 | Q1570: 0 | R1570: T1566:Phishing | T1566.002:Spearphishing Link | S1570: 1 | T1570: LOW (40%) | U1570: NONE | V1570: NONE | W1570: https://swisspost.photocollect.io/ | X1570: NONE | Y1570: 0 | AA1570: https://swisspost.photocollect.io/
A1571: PHISH | C1571: Phishing site targeting: kucoin_x_logi.godaddysites.com | URL: https://kucoin_x_logi.godaddysites.com/ | D1571: 6 | E1571: MEDIUM | F1571: 3 | G1571: 1 | H1571: MEDIUM | I1571: 9 | J1571: NO | K1571: 2026-02-25T22:13:13+00:00 | L1571: Block URL | M1571: Email users / kucoin_x_logi.godaddysites.com | N1571: P4 | O1571: Phishing URL | P1571: 0 | Q1571: 0 | R1571: T1566:Phishing | T1566.002:Spearphishing Link | S1571: 1 | T1571: LOW (40%) | U1571: NONE | V1571: NONE | W1571: https://kucoin_x_logi.godaddysites.com/ | X1571: NONE | Y1571: 0 | AA1571: https://kucoin_x_logi.godaddysites.com/
A1572: PHISH | C1572: Phishing site targeting: roblox.com.ge | URL: https://roblox.com.ge/users/4587284650/profile | D1572: 6 | E1572: MEDIUM | F1572: 3 | G1572: 1 | H1572: MEDIUM | I1572: 9 | J1572: NO | K1572: 2026-02-25T22:13:13+00:00 | L1572: Block URL | M1572: Email users / roblox.com.ge | N1572: P4 | O1572: Phishing URL | P1572: 0 | Q1572: 0 | R1572: T1566:Phishing | T1566.002:Spearphishing Link | S1572: 1 | T1572: LOW (40%) | U1572: NONE | V1572: NONE | W1572: https://roblox.com.ge/users/4587284650/profile | X1572: NONE | Y1572: 0 | AA1572: https://roblox.com.ge/users/4587284650/profile
A1573: PHISH | C1573: Phishing site targeting: www.robiox.com.ua | URL: https://www.robiox.com.ua/communities/9764817946/KHMER | D1573: 6 | E1573: MEDIUM | F1573: 3 | G1573: 1 | H1573: MEDIUM | I1573: 9 | J1573: NO | K1573: 2026-02-25T22:13:13+00:00 | L1573: Block URL | M1573: Email users / www.robiox.com.ua | N1573: P4 | O1573: Phishing URL | P1573: 0 | Q1573: 0 | R1573: T1566:Phishing | T1566.002:Spearphishing Link | S1573: 1 | T1573: LOW (40%) | U1573: NONE | V1573: NONE | W1573: https://www.robiox.com.ua/communities/9764817946/KHMER | X1573: NONE | Y1573: 0 | AA1573: https://www.robiox.com.ua/communities/9764817946/KHMER
... A1591: PHISH | C1591: Phishing site targeting: www.roblox.com.py | URL: https://www.roblox.com.py/upgrades/robux?ctx=navpopover | D1591: 6 | E1591: MEDIUM | F1591: 3 | G1591: 1 | H1591: MEDIUM | I1591: 9 | J1591: NO | K1591: 2026-02-25T22:13:13+00:00 | L1591: Block URL | M1591: Email users / www.roblox.com.py | N1591: P4 | O1591: Phishing URL | P1591: 0 | Q1591: 0 | R1591: T1566:Phishing | T1566.002:Spearphishing Link | S1591: 1 | T1591: LOW (40%) | U1591: NONE | V1591: NONE | W1591: https://www.roblox.com.py/upgrades/robux?ctx=navpopover | X1591: NONE | Y1591: 0 | AA1591: https://www.roblox.com.py/upgrades/robux?ctx=navpopover
A1592: OTX_PULSE | B1592: 699f5536e9f0860107bbaba7 | C1592: Unmasking Agent Tesla: A Deep Dive into a Multi-Stage Campaign: This analysis examines a sophisticated multi-stage infection chain utilizing Agent Tesla malware. The attack begins with a phishing email containing a RAR file, which includes an obfuscated JSE file. This initial stage triggers a series of script-based evasions, leading to the download and decryption of a PowerShell script. The malware then employs process hollowing to inject its payload into a legitimate Windows process, evading de | D1592: 7 | E1592: HIGH | F1592: 3 | G1592: 2 | H1592: HIGH | I1592: 13 | J1592: NO | K1592: 2026-02-25T20:01:58.886000 | L1592: SEE_PULSE | M1592: credential harvesting, smtp, data exfiltration, anti-analysis, phishing, process hollowing, in-memory execution, agent tesla, multi-stage attack | N1592: P3 | O1592: OTX Pulse - check IP IOCs separately | P1592: 0 | Q1592: 0 | R1592: See OTX pulse tags | S1592: 1 | T1592: LOW (40%) | U1592: NONE | V1592: NONE | W1592: NONE | X1592: NONE | Y1592: 0 | AA1592: https://www.fortinet.com/blog/threat-research/unmasking-agent-tesla-deep-dive-into-multi-stage-campaign
A1593: OTX_PULSE | B1593: 6894566bd94b79b7fbdbade1 | C1593: Infrastructure of Interest: Medium Confidence InfoStealer: These indicators of compromise (IOCs) were identified through LevelBlue Labs' proprietary collection and threat hunting processes, leveraging AI-driven heuristics to detect anomalous patterns, behavioral analysis of malicious activity, and cross-referenced intelligence from endpoint telemetry and external sources. The IOCs included in this pulse are associated with infostealer malware, designed to harvest sensitive data such as credentia | D1593: 7 | E1593: HIGH | F1593: 3 | G1593: 2 | H1593: HIGH | I1593: 13 | J1593: NO | K1593: 2025-08-07T07:31:55.617000 | L1593: SEE_PULSE | M1593: Various | N1593: P3 | O1593: OTX Pulse - check IP IOCs separately | P1593: 0 | Q1593: 0 | R1593: See OTX pulse tags | S1593: 1 | T1593: LOW (40%) | U1593: NONE | V1593: NONE | W1593: NONE | X1593: NONE | Y1593: 0 | AA1593: https://otx.alienvault.com
A1594: OTX_PULSE | B1594: 689455e11e25236fe810364b | C1594: Infrastructure of Interest: Medium Confidence Command And Control: These indicators of compromise (IOCs) were identified through LevelBlue Labs' proprietary collection and threat hunting processes, leveraging AI-driven heuristics to detect anomalous patterns, behavioral analysis of malicious activity, and cross-referenced intelligence from endpoint telemetry and external sources. The IOCs included in this pulse are associated with command and control (C2) infrastructure, facilitating malware com | D1594: 7 | E1594: HIGH | F1594: 3 | G1594: 2 | H1594: HIGH | I1594: 13 | J1594: NO | K1594: 2025-08-07T07:29:37.542000 | L1594: SEE_PULSE | M1594: Various | N1594: P3 | O1594: OTX Pulse - check IP IOCs separately | P1594: 0 | Q1594: 0 | R1594: See OTX pulse tags | S1594: 1 | T1594: LOW (40%) | U1594: NONE | V1594: NONE | W1594: NONE | X1594: NONE | Y1594: 0 | AA1594: https://otx.alienvault.com
A1595: OTX_PULSE | B1595: 689453a1603f3d4b93557f2a | C1595: Infrastructure of Interest: Medium Confidence Phishing: These indicators of compromise (IOCs) were identified through LevelBlue Labs' proprietary collection and threat hunting processes, leveraging AI-driven heuristics to detect anomalous patterns, behavioral analysis of malicious activity, and cross-referenced intelligence from endpoint telemetry and external sources. The IOCs included in this pulse are associated with phishing campaigns, targeting credential theft and fraudulent resource acces | D1595: 7 | E1595: HIGH | F1595: 3 | G1595: 2 | H1595: HIGH | I1595: 13 | J1595: NO | K1595: 2025-08-07T07:20:01.253000 | L1595: SEE_PULSE | M1595: Various | N1595: P3 | O1595: OTX Pulse - check IP IOCs separately | P1595: 0 | Q1595: 0 | R1595: See OTX pulse tags | S1595: 1 | T1595: LOW (40%) | U1595: NONE | V1595: NONE | W1595: NONE | X1595: NONE | Y1595: 0 | AA1595: https://otx.alienvault.com
A1596: OTX_PULSE | B1596: 69778aef872cffc134e67ace | C1596: Chrome Extensions: Are you getting more than you bargained for?: This analysis reveals the hidden dangers of certain Chrome extensions available on the Google Chrome Web Store. Despite the store's vetting process, some malicious extensions have slipped through, compromising user security. The study examines four examples of extensions with combined user bases exceeding 100,000, showcasing various security risks. These include undisclosed clipboard access to remote domains, data exfiltration, rem | D1596: 7 | E1596: HIGH | F1596: 3 | G1596: 2 | H1596: HIGH | I1596: 13 | J1596: NO | K1596: 2026-01-26T15:40:31.078000 | L1596: SEE_PULSE | M1596: data exfiltration, malicious extensions, xss vulnerability, security risks, cve-2020-28707, search hijacking, chrome extensions, remote code execution, clipboard access | N1596: P3 | O1596: OTX Pulse - check IP IOCs separately | P1596: 0 | Q1596: 0 | R1596: See OTX pulse tags | S1596: 1 | T1596: LOW (40%) | U1596: NONE | V1596: NONE | W1596: NONE | X1596: NONE | Y1596: 0 | AA1596: https://www.security.com/threat-intelligence/chrome-extensions-are-you-getting-more-you-bargained
A1597: OTX_PULSE | B1597: 69777a203745e70e7425106f | C1597: Malware MoonPeak Executed via LNK Files: In January 2026, IIJ observed malicious LNK files targeting Korean users to execute the MoonPeak malware, attributed to North Korean threat actors. The infection chain begins with a LNK file that runs an obfuscated PowerShell script, which checks for analysis environments, creates additional scripts, and sets up persistence. The second stage downloads and executes a payload from GitHub, which is actually the MoonPeak malware. MoonPeak is obfuscated using | D1597: 7 | E1597: HIGH | F1597: 3 | G1597: 2 | H1597: HIGH | I1597: 13 | J1597: NO | K1597: 2026-01-26T14:28:48.027000 | L1597: SEE_PULSE | M1597: lots, korea, persistence, github, lnk files, xenorat, powershell, moonpeak, confuserex | N1597: P3 | O1597: OTX Pulse - check IP IOCs separately | P1597: 0 | Q1597: 0 | R1597: See OTX pulse tags | S1597: 1 | T1597: LOW (40%) | U1597: NONE | V1597: NONE | W1597: NONE | X1597: NONE | Y1597: 0 | AA1597: https://sect.iij.ad.jp/blog/2026/01/dprk-moonpeak-executed-via-malicious-lnk-file
A1598: OTX_PULSE | B1598: 699ee10d4bfa4e5fcf71399d | C1598: Inside the Fix: Analysis of In-the-Wild Exploit of CVE-2026-21513: This analysis examines CVE-2026-21513, a security bypass vulnerability in Microsoft's MSHTML framework, patched in February 2026. The flaw, actively exploited by Russian state-sponsored actor APT28, affects all Windows versions and has a CVSS score of 8.8. Using PatchDiff-AI, researchers identified the root cause in ieframe.dll's hyperlink navigation handling, allowing arbitrary file execution outside the browser's security conte | D1598: 7 | E1598: HIGH | F1598: 3 | G1598: 2 | H1598: HIGH | I1598: 13 | J1598: NO | K1598: 2026-02-25T11:46:21.970000 | L1598: SEE_PULSE | M1598: exploit, patchdiff-ai, windows, ieframe.dll, cve-2026-21513, shellexecuteexw, mshtml, zero-day | N1598: P3 | O1598: OTX Pulse - check IP IOCs separately | P1598: 0 | Q1598: 0 | R1598: See OTX pulse tags | S1598: 1 | T1598: LOW (40%) | U1598: NONE | V1598: NONE | W1598: NONE | X1598: NONE | Y1598: 0 | AA1598: https://www.akamai.com/blog/security-research/2026/feb/inside-the-fix-cve-2026-21513-mshtml-exploit-analysis
A1599: OTX_PULSE | B1599: 689456eba72f618e9d63e8dd | C1599: Infrastructure of Interest: Medium Confidence FastFlux: These indicators of compromise (IOCs) were identified through LevelBlue Labs' proprietary collection and threat hunting processes, leveraging AI-driven heuristics to detect anomalous DNS patterns, behavioral analysis of rapid IP rotation, and cross-referenced intelligence from global sinkhole data and network telemetry. The IOCs included in this pulse are associated with Fastflux networks, characterized by constantly changing IP addresses a | D1599: 7 | E1599: HIGH | F1599: 3 | G1599: 2 | H1599: HIGH | I1599: 13 | J1599: NO | K1599: 2025-08-07T07:34:03.778000 | L1599: SEE_PULSE | M1599: Various | N1599: P3 | O1599: OTX Pulse - check IP IOCs separately | P1599: 0 | Q1599: 0 | R1599: See OTX pulse tags | S1599: 1 | T1599: LOW (40%) | U1599: NONE | V1599: NONE | W1599: NONE | X1599: NONE | Y1599: 0 | AA1599: https://otx.alienvault.com
A1600: OTX_PULSE | B1600: 699ede794dd30674f7d583d5 | C1600: Mercenary Akula Hits Ukraine-Supporting Financial...: A European financial institution involved in regional development and reconstruction initiatives was targeted by a social engineering attack attributed to the Russia-aligned Mercenary Akula. The attack used a spoofed Ukrainian judicial domain to deliver an email containing a link to a remote access payload. The target was a senior legal and policy advisor involved in procurement. The attack employed a multi-stage extraction process and deploy | D1600: 7 | E1600: HIGH | F1600: 3 | G1600: 2 | H1600: HIGH | I1600: 13 | J1600: NO | K1600: 2026-02-25T11:35:21.172000 | L1600: SEE_PULSE | M1600: remote manipulator system, quasarrat, fire cells group, uac-0050, spearphishing, remote access, cyber espionage, financial theft, remcos, social engineering, davinci group | N1600: P3 | O1600: OTX Pulse - check IP IOCs separately | P1600: 0 | Q1600: 0 | R1600: See OTX pulse tags | S1600: 1 | T1600: LOW (40%) | U1600: NONE | V1600: NONE | W1600: NONE | X1600: NONE | Y1600: 0 | AA1600: https://www.bluevoyant.com/blog/mercenary-akula-hits-financial-institution
A1601: OTX_PULSE | B1601: 699edea96aa1a8d035261fc9 | C1601: The Latest PlugX Variant Executed by STATICPLUGIN: In January 2026, a new variant of the PlugX malware was observed being used in targeted attacks. Analysis suggests involvement of the UNC6384 APT group, linked to Mustang Panda, targeting government agencies in Southeast Asia. The malware uses a browser updater disguise to download and execute a malicious MSI file, leading to PlugX infection. The STATICPLUGIN downloader uses a revoked code-signing certificate from a Chinese company. The PlugX va | D1601: 7 | E1601: HIGH | F1601: 3 | G1601: 2 | H1601: HIGH | I1601: 13 | J1601: NO | K1601: 2026-02-25T11:36:09.887000 | L1601: SEE_PULSE | M1601: rc4-encryption, apt, targeted-attack, plugx, staticplugin, valleyrat, dll-sideloading, code-signing | N1601: P3 | O1601: OTX Pulse - check IP IOCs separately | P1601: 0 | Q1601: 0 | R1601: See OTX pulse tags | S1601: 1 | T1601: LOW (40%) | U1601: NONE | V1601: NONE | W1601: NONE | X1601: NONE | Y1601: 0 | AA1601: https://sect.iij.ad.jp/blog/2026/02/plugx-executed-via-staticplugin/
A1602: OTX_PULSE | B1602: 69772b44fe2e1c30ec984e32 | C1602: A $6,000 Russian Malware Toolkit with Chrome Web Store Guarantee: A new malware-as-a-service toolkit called 'Stanley' is being sold on Russian cybercrime forums for $2,000 to $6,000. It provides a turnkey website-spoofing operation disguised as a Chrome extension, with the premium tier promising guaranteed publication on the Chrome Web Store. The toolkit allows full-page website spoofing, element injection, push notifications, and backup domain rotation. It uses victims' IP addresses for trackin | D1602: 7 | E1602: HIGH | F1602: 3 | G1602: 2 | H1602: HIGH | I1602: 13 | J1602: NO | K1602: 2026-01-26T08:52:20.218000 | L1602: SEE_PULSE | M1602: chrome web store, phishing, credential theft, browser extension, malware-as-service, website spoofing, russian cybercrime, stanley | N1602: P3 | O1602: OTX Pulse - check IP IOCs separately | P1602: 0 | Q1602: 0 | R1602: See OTX pulse tags | S1602: 1 | T1602: LOW (40%) | U1602: NONE | V1602: NONE | W1602: NONE | X1602: NONE | Y1602: 0 | AA1602: https://www.varonis.com/blog/stanley-malware-kit
A1603: OTX_PULSE | B1603: 699e18510d30e21605243f81 | C1603: Developer-targeting campaign using malicious Next.js repositories: A coordinated campaign is targeting developers through malicious repositories disguised as legitimate Next.js projects and technical assessment materials. The attack uses multiple entry points that lead to runtime retrieval and local execution of attacker-controlled JavaScript, transitioning into staged command-and-control. The campaign employs three main execution paths: Visual Studio Code workspace automation, build-time execut | D1603: 7 | E1603: HIGH | F1603: 3 | G1603: 2 | H1603: HIGH | I1603: 13 | J1603: NO | K1603: 2026-02-24T21:29:53.984000 | L1603: SEE_PULSE | M1603: next.js, command-and-control, javascript, remote code execution, node.js, developer-targeting, visual studio code, environment variable exfiltration | N1603: P3 | O1603: OTX Pulse - check IP IOCs separately | P1603: 0 | Q1603: 0 | R1603: See OTX pulse tags | S1603: 1 | T1603: LOW (40%) | U1603: NONE | V1603: NONE | W1603: NONE | X1603: NONE | Y1603: 0 | AA1603: https://www.microsoft.com/en-us/security/blog/2026/02/24/c2-developer-targeting-campaign/
... A1641: THREATFOX_IOC | B1641: 1754850 | C1641: ip:port IOC: | Malware: DCRat | Confidence: 100% | D1641: 7.5 | E1641: HIGH | F1641: 3 | G1641: 2 | H1641: HIGH | I1641: 13.5 | J1641: NO | K1641: 2026-02-25 20:05:15 UTC | L1641: Block IOC | M1641: botnet_cc | N1641: P3 | O1641: Classification: skipped | Context: Skipped (20/run IOC cap) | Name: N/A | P1641: 0 | Q1641: 0 | R1641: T1071:Application Layer Protocol | T1102:Web Service | S1641: 1 | T1641: LOW (40%) | U1641: NONE | V1641: NONE | W1641: NONE | X1641: NONE | Y1641: 0 | AA1641: https://threatfox.abuse.ch/ioc/1754850/
A1642: THREATMINER | B1642: d41d8cd98f00 | C1642: Malicious domain: | IP: 91.224.92.78 | Last seen: | D1642: 6.5 | E1642: MEDIUM | F1642: 2 | G1642: 2 | H1642: MEDIUM | I1642: 10.5 | J1642: NO | L1642: Block domain | M1642: DNS/Network | N1642: P4 | O1642: Domain IOC - check IP separately | P1642: 0 | Q1642: 0 | R1642: T1071.001:Web Protocols | T1568:Dynamic Resolution | S1642: 1 | T1642: LOW (40%) | U1642: NONE | V1642: NONE | W1642: NONE | X1642: NONE | Y1642: 0 | AA1642: https://www.threatminer.org/domain.php?q=
A1643: THREATMINER | B1643: d41d8cd98f00 | C1643: Malicious domain: | IP: 91.224.92.190 | Last seen: | D1643: 6.5 | E1643: MEDIUM | F1643: 2 | G1643: 2 | H1643: MEDIUM | I1643: 10.5 | J1643: NO | L1643: Block domain | M1643: DNS/Network | N1643: P4 | O1643: Domain IOC - check IP separately | P1643: 0 | Q1643: 0 | R1643: T1071.001:Web Protocols | T1568:Dynamic Resolution | S1643: 1 | T1643: LOW (40%) | U1643: NONE | V1643: NONE | W1643: NONE | X1643: NONE | Y1643: 0 | AA1643: https://www.threatminer.org/domain.php?q=
A1644: THREATMINER | B1644: d41d8cd98f00 | C1644: Malicious domain: | IP: 103.218.241.106 | Last seen: | D1644: 6.5 | E1644: MEDIUM | F1644: 2 | G1644: 2 | H1644: MEDIUM | I1644: 10.5 | J1644: NO | L1644: Block domain | M1644: DNS/Network | N1644: P4 | O1644: Domain IOC - check IP separately | P1644: 0 | Q1644: 0 | R1644: T1071.001:Web Protocols | T1568:Dynamic Resolution | S1644: 1 | T1644: LOW (40%) | U1644: NONE | V1644: NONE | W1644: NONE | X1644: NONE | Y1644: 0 | AA1644: https://www.threatminer.org/domain.php?q=
A1645: THREATMINER | B1645: d41d8cd98f00 | C1645: Malicious domain: | IP: 185.91.69.217 | Last seen: | D1645: 6.5 | E1645: MEDIUM | F1645: 2 | G1645: 2 | H1645: MEDIUM | I1645: 10.5 | J1645: NO | L1645: Block domain | M1645: DNS/Network | N1645: P4 | O1645: Domain IOC - check IP separately | P1645: 0 | Q1645: 0 | R1645: T1071.001:Web Protocols | T1568:Dynamic Resolution | S1645: 1 | T1645: LOW (40%) | U1645: NONE | V1645: NONE | W1645: NONE | X1645: NONE | Y1645: 0 | AA1645: https://www.threatminer.org/domain.php?q=
A1646: THREATMINER | B1646: d41d8cd98f00 | C1646: Malicious domain: | IP: 2.57.121.25 | Last seen: | D1646: 6.5 | E1646: MEDIUM | F1646: 2 | G1646: 2 | H1646: MEDIUM | I1646: 10.5 | J1646: NO | L1646: Block domain | M1646: DNS/Network | N1646: P4 | O1646: Domain IOC - check IP separately | P1646: 0 | Q1646: 0 | R1646: T1071.001:Web Protocols | T1568:Dynamic Resolution | S1646: 1 | T1646: LOW (40%) | U1646: NONE | V1646: NONE | W1646: NONE | X1646: NONE | Y1646: 0 | AA1646: https://www.threatminer.org/domain.php?q=
A1647: THREATMINER | B1647: d41d8cd98f00 | C1647: Malicious domain: | IP: 2.57.122.238 | Last seen: | D1647: 6.5 | E1647: MEDIUM | F1647: 2 | G1647: 2 | H1647: MEDIUM | I1647: 10.5 | J1647: NO | L1647: Block domain | M1647: DNS/Network | N1647: P4 | O1647: Domain IOC - check IP separately | P1647: 0 | Q1647: 0 | R1647: T1071.001:Web Protocols | T1568:Dynamic Resolution | S1647: 1 | T1647: LOW (40%) | U1647: NONE | V1647: NONE | W1647: NONE | X1647: NONE | Y1647: 0 | AA1647: https://www.threatminer.org/domain.php?q=
A1648: THREATMINER | B1648: d41d8cd98f00 | C1648: Malicious domain: | IP: 45.148.10.141 | Last seen: | D1648: 6.5 | E1648: MEDIUM | F1648: 2 | G1648: 2 | H1648: MEDIUM | I1648: 10.5 | J1648: NO | L1648: Block domain | M1648: DNS/Network | N1648: P4 | O1648: Domain IOC - check IP separately | P1648: 0 | Q1648: 0 | R1648: T1071.001:Web Protocols | T1568:Dynamic Resolution | S1648: 1 | T1648: LOW (40%) | U1648: NONE | V1648: NONE | W1648: NONE | X1648: NONE | Y1648: 0 | AA1648: https://www.threatminer.org/domain.php?q=
A1649: THREATMINER | B1649: d41d8cd98f00 | C1649: Malicious domain: | IP: 45.148.10.147 | Last seen: | D1649: 6.5 | E1649: MEDIUM | F1649: 2 | G1649: 2 | H1649: MEDIUM | I1649: 10.5 | J1649: NO | L1649: Block domain | M1649: DNS/Network | N1649: P4 | O1649: Domain IOC - check IP separately | P1649: 0 | Q1649: 0 | R1649: T1071.001:Web Protocols | T1568:Dynamic Resolution | S1649: 1 | T1649: LOW (40%) | U1649: NONE | V1649: NONE | W1649: NONE | X1649: NONE | Y1649: 0 | AA1649: https://www.threatminer.org/domain.php?q=
A1650: THREATMINER | B1650: d41d8cd98f00 | C1650: Malicious domain: | IP: 45.148.10.151 | Last seen: | D1650: 6.5 | E1650: MEDIUM | F1650: 2 | G1650: 2 | H1650: MEDIUM | I1650: 10.5 | J1650: NO | L1650: Block domain | M1650: DNS/Network | N1650: P4 | O1650: Domain IOC - check IP separately | P1650: 0 | Q1650: 0 | R1650: T1071.001:Web Protocols | T1568:Dynamic Resolution | S1650: 1 | T1650: LOW (40%) | U1650: NONE | V1650: NONE | W1650: NONE | X1650: NONE | Y1650: 0 | AA1650: https://www.threatminer.org/domain.php?q=
A1651: THREATMINER | B1651: d41d8cd98f00 | C1651: Malicious domain: | IP: 45.148.10.152 | Last seen: | D1651: 6.5 | E1651: MEDIUM | F1651: 2 | G1651: 2 | H1651: MEDIUM | I1651: 10.5 | J1651: NO | L1651: Block domain | M1651: DNS/Network | N1651: P4 | O1651: Domain IOC - check IP separately | P1651: 0 | Q1651: 0 | R1651: T1071.001:Web Protocols | T1568:Dynamic Resolution | S1651: 1 | T1651: LOW (40%) | U1651: NONE | V1651: NONE | W1651: NONE | X1651: NONE | Y1651: 0 | AA1651: https://www.threatminer.org/domain.php?q=
A1652: THREATMINER | B1652: d41d8cd98f00 | C1652: Malicious domain: | IP: 45.148.10.157 | Last seen: | D1652: 6.5 | E1652: MEDIUM | F1652: 2 | G1652: 2 | H1652: MEDIUM | I1652: 10.5 | J1652: NO | L1652: Block domain | M1652: DNS/Network | N1652: P4 | O1652: Domain IOC - check IP separately | P1652: 0 | Q1652: 0 | R1652: T1071.001:Web Protocols | T1568:Dynamic Resolution | S1652: 1 | T1652: LOW (40%) | U1652: NONE | V1652: NONE | W1652: NONE | X1652: NONE | Y1652: 0 | AA1652: https://www.threatminer.org/domain.php?q=
A1653: THREATMINER | B1653: d41d8cd98f00 | C1653: Malicious domain: | IP: 45.249.244.185 | Last seen: | D1653: 6.5 | E1653: MEDIUM | F1653: 2 | G1653: 2 | H1653: MEDIUM | I1653: 10.5 | J1653: NO | L1653: Block domain | M1653: DNS/Network | N1653: P4 | O1653: Domain IOC - check IP separately | P1653: 0 | Q1653: 0 | R1653: T1071.001:Web Protocols | T1568:Dynamic Resolution | S1653: 1 | T1653: LOW (40%) | U1653: NONE | V1653: NONE | W1653: NONE | X1653: NONE | Y1653: 0 | AA1653: https://www.threatminer.org/domain.php?q=
... A1671: THREATMINER | B1671: d41d8cd98f00 | C1671: Malicious domain: | IP: 2.57.121.112 | Last seen: | D1671: 6.5 | E1671: MEDIUM | F1671: 2 | G1671: 2 | H1671: MEDIUM | I1671: 10.5 | J1671: NO | L1671: Block domain | M1671: DNS/Network | N1671: P4 | O1671: Domain IOC - check IP separately | P1671: 0 | Q1671: 0 | R1671: T1071.001:Web Protocols | T1568:Dynamic Resolution | S1671: 1 | T1671: LOW (40%) | U1671: NONE | V1671: NONE | W1671: NONE | X1671: NONE | Y1671: 0 | AA1671: https://www.threatminer.org/domain.php?q=
